Workbook

Sheet Part 1
B1: CUB | H1: PAGEIND | N1: INOXWIND | T1: DATAPATTNS | Z1: POLICYBZR | AF1: DALBHARAT | AL1: DLF | AR1: OIL | AY1: NIFTY 50 INDEX | BF1: PORTFOLIO | BL1: WEIGHTS OF INDIVIDUAL STOCK IN THE PORTFOLIO
A2: DATE | B2: DAILY RETURNS(%) | C2: WEEKDAY | D2: WEEKLY RETURN(%) | E2: MONTH NUM | F2: MONTHLY RETURN(%) | H2: DAILY RETURNS(%) | I2: WEEKDAY | J2: WEEKLY RETURN(%) | K2: MONTH NUM | L2: MONTHLY RETURN(%) | N2: DAILY RETURNS(%) | O2: WEEKDAY | P2: WEEKLY RETURN(%) | Q2: MONTH NUM | R2: MONTHLY RETURN(%) | T2: DAILY RETURNS(%) | U2: WEEKDAY | V2: WEEKLY RETURN(%) | W2: MONTH NUM | X2: MONTHLY RETURN(%) | Z2: DAILY RETURNS(%) | AA2: WEEKDAY | AB2: WEEKLY RETURN(%) | AC2: MONTH NUM | AD2: MONTHLY RETURN(%) | AF2: DAILY RETURNS(%) | AG2: WEEKDAY | AH2: WEEKLY RETURN(%) | AI2: MONTH NUMBER | AJ2: MONTHLY RETURNS(%) | AL2: DAILY RETURNS(%) | AM2: WEEKDAY | AN2: WEEKLY RETURN(%) | AO2: MONTH NUMBER | AP2: MONTHLY RETURN(%) | AR2: DAILY RETURNS(%) | AS2: WEEKDAY | AT2: WEEKLY RETURN(%) | AU2: MONTH NUMBER | AV2: MONTHLY RETURN(%) | BL2: CUB | BM2: PAGEIND | BN2: INOXWIND | BO2: DATAPATTNS | BP2: POLICYBZR | BQ2: DALBHARAT | BR2: DLF | BS2: OIL | BV2: On the basis of daily returns | BW2: CUB | BX2: PAGEIND | BY2: INOXWIND | BZ2: DATAPATTNS | CA2: POLICYBZR | CB2: DALBHARAT | CC2: DLF | CD2: OIL
A3: 44742 | C3: 4 | I3: 4 | O3: 4 | U3: 4 | AA3: 4 | AG3: 4 | AM3: 4 | AS3: 4 | AY3: DAILY VARIATION(%)-NIFTY 50 | AZ3: WEEKLY VARIATION(%)-NIFTY 50 | BA3: MONTHLY VARIATION(%)-NIFTY 50 | BF3: DAILY RETURNS(%) | BG3: WEEKLY RETURNS(%) | BH3: MONTHLY RETURNS(%) | BL3: 0.15 | BM3: 0.1 | BN3: 0.12 | BO3: 0.13 | BP3: 0.1 | BQ3: 0.15 | BR3: 0.12 | BS3: 0.13 | BV3: Correlation(Stock vs NIFTY 50) | BW3: =CORREL(B4:B497,AY4:AY497) -> 0.44466894 | BX3: =CORREL(H4:H497,AY4:AY497) -> 0.26450938 | BY3: =CORREL(N4:N497,AY4:AY497) -> 0.18621438 | BZ3: =CORREL(T4:T497,AY4:AY497) -> 0.27667805 | CA3: =CORREL(Z4:Z497,AY4:AY497) -> 0.26421572 | CB3: =CORREL(AF4:AF497,AY4:AY497) -> 0.49556188 | CC3: =CORREL(AL4:AL497,AY4:AY497) -> 0.58882038 | CD3: =CORREL(AR4:AR497,AY4:AY497) -> 0.29604095
A4: 44743 | B4: 1.8038331 | C4: 5 | E4: 44743 | F4: 18.752307 | H4: 3.0107179 | I4: 5 | K4: 44743 | L4: 18.11977 | N4: -1.958307 | O4: 5 | Q4: 44743 | R4: 14.43299 | T4: -0.67135051 | U4: 5 | W4: 44743 | X4: 21.997799 | Z4: 2.635483 | AA4: 5 | AC4: 44743 | AD4: -20.372417 | AF4: 3.3654033 | AG4: 5 | AI4: 44743 | AJ4: 20.559973 | AL4: 3.3418612 | AM4: 5 | AO4: 44743 | AP4: 19.4337 | AR4: -14.970179 | AS4: 5 | AU4: 44743 | AV4: -11.152677 | AY4: -0.17870439 | BA4: 8.927092 | BF4: -0.52736676 | BH4: 11.145446
A5: 44746 | B5: 2.1410114 | C5: 1 | H5: 1.6357388 | I5: 1 | N5: 3.0927835 | O5: 1 | T5: 0.80163471 | U5: 1 | Z5: -0.56967945 | AA5: 1 | AF5: -0.68206655 | AG5: 1 | AL5: 0.4951261 | AM5: 1 | AR5: -5.7049334 | AS5: 1 | AY5: 0.52882006 | BF5: 0.11856799
A6: 44747 | B6: 1.4817492 | C6: 2 | H6: 0.70304809 | I6: 2 | N6: -2.3125 | O6: 2 | T6: 2.3935755 | U6: 2 | Z6: 0.19668206 | AA6: 2 | AF6: -1.2027622 | AG6: 2 | AL6: -0.81601232 | AM6: 2 | AR6: -5.4797917 | AS6: 2 | AY6: -0.15471714 | BF6: -0.64480851 | BV6: On the basis of weekly returns | BW6: CUB | BX6: PAGEIND | BY6: INOXWIND | BZ6: DATAPATTNS | CA6: POLICYBZR | CB6: DALBHARAT | CC6: DLF | CD6: OIL
A7: 44748 | B7: 0.64102564 | C7: 3 | H7: 2.8871323 | I7: 3 | N7: 0.44785669 | O7: 3 | T7: 5.7184192 | U7: 3 | Z7: -2.2702057 | AA7: 3 | AF7: 6.1100657 | AG7: 3 | AL7: 2.3284694 | AM7: 3 | AR7: -8.6044071 | AS7: 3 | AY7: 1.1318177 | BF7: 1.0323371 | BL7: Portfolio Value | BM7: 1000000 | BV7: Correlation(Stock vs NIFTY 50) | BW7: =CORREL(D4:D497,AZ4:AZ497) -> 0.40139814 | BX7: =CORREL(J4:J497,AZ4:AZ497) -> 0.28008765 | BY7: =CORREL(P4:P497,AZ4:AZ497) -> 0.37197175 | BZ7: =CORREL(V4:V497,AZ4:AZ497) -> 0.34040083 | CA7: =CORREL(AB4:AB497,AZ4:AZ497) -> 0.21844661 | CB7: =CORREL(AH4:AH497,AZ4:AZ497) -> 0.53885662 | CC7: =CORREL(AN4:AN497,AZ4:AZ497) -> 0.60912346 | CD7: =CORREL(AT4:AT497,AY4:AY497) -> -0.024498016
A8: 44749 | B8: 2.5831564 | C8: 4 | D8: 8.944006 | H8: 1.0176517 | I8: 4 | J8: 9.5796248 | N8: 3.2484076 | O8: 4 | P8: 2.4005054 | T8: 0.14405071 | U8: 4 | V8: 8.540203 | Z8: -0.4803074 | AA8: 4 | AB8: -0.54978619 | AF8: 5.1863916 | AG8: 4 | AH8: 13.204534 | AL8: 2.2148058 | AM8: 4 | AN8: 7.739047 | AR8: 1.3490241 | AS8: 4 | AT8: -29.801193 | AY8: 0.89494553 | AZ8: 2.2347555 | BF8: 2.068852 | BG8: 2.6788246 | BL8: Company | BM8: Total Market Cap (₹ Cr.) | BN8: Industry | BO8: Weight Assigned | BP8: Investment Amount (₹) | BQ8: Daily Volatility
A9: 44750 | B9: -0.068989307 | C9: 5 | H9: -0.99649432 | I9: 5 | N9: 1.1104257 | O9: 5 | T9: 1.9490794 | U9: 5 | Z9: -1.009126 | AA9: 5 | AF9: -1.3419124 | AG9: 5 | AL9: 1.0388839 | AM9: 5 | AR9: 4.3330501 | AS9: 5 | AY9: 0.54360964 | BF9: 0.6623967 | BL9: CUB | BM9: 13399.5 | BN9: Private Sector Bank | BO9: 0.15 | BP9: =BO9*1000000 -> 150000 | BQ9: 2.05
A10: 44753 | B10: 2.9340697 | C10: 1 | H10: -0.40527175 | I10: 1 | N10: -0.12202563 | O10: 1 | T10: 3.2592593 | U10: 1 | Z10: -1.0105487 | AA10: 1 | AF10: 1.1753217 | AG10: 1 | AL10: 1.6891892 | AM10: 1 | AR10: 1.3029316 | AS10: 1 | AY10: -0.028359 | BF10: 1.2559711 | BL10: PAGEIND | BM10: 50359.74 | BN10: Garments & Apparels | BO10: 0.1 | BP10: =BO10*1000000 -> 100000 | BQ10: 1.49 | BV10: On the basis of monthly returns | BW10: CUB | BX10: PAGEIND | BY10: INOXWIND | BZ10: DATAPATTNS | CA10: POLICYBZR | CB10: DALBHARAT | CC10: DLF | CD10: OIL
A11: 44754 | B11: -0.46948357 | C11: 2 | H11: -0.71487658 | I11: 2 | N11: -2.3824068 | O11: 2 | T11: -1.9471203 | U11: 2 | Z11: 0.34028835 | AA11: 2 | AF11: -0.85143054 | AG11: 2 | AL11: 0.18777986 | AM11: 2 | AR11: -1.6881029 | AS11: 2 | AY11: -0.9724963 | BF11: -0.97153019 | BL11: INOXWIND | BM11: 28650.87 | BN11: Heavy Electrical Equipment | BO11: 0.12 | BP11: =BO11*1000000 -> 120000 | BQ11: 3.46 | BV11: Correlation(Stock vs NIFTY 50) | BW11: =CORREL(F4:F497,BA4:BA497) -> 0.60061112 | BX11: =CORREL(L4:L497,BA4:BA497) -> 0.55434405 | BY11: =CORREL(R4:R497,BA4:BA497) -> 0.42594815 | BZ11: =CORREL(X4:X497,BA4:BA497) -> 0.29513966 | CA11: =CORREL(AD4:AD497,BA4:BA497) -> -0.22921819 | CB11: =CORREL(AJ4:AJ497,BA4:BA497) -> 0.41424883 | CC11: =CORREL(AP4:AP497,BA4:BA497) -> 0.70765904 | CD11: =CORREL(AV4:AV497,BA4:BA497) -> 0.03744721
A12: 44755 | B12: 1.5498652 | C12: 3 | H12: 0.95349493 | I12: 3 | N12: -0.8135169 | O12: 3 | T12: 0.02090301 | U12: 3 | Z12: -0.09817046 | AA12: 3 | AF12: 2.7118173 | AG12: 3 | AL12: 0.18742791 | AM12: 3 | AR12: 1.0902153 | AS12: 3 | AY12: -0.57073289 | BF12: 0.79409953 | BL12: DATAPATTNS | BM12: 13402 | BN12: Aerospace & Defense | BO12: 0.13 | BP12: =BO12*1000000 -> 130000 | BQ12: 3.06
A13: 44756 | B13: -0.2986065 | C13: 4 | D13: 3.6564333 | H13: 0.42448569 | I13: 4 | J13: -0.74964273 | N13: 0.3785489 | O13: 4 | P13: -1.8507094 | T13: 1.6858238 | U13: 4 | V13: 4.9841772 | Z13: -2.6442737 | AA13: 4 | AB13: -4.3699544 | AF13: -2.5082084 | AG13: 4 | AH13: -0.89804907 | AL13: 0.31659232 | AM13: 4 | AN13: 3.4579994 | AR13: -4.0172553 | AS13: 4 | AT13: 0.82129708 | AY13: -0.17536553 | AZ13: -1.2040613 | BF13: -0.86267019 | BG13: 0.84938437 | BL13: POLICYBZR | BM13: 79388.22 | BN13: Financial Technology | BO13: 0.1 | BP13: =BO13*1000000 -> 100000 | BQ13: 2.65
A14: 44757 | B14: 0.86522463 | C14: 5 | H14: 1.5661215 | I14: 5 | N14: -1.9484601 | O14: 5 | T14: -1.8496951 | U14: 5 | Z14: -3.8080382 | AA14: 5 | AF14: 0.57287688 | AG14: 5 | AL14: 1.4632047 | AM14: 5 | AR14: 2.3876404 | AS14: 5 | AY14: 0.69359701 | BF14: 0.0032258037 | BL14: DALBHARAT | BM14: 33664.8 | BN14: Construction Materials | BO14: 0.15 | BP14: =BO14*1000000 -> 150000 | BQ14: 1.8
A15: 44760 | B15: 1.682613 | C15: 1 | H15: -0.66195612 | I15: 1 | N15: 2.5 | O15: 1 | T15: -0.10469742 | U15: 1 | Z15: 0.15262806 | AA15: 1 | AF15: 2.9033038 | AG15: 1 | AL15: -0.12724445 | AM15: 1 | AR15: 1.2620027 | AS15: 1 | AY15: 1.4287317 | BF15: 1.0721351 | BL15: DLF | BM15: 199064.84 | BN15: Realty | BO15: 0.12 | BP15: =BO15*1000000 -> 120000 | BQ15: 2.14
A16: 44761 | B16: 2.5308241 | C16: 2 | H16: -0.7350005 | I16: 2 | N16: 1.6260163 | O16: 2 | T16: 4.1154276 | U16: 2 | Z16: 0.46671112 | AA16: 2 | AF16: 1.6304348 | AG16: 2 | AL16: 1.882786 | AM16: 2 | AR16: 1.1108101 | AS16: 2 | AY16: 0.38117763 | BF16: 1.6978271 | BL16: OIL | BM16: 84559.21 | BN16: Oil Exploration & Production | BO16: 0.13 | BP16: =BO16*1000000 -> 130000 | BQ16: 2.88
A17: 44762 | B17: -0.15822785 | C17: 3 | H17: 0.54844649 | I17: 3 | N17: 0.86153846 | O17: 3 | T17: 0.51674384 | U17: 3 | Z17: -0.58778915 | AA17: 3 | AF17: -0.11883541 | AG17: 3 | AL17: -0.95873281 | AM17: 3 | AR17: 5.8145766 | AS17: 3 | AY17: 1.10339 | BF17: 0.76591458
A18: 44763 | B18: 1.4896989 | C18: 4 | D18: 6.5557404 | H18: 2.5816762 | I18: 4 | J18: 3.3012967 | N18: -0.18303844 | O18: 4 | P18: 2.8284098 | T18: 1.1416745 | U18: 4 | V18: 3.781599 | Z18: 0.54358192 | AA18: 4 | AB18: -3.2574784 | AF18: 1.7747373 | AG18: 4 | AH18: 6.9196584 | AL18: 1.1784512 | AM18: 4 | AN18: 3.4571797 | AR18: 1.6713092 | AS18: 4 | AT18: 12.780899 | AY18: 0.5108696 | AZ18: 4.1822865 | BF18: 1.2873286 | BG18: 4.9338718
A19: 44764 | B19: 2.467208 | C19: 5 | H19: 0.47854365 | I19: 5 | N19: -0.85574572 | O19: 5 | T19: -0.88454683 | U19: 5 | Z19: -1.3373803 | AA19: 5 | AF19: 3.6174704 | AG19: 5 | AL19: -0.12479201 | AM19: 5 | AR19: -2.5902864 | AS19: 5 | AY19: 0.6877343 | BF19: 0.25742524
A20: 44767 | B20: -1.5239256 | C20: 1 | H20: 0.60506214 | I20: 1 | N20: -1.541307 | O20: 1 | T20: -0.97236097 | U20: 1 | Z20: -3.9223226 | AA20: 1 | AF20: -2.8643956 | AG20: 1 | AL20: -0.77745384 | AM20: 1 | AR20: -4.6279724 | AS20: 1 | AY20: -0.52902458 | BF20: -1.9962689
A21: 44768 | B21: 0.40235221 | C21: 2 | H21: 1.2651041 | I21: 2 | N21: 9.6430808 | O21: 2 | T21: -1.7687807 | U21: 2 | Z21: -5.573344 | AA21: 2 | AF21: -0.98725601 | AG21: 2 | AL21: 0.96544004 | AM21: 2 | AR21: -1.0991957 | AS21: 2 | AY21: -0.88479346 | BF21: 0.38162601
A22: 44769 | B22: -0.18495684 | C22: 3 | H22: 2.3021438 | I22: 3 | N22: -3.2552827 | O22: 3 | T22: 5.0732576 | U22: 3 | Z22: -2.9246583 | AA22: 3 | AF22: 2.7371371 | AG22: 3 | AL22: 2.1757206 | AM22: 3 | AR22: 1.3282732 | AS22: 3 | AY22: 0.95821061 | BF22: 1.0232271
A23: 44770 | B23: -0.46324892 | C23: 4 | D23: 0.6558401 | H23: 1.0647021 | I23: 4 | J23: 5.8369251 | N23: 2.7154664 | O23: 4 | P23: 6.3569682 | T23: -1.3357659 | U23: 4 | V23: -0.04620767 | Z23: 0.31655933 | AA23: 4 | AB23: -12.833159 | AF23: 0.56138793 | AG23: 4 | AH23: 2.9582724 | AL23: 3.621321 | AM23: 4 | AN23: 5.9345535 | AR23: -0.16051364 | AS23: 4 | AT23: -7.0485679 | AY23: 1.7293802 | AZ23: 1.9532979 | BF23: 0.71874513 | BG23: 0.39515523
A24: 44771 | B24: -0.18616196 | C24: 5 | H24: 2.3293307 | I24: 5 | N24: 2.0689655 | O24: 5 | T24: 2.5161802 | U24: 5 | Z24: 1.9042437 | AA24: 5 | AF24: 0.90519145 | AG24: 5 | AL24: 1.0340314 | AM24: 5 | AR24: 1.8220793 | AS24: 5 | AY24: 1.350593 | BF24: 1.4675452
A25: 44774 | B25: 0.15542431 | C25: 1 | E25: 44774 | F25: 11.700807 | H25: 0.71573261 | I25: 1 | K25: 44774 | L25: 3.6981846 | N25: 5.9684685 | O25: 1 | Q25: 44774 | R25: 18.756642 | T25: 2.7378728 | U25: 1 | W25: 44774 | X25: 33.834964 | Z25: 7.6775227 | AA25: 1 | AC25: 44774 | AD25: -0.22808409 | AF25: -0.83455756 | AG25: 1 | AI25: 44774 | AJ25: -3.1488369 | AL25: -0.44047156 | AM25: 1 | AO25: 44774 | AP25: 1.4964216 | AR25: 2.0263158 | AS25: 1 | AU25: 44774 | AV25: -0.54165592 | AY25: 1.0595486 | BA25: 2.4178131 | BF25: 2.0201597 | BH25: 8.3883317
A26: 44775 | B26: 1.3345748 | C26: 2 | H26: -0.47803051 | I26: 2 | N26: 3.8788523 | O26: 2 | T26: -5.8251818 | U26: 2 | Z26: 10.948036 | AA26: 2 | AF26: -0.24270315 | AG26: 2 | AL26: -1.977879 | AM26: 2 | AR26: -1.7539335 | AS26: 2 | AY26: 0.031141779 | BF26: 0.45361315
A27: 44776 | B27: -0.4287902 | C27: 3 | H27: -1.9798928 | I27: 3 | N27: 4.5524297 | O27: 3 | T27: 3.3024835 | U27: 3 | Z27: -0.70611369 | AA27: 3 | AF27: -2.2212392 | AG27: 3 | AL27: -1.1814682 | AM27: 3 | AR27: -0.57757942 | AS27: 3 | AY27: 0.24617407 | BF27: 0.092647844
A28: 44777 | B28: -1.6610274 | C28: 4 | D28: -0.80670183 | H28: 2.1015211 | I28: 4 | J28: 2.6511448 | N28: -0.048923679 | O28: 4 | P28: 17.413793 | T28: 3.0808895 | U28: 4 | V28: 5.6201294 | Z28: -1.0081916 | AA28: 4 | AB28: 19.662677 | AF28: 0.9403477 | AG28: 4 | AH28: -1.4792153 | AL28: -1.2358947 | AM28: 4 | AN28: -3.7696335 | AR28: -0.73937153 | AS28: 4 | AT28: 0.72347267 | AY28: -0.035368915 | AZ28: 2.6722427 | BF28: 0.15145013 | BG28: 4.3546217
A29: 44778 | B29: 0.75070378 | C29: 5 | H29: -1.6625635 | I29: 5 | N29: 1.9089574 | O29: 5 | T29: 2.5698743 | U29: 5 | Z29: 3.8919705 | AA29: 5 | AF29: 3.4862503 | AG29: 5 | AL29: 0.054406964 | AM29: 5 | AR29: 5.2407555 | AS29: 5 | AY29: 0.089172707 | BF29: 2.1094694
A30: 44781 | B30: 1.0866191 | C30: 1 | H30: 0.86182578 | I30: 1 | N30: -0.81652257 | O30: 1 | T30: 1.6093636 | U30: 1 | Z30: -2.4157549 | AA30: 1 | AF30: -0.80430613 | AG30: 1 | AL30: 0.67971724 | AM30: 1 | AR30: 0.075834176 | AS30: 1 | AY30: 0.73343871 | BF30: 0.089613092
A31: 44783 | B31: 8.5380835 | C31: 3 | H31: -0.49293501 | I31: 3 | N31: 5.9564165 | O31: 3 | T31: 0 | U31: 3 | Z31: 0.54713427 | AA31: 3 | AF31: -2.844134 | AG31: 3 | AL31: -0.48609236 | AM31: 3 | AR31: -5.5822177 | AS31: 3 | AY31: 0.05506388 | BF31: 0.79026295
A32: 44784 | B32: -0.87719298 | C32: 4 | D32: 7.7514611 | H32: 1.2889719 | I32: 4 | J32: 2.069033 | N32: 3.1078611 | O32: 4 | P32: 10.37182 | T32: -0.14398848 | U32: 4 | V32: 7.2768289 | Z32: 4.058876 | AA32: 4 | AB32: 5.0049509 | AF32: 0.35629454 | AG32: 4 | AH32: 1.0308279 | AL32: 1.0990502 | AM32: 4 | AN32: 0.094035465 | AR32: 0.56179775 | AS32: 4 | AT32: -0.73937153 | AY32: 0.70859294 | AZ32: 1.55767 | BF32: 1.0157946 | BG32: 4.1351385
A33: 44785 | B33: 1.0562375 | C33: 5 | H33: 0.25759471 | I33: 5 | N33: -0.66489362 | O33: 5 | T33: 0.76303773 | U33: 5 | Z33: -1.731676 | AA33: 5 | AF33: -0.22069407 | AG33: 5 | AL33: 0.093947121 | AM33: 5 | AR33: 1.2769354 | AS33: 5 | AY33: 0.22169998 | BF33: 0.17460631
A34: 44789 | B34: 0.70621469 | C34: 2 | H34: 1.102013 | I34: 2 | N34: -5.577867 | O34: 2 | T34: 2.5341363 | U34: 2 | Z34: 0.68917386 | AA34: 2 | AF34: 1.593153 | AG34: 2 | AL34: 1.6760526 | AM34: 2 | AR34: 0.18387182 | AS34: 2 | AY34: 0.71815416 | BF34: 0.40914716
A35: 44790 | B35: -0.28050491 | C35: 3 | H35: -0.37772613 | I35: 3 | N35: -0.14177694 | O35: 3 | T35: 0.50011631 | U35: 3 | Z35: -0.91838503 | AA35: 3 | AF35: 0.67522797 | AG35: 3 | AL35: 0.31649743 | AM35: 3 | AR35: -0.15731515 | AS35: 3 | AY35: 0.66759232 | BF35: -0.0048720488
A36: 44791 | B36: 0.61884669 | C36: 4 | D36: 1.2167516 | H36: 1.1127231 | I36: 4 | J36: 3.4192786 | N36: -0.8045433 | O36: 4 | P36: -4.2047532 | T36: 0.27195926 | U36: 4 | V36: 3.9656827 | Z36: -2.0286814 | AA36: 4 | AB36: -0.05352364 | AF36: 4.4849093 | AG36: 4 | AH36: 7.0103358 | AL36: 2.3136585 | AM36: 4 | AN36: 5.6037992 | AR36: 0.65651261 | AS36: 4 | AT36: 2.541466 | AY36: 0.068266994 | AZ36: 2.4052239 | BF36: 0.97576273 | BG36: 2.5844534
A37: 44792 | B37: -1.6773833 | C37: 5 | H37: -0.019883338 | I37: 5 | N37: 2.6717557 | O37: 5 | T37: -0.33469906 | U37: 5 | Z37: -1.0085684 | AA37: 5 | AF37: -3.0475733 | AG37: 5 | AL37: -3.9701914 | AM37: 5 | AR37: -1.2261936 | AS37: 5 | AY37: -1.1029432 | BF37: -1.170317
A38: 44795 | B38: -2.3599659 | C38: 1 | H38: -2.0685782 | I38: 1 | N38: -3.3457249 | O38: 1 | T38: -2.7560651 | U38: 1 | Z38: -5.4278244 | AA38: 1 | AF38: -3.8363963 | AG38: 1 | AL38: -2.3815895 | AM38: 1 | AR38: -2.4035922 | AS38: 1 | AY38: -1.5077329 | BF38: -3.0371277
A39: 44796 | B39: 4.1933605 | C39: 2 | H39: 2.3000388 | I39: 2 | N39: 0.72115385 | O39: 2 | T39: 0.3929741 | U39: 2 | Z39: -2.2881114 | AA39: 2 | AF39: 0.46650795 | AG39: 2 | AL39: 0.93201754 | AM39: 2 | AR39: 0.1082544 | AS39: 2 | AY39: 0.49626373 | BF39: 0.96371328
A40: 44797 | B40: -0.50307434 | C40: 3 | H40: -0.64589882 | I40: 3 | N40: 0.66825776 | O40: 3 | T40: 4.5074432 | U40: 3 | Z40: 0.048785247 | AA40: 3 | AF40: -0.57322189 | AG40: 3 | AL40: 1.0456274 | AM40: 3 | AR40: 3.2170857 | AS40: 3 | AY40: 0.15616555 | BF40: 0.98869918
A41: 44798 | B41: 6.4325843 | C41: 4 | D41: 5.9267543 | H41: -0.24517974 | I41: 4 | J41: -0.72699078 | N41: 1.6121385 | O41: 4 | P41: 2.2423664 | T41: 1.5379377 | U41: 4 | V41: 3.2488891 | Z41: -1.3555686 | AA41: 4 | AB41: -9.7197429 | AF41: -0.98879155 | AG41: 4 | AH41: -7.7899094 | AL41: 1.249832 | AM41: 4 | AN41: -3.1992805 | AR41: 0.13095862 | AS41: 4 | AT41: -0.26089225 | AY41: -0.4686182 | AZ41: -2.4172305 | BF41: 1.2168871 | BG41: -1.5536738
A42: 44799 | B42: -0.76537345 | C42: 5 | H42: 0.52236297 | I42: 5 | N42: 1.259916 | O42: 5 | T42: 7.0590208 | U42: 5 | Z42: 1.2654474 | AA42: 5 | AF42: -0.35782831 | AG42: 5 | AL42: 0.87602867 | AM42: 5 | AR42: 0.052314936 | AS42: 5 | AY42: 0.20801886 | BF42: 1.1910878
A43: 44802 | B43: -4.7074468 | C43: 1 | H43: -1.0951668 | I43: 1 | N43: 1.6589862 | O43: 1 | T43: 7.8047507 | U43: 1 | Z43: -3.1240847 | AA43: 1 | AF43: -0.18282132 | AG43: 1 | AL43: -2.6578947 | AM43: 1 | AR43: -1.4640523 | AS43: 1 | AY43: -1.4009989 | BF43: -0.4510436
A44: 44803 | B44: 0.44655317 | C44: 2 | H44: 3.3456703 | I44: 2 | N44: 1.3145966 | O44: 2 | T44: 3.3607748 | U44: 2 | Z44: 1.3907085 | AA44: 2 | AF44: 0.49713818 | AG44: 2 | AL44: 5.4339011 | AM44: 2 | AR44: 2.3083046 | AS44: 2 | AY44: 2.5784242 | BF44: 2.1619916
A45: 44805 | B45: 0.61128091 | C45: 4 | D45: 1.7134831 | E45: 44805 | F45: -3.8387186 | H45: -0.85623634 | I45: 4 | J45: 1.6182666 | K45: 44805 | L45: 0.11866158 | N45: 9.1275168 | O45: 4 | P45: 15.647226 | Q45: 44805 | R45: 21.03321 | T45: 2.8673163 | U45: 4 | V45: 24.601328 | W45: 44805 | X45: 2.8967025 | Z45: -1.4909055 | AA45: 4 | AB45: -3.3450361 | AC45: 44805 | AD45: -4.6413076 | AF45: -0.36124581 | AG45: 4 | AH45: -1.391394 | AI45: 44805 | AJ45: 4.3898615 | AL45: 2.1282051 | AM45: 4 | AN45: 7.0555033 | AO45: 44805 | AP45: -10.444389 | AR45: -0.18153527 | AS45: 4 | AT45: 0.81194343 | AU45: 44805 | AV45: -9.3530787 | AY45: -1.2190796 | AZ45: -0.35302571 | BA45: -2.5563194 | BF45: 1.5026293 | BG45: 5.9368924 | BH45: 0.61736526
A46: 44806 | B46: -0.52471693 | C46: 5 | H46: -1.3637684 | I46: 5 | N46: 2.6650267 | O46: 5 | T46: -3.5297868 | U46: 5 | Z46: -2.4720008 | AA46: 5 | AF46: 0.25150248 | AG46: 5 | AL46: -0.82852122 | AM46: 5 | AR46: -0.88334632 | AS46: 5 | AY46: -0.019096153 | BF46: -0.77788575
A47: 44809 | B47: -0.77734592 | C47: 1 | H47: -0.25993695 | I47: 1 | N47: 2.3162939 | O47: 1 | T47: 1.732685 | U47: 1 | Z47: 2.4932754 | AA47: 1 | AF47: 1.0393249 | AG47: 1 | AL47: -0.2278481 | AM47: 1 | AR47: 1.4154653 | AS47: 1 | AY47: 0.72037607 | BF47: 0.92250372
A48: 44810 | B48: -1.2311136 | C48: 2 | H48: 0.14612483 | I48: 2 | N48: -2.2638564 | O48: 2 | T48: -1.0859477 | U48: 2 | Z48: -1.1002322 | AA48: 2 | AF48: 0.4095189 | AG48: 2 | AL48: 0.29180411 | AM48: 2 | AR48: 0.10338589 | AS48: 2 | AY48: -0.057738682 | BF48: -0.58302924
A49: 44811 | B49: -2.6062323 | C49: 3 | H49: -0.23837245 | I49: 3 | N49: 6.3498403 | O49: 3 | T49: 6.3432486 | U49: 3 | Z49: 0 | AA49: 3 | AF49: 3.0122997 | AG49: 3 | AL49: 1.0499684 | AM49: 3 | AR49: 0.98115156 | AS49: 3 | AY49: -0.17671447 | BF49: 1.8772219
A50: 44812 | B50: 3.9267016 | C50: 4 | D50: -1.3256007 | H50: -0.34187708 | I50: 4 | J50: -2.0472828 | N50: 3.0416823 | O50: 4 | P50: 12.505125 | T50: 3.8780552 | U50: 4 | V50: 7.2372017 | Z50: 1.7860788 | AA50: 4 | AB50: 0.62556755 | AF50: 3.0208561 | AG50: 4 | AH50: 7.9370264 | AL50: -0.55082624 | AM50: 4 | AN50: -0.27617374 | AR50: -0.81820506 | AS50: 4 | AT50: 0.77942323 | AY50: 0.98925353 | AZ50: 1.4590031 | BF50: 1.8832371 | BG50: 3.3591777
A51: 44813 | B51: -0.055975371 | C51: 5 | H51: -1.2270514 | I51: 5 | N51: -1.2390671 | O51: 5 | T51: -1.4015715 | U51: 5 | Z51: 2.9479595 | AA51: 5 | AF51: 0.48114749 | AG51: 5 | AL51: -0.075528701 | AM51: 5 | AR51: -0.05155968 | AS51: 5 | AY51: 0.19439567 | BF51: -0.11079191
A52: 44816 | B52: 2.800336 | C52: 1 | H52: 0.24120845 | I52: 1 | N52: 7.0479705 | O52: 1 | T52: -2.3217747 | U52: 1 | Z52: -1.6168306 | AA52: 1 | AF52: 1.9515133 | AG52: 1 | AL52: 3.1997984 | AM52: 1 | AR52: 1.2122775 | AS52: 1 | AY52: 0.57756955 | BF52: 1.6607128
A53: 44817 | B53: -1.0351403 | C53: 2 | H53: -1.4266533 | I53: 2 | N53: 6.2392279 | O53: 2 | T53: -4.7803845 | U53: 2 | Z53: 11.880012 | AA53: 2 | AF53: -1.9171122 | AG53: 2 | AL53: -0.20751953 | AM53: 2 | AR53: -0.71355759 | AS53: 2 | AY53: 0.74541364 | BF53: 0.6120905
A54: 44818 | B54: 1.9818332 | C54: 3 | H54: -0.14014142 | I54: 3 | N54: -3.1148605 | O54: 3 | T54: 4.8073361 | U54: 3 | Z54: -3.256349 | AA54: 3 | AF54: 6.297434 | AG54: 3 | AL54: -0.37920489 | AM54: 3 | AR54: -0.97535934 | AS54: 3 | AY54: -0.36690546 | BF54: 0.98111017
A55: 44819 | B55: -1.3495277 | C55: 4 | D55: 2.2949902 | H55: 1.8012125 | I55: 4 | J55: -0.78262983 | N55: 5.7602143 | O55: 4 | P55: 15.087464 | T55: 4.4233319 | U55: 4 | V55: 0.36525802 | Z55: -4.939175 | AA55: 4 | AB55: 4.2113707 | AF55: -0.0226661 | AG55: 4 | AH55: 6.7814562 | AL55: 0.93320236 | AM55: 4 | AN55: 3.4743202 | AR55: -2.4105754 | AS55: 4 | AT55: -2.9389018 | AY55: -0.70179824 | AZ55: 0.44188496 | BF55: 0.54524303 | BG55: 3.5971815
A56: 44820 | B56: -2.4623803 | C56: 5 | H56: -0.75037463 | I56: 5 | N56: -8.1063965 | O56: 5 | T56: 0.14811053 | U56: 5 | Z56: -0.19243722 | AA56: 5 | AF56: -4.3755491 | AG56: 5 | AL56: -5.3284672 | AM56: 5 | AR56: -0.66401062 | AS56: 5 | AY56: -1.938481 | BF56: -2.7992212
A57: 44823 | B57: 1.0378682 | C57: 1 | H57: -0.35830582 | I57: 1 | N57: -1.3094418 | O57: 1 | T57: 4.6395673 | U57: 1 | Z57: -0.89655837 | AA57: 1 | AF57: -1.1854311 | AG57: 1 | AL57: -1.0151632 | AM57: 1 | AR57: -0.96256684 | AS57: 1 | AY57: 0.52136662 | BF57: 0.051436612
A58: 44824 | B58: 2.4153248 | C58: 2 | H58: 3.5307675 | I58: 2 | N58: -1.1173184 | O58: 2 | T58: -3.1133904 | U58: 2 | Z58: -0.5155642 | AA58: 2 | AF58: 3.0411181 | AG58: 2 | AL58: 1.7655459 | AM58: 2 | AR58: -0.02699784 | AS58: 2 | AY58: 1.100881 | BF58: 0.78952359
A59: 44825 | B59: 1.0029818 | C59: 3 | H59: 1.558024 | I59: 3 | N59: -1.5536723 | O59: 3 | T59: 0.10419706 | U59: 3 | Z59: -0.28356312 | AA59: 3 | AF59: -2.2586373 | AG59: 3 | AL59: -3.1126419 | AM59: 3 | AR59: 0.081015393 | AS59: 3 | AY59: -0.54949835 | BF59: -0.59678231
A60: 44826 | B60: -3.4621578 | C60: 4 | D60: -1.5868673 | H60: 3.6616152 | I60: 4 | J60: 7.788301 | N60: 2.8335725 | O60: 4 | P60: -9.2146928 | T60: 2.1775335 | U60: 4 | V60: 3.8508739 | Z60: -0.63737988 | AA60: 4 | AB60: -2.5016838 | AF60: -1.6378309 | AG60: 4 | AH60: -6.3932893 | AL60: 0.25016458 | AM60: 4 | AN60: -7.3722628 | AR60: -1.4301133 | AS60: 4 | AT60: -2.9747676 | AY60: -0.49976437 | AZ60: -1.3849889 | BF60: 0.0046382891 | BG60: -2.5449263
A61: 44827 | B61: -2.0572699 | C61: 5 | H61: 0.12374428 | I61: 5 | N61: -1.04639 | O61: 5 | T61: -3.6632574 | U61: 5 | Z61: -2.7829863 | AA61: 5 | AF61: -4.326239 | AG61: 5 | AL61: -2.8237457 | AM61: 5 | AR61: 1.2318642 | AS61: 5 | AY61: -1.7155612 | BF61: -2.0039479
A62: 44830 | B62: -1.5611695 | C62: 1 | H62: -4.6001038 | I62: 1 | N62: -1.6214311 | O62: 1 | T62: 1.9456899 | U62: 1 | Z62: -2.7712923 | AA62: 1 | AF62: -2.1707487 | AG62: 1 | AL62: -4.8384917 | AM62: 1 | AR62: -3.190914 | AS62: 1 | AY62: -1.7951389 | BF62: -2.2339972
A63: 44831 | B63: -1.0957324 | C63: 2 | H63: -1.7305698 | I63: 2 | N63: 0.57327123 | O63: 2 | T63: -6.0783337 | U63: 2 | Z63: -0.26101483 | AA63: 2 | AF63: -1.2226679 | AG63: 2 | AL63: -0.36926573 | AM63: 2 | AR63: -2.150838 | AS63: 2 | AY63: -0.052302792 | BF63: -1.5922302
A64: 44832 | B64: -0.14577259 | C64: 3 | H64: 0.46543221 | I64: 3 | N64: 1.2112576 | O64: 3 | T64: -1.9172152 | U64: 3 | Z64: -1.7167382 | AA64: 3 | AF64: -0.25541948 | AG64: 3 | AL64: -0.5702067 | AM64: 3 | AR64: -3.1687125 | AS64: 3 | AY64: -0.87491327 | BF64: -0.76955391
A65: 44833 | B65: 0.2919708 | C65: 4 | D65: -4.5037531 | H65: -0.65390724 | I65: 4 | J65: -6.3148255 | N65: 1.6895459 | O65: 4 | P65: 0.76735263 | T65: 1.0223844 | U65: 4 | V65: -8.6019315 | Z65: -0.47928427 | AA65: 4 | AB65: -7.7864403 | AF65: 1.7892318 | AG65: 4 | AH65: -6.133632 | AL65: 0.53046595 | AM65: 4 | AN65: -7.906488 | AR65: 3.5966981 | AS65: 4 | AT65: -3.8050917 | AY65: -0.24023347 | AZ65: -4.6041362 | BF65: 1.0657434 | BG65: -5.4753436
A66: 44834 | B66: 1.3682678 | C66: 5 | H66: 2.0160113 | I66: 5 | N66: 2.1806854 | O66: 5 | T66: 0.72224699 | U66: 5 | Z66: 1.1451199 | AA66: 5 | AF66: 3.0801484 | AG66: 5 | AL66: 1.7398745 | AM66: 5 | AR66: -0.71143995 | AS66: 5 | AY66: 1.6425756 | BF66: 1.4552476
A67: 44837 | B67: -2.9293509 | C67: 1 | E67: 44837 | F67: 10.059172 | H67: -2.1890355 | I67: 1 | K67: 44837 | L67: 0.42698264 | N67: -1.0840108 | O67: 1 | Q67: 44837 | R67: 2.0205479 | T67: -3.9438739 | U67: 1 | W67: 44837 | X67: 23.031197 | Z67: -0.78298593 | AA67: 1 | AC67: 44837 | AD67: -17.660232 | AF67: -2.7690864 | AG67: 1 | AI67: 44837 | AJ67: 3.0378117 | AL67: -2.4810765 | AM67: 1 | AO67: 44837 | AP67: 10.823631 | AR67: 3.2960734 | AS67: 1 | AU67: 44837 | AV67: 7.1032186 | AY67: -1.2109264 | BA67: 6.660903 | BF67: -1.6639923 | BH67: 5.699998 | BX67: Portoflio Correlation of Returns
A68: 44838 | B68: 2.3076923 | C68: 2 | H68: 5.3389982 | I68: 2 | N68: -0.92465753 | O68: 2 | T68: 3.46067 | U68: 2 | Z68: 2.8367282 | AA68: 2 | AF68: 2.7160097 | AG68: 2 | AL68: 3.2341527 | AM68: 2 | AR68: 2.0532741 | AS68: 2 | AY68: 2.2913601 | BF68: 2.5650801 | BW68: Daily | BX68: =CORREL(BF4:BF497,AY4:AY497) -> 0.61982253 | BZ68: (+ve)
A69: 44840 | B69: -0.8675535 | C69: 4 | D69: 0.087591241 | H69: 1.6781635 | I69: 4 | J69: 6.1753128 | N69: 3.8368476 | O69: 4 | P69: 5.7374164 | T69: 7.371281 | U69: 4 | V69: 8.5754177 | Z69: 1.7110858 | AA69: 4 | AB69: 4.4626691 | AF69: -1.5852627 | AG69: 4 | AH69: 3.1286934 | AL69: 2.2974102 | AM69: 4 | AN69: 5.3333333 | AR69: 1.6856987 | AS69: 4 | AT69: 6.4314172 | AY69: 0.33286443 | AZ69: 2.806876 | BF69: 1.8845208 | BG69: 4.8256194 | BW69: Weekly | BX69: =CORREL(BG4:BG497,AZ4:AZ497) -> 0.71141999 | BZ69: (+ve)
A70: 44841 | B70: 4.4340723 | C70: 5 | H70: 0.70508177 | I70: 5 | N70: 1.1651132 | O70: 5 | T70: -0.51852159 | U70: 5 | Z70: -0.57096248 | AA70: 5 | AF70: -2.9478241 | AG70: 5 | AL70: 0.42194093 | AM70: 5 | AR70: 0.56149733 | AS70: 5 | AY70: -0.098951061 | BF70: 0.4323825 | BW70: Monthly | BX70: =CORREL(BH4:BH497,BA4:BA497) -> 0.64632676 | BZ70: (+ve)
A71: 44844 | B71: 0 | C71: 1 | H71: -1.9983836 | I71: 1 | N71: 2.6653504 | O71: 1 | T71: -0.75890251 | U71: 1 | Z71: -1.7432322 | AA71: 1 | AF71: 0.53137403 | AG71: 1 | AL71: -0.71835186 | AM71: 1 | AR71: 0.77107152 | AS71: 1 | AY71: -0.42536234 | BF71: -0.059233673
A72: 44845 | B72: -1.3128492 | C72: 2 | H72: -2.0593681 | I72: 2 | N72: -1.7307692 | O72: 2 | T72: -3.0420168 | U72: 2 | Z72: -2.3898977 | AA72: 2 | AF72: -2.7602858 | AG72: 2 | AL72: -2.116041 | AM72: 2 | AR72: -1.1873351 | AS72: 2 | AY72: -1.4932429 | BF72: -2.0673298
A73: 44846 | B73: 4.8117747 | C73: 3 | H73: -0.5693269 | I73: 3 | N73: 1.1741683 | O73: 3 | T73: 0.46368521 | U73: 3 | Z73: -2.2131936 | AA73: 3 | AF73: 2.1474348 | AG73: 3 | AL73: 2.3291492 | AM73: 3 | AR73: 0.45393858 | AS73: 3 | AY73: 0.82462147 | BF73: 1.3053186
A74: 44847 | B74: -1.7013233 | C74: 4 | D74: 6.1843641 | H74: -0.45556033 | I74: 4 | J74: -4.3279869 | N74: -2.9980658 | O74: 4 | P74: 0.16644474 | T74: 0.4615451 | U74: 4 | V74: -3.3890571 | Z74: -1.0277717 | AA74: 4 | AB74: -7.7079935 | AF74: -1.0347206 | AG74: 4 | AH74: -4.0906631 | AL74: -1.1721412 | AM74: 4 | AN74: -1.3066558 | AR74: 0.50505051 | AS74: 4 | AT74: 1.0962567 | AY74: -0.63800836 | AZ74: -1.8316043 | BF74: -0.93350719 | BG74: -1.3244323
A75: 44848 | B75: 1.1263736 | C75: 5 | H75: -0.053956445 | I75: 5 | N75: 0 | O75: 5 | T75: 3.0656934 | U75: 5 | Z75: -2.2536456 | AA75: 5 | AF75: -0.19583112 | AG75: 5 | AL75: -1.0619225 | AM75: 5 | AR75: -1.4281936 | AS75: 5 | AY75: 1.0070911 | BF75: -0.0057345501
A76: 44851 | B76: 4.9171421 | C76: 1 | H76: 1.1538924 | I76: 1 | N76: 0.39880359 | O76: 1 | T76: 7.1613064 | U76: 1 | Z76: -3.5940325 | AA76: 1 | AF76: 0.37580232 | AG76: 1 | AL76: 0.19514915 | AM76: 1 | AR76: -0.99275557 | AS76: 1 | AY76: 0.73374957 | BF76: 1.4231136
A77: 44852 | B77: 0.1294666 | C77: 2 | H77: 1.9595851 | I77: 2 | N77: 0.33101622 | O77: 2 | T77: 9.742254 | U77: 2 | Z77: 0.82063306 | AA77: 2 | AF77: 0.10602346 | AG77: 2 | AL77: 1.7390095 | AM77: 2 | AR77: 2.6287263 | AS77: 2 | AY77: 1.0117377 | BF77: 2.1699758
A78: 44853 | B78: -0.077579519 | C78: 3 | H78: 1.058247 | I78: 3 | N78: 0.32992412 | O78: 3 | T78: -3.6416451 | U78: 3 | Z78: -0.6627907 | AA78: 3 | AF78: 0.48652942 | AG78: 3 | AL78: 1.2717079 | AM78: 3 | AR78: -0.18484288 | AS78: 3 | AY78: 0.14467932 | BF78: -0.20435948
A79: 44854 | B79: -3.1573499 | C79: 4 | D79: 2.8021978 | H79: 1.6934799 | I79: 4 | J79: 5.9354059 | N79: -0.88786583 | O79: 4 | P79: 0.16616816 | T79: 0.08823205 | U79: 4 | V79: 16.895663 | Z79: -6.1804987 | AA79: 4 | AB79: -11.456032 | AF79: 0.36889431 | AG79: 4 | AH79: 1.1451142 | AL79: 0.83715906 | AM79: 4 | AN79: 2.9926907 | AR79: 3.2539683 | AS79: 4 | AT79: 4.7222968 | AY79: 0.29522192 | AZ79: 3.2302145 | BF79: -0.43856899 | BG79: 3.2294328
A80: 44855 | B80: -0.88188135 | C80: 5 | H80: -1.4892427 | I80: 5 | N80: -1.6257465 | O80: 5 | T80: -2.0899908 | U80: 5 | Z80: -5.2651279 | AA80: 5 | AF80: 0.32487776 | AG80: 5 | AL80: -0.96411355 | AM80: 5 | AR80: -0.94798873 | AS80: 5 | AY80: 0.070314479 | BF80: -1.4647081
A81: 44858 | B81: 0.86276624 | C81: 1 | H81: 0.42938297 | I81: 1 | N81: 2.158516 | O81: 1 | T81: 0.33013205 | U81: 1 | Z81: 3.8983274 | AA81: 1 | AF81: -0.51681277 | AG81: 1 | AL81: -0.58139535 | AM81: 1 | AR81: 0.12933264 | AS81: 1 | AY81: 0.87874012 | BF81: 0.73364895
A82: 44859 | B82: -0.16038492 | C82: 2 | H82: -2.3626419 | I82: 2 | N82: -0.49521294 | O82: 2 | T82: 1.4545319 | U82: 2 | Z82: -2.5858791 | AA82: 2 | AF82: 0.75623068 | AG82: 2 | AL82: 0.57119543 | AM82: 2 | AR82: -3.2033066 | AS82: 2 | AY82: -0.41961 | BF82: -0.62369806
A83: 44861 | B83: 0.9103079 | C83: 4 | D83: -2.4585921 | H83: -2.1057544 | I83: 4 | J83: -3.836393 | N83: -0.099535501 | O83: 4 | P83: -0.98651759 | T83: -1.5811005 | U83: 4 | V83: -1.8271387 | Z83: -0.68965517 | AA83: 4 | AB83: -10.663701 | AF83: 3.2698081 | AG83: 4 | AH83: 4.2324034 | AL83: 3.7187289 | AM83: 4 | AN83: 3.5646773 | AR83: -0.053376034 | AS83: 4 | AT83: -0.92592593 | AY83: 0.45649299 | AZ83: 1.2831018 | BF83: 0.5692977 | BG83: -1.232457
A84: 44862 | B84: -0.37145131 | C84: 5 | H84: -3.2347824 | I84: 5 | N84: 0.2324809 | O84: 5 | T84: 0.13855602 | U84: 5 | Z84: 3.0267296 | AA84: 5 | AF84: -3.1441572 | AG84: 5 | AL84: 0.28683181 | AM84: 5 | AR84: 3.9252336 | AS84: 5 | AY84: 0.2810517 | BF84: 0.042463612
A85: 44865 | B85: -0.93209055 | C85: 1 | H85: 1.1045212 | I85: 1 | N85: -1.2922465 | O85: 1 | T85: -0.15706219 | U85: 1 | Z85: -1.8059265 | AA85: 1 | AF85: 4.4631497 | AG85: 1 | AL85: 0.23400936 | AM85: 1 | AR85: -0.82219938 | AS85: 1 | AY85: 1.2672319 | BF85: 0.20522587
A86: 44866 | B86: -0.1344086 | C86: 2 | E86: 44866 | F86: 1.6419919 | H86: 1.0469442 | I86: 2 | K86: 44866 | L86: -5.7129989 | N86: -0.63779792 | O86: 2 | Q86: 44866 | R86: -13.851351 | T86: 0.61425522 | U86: 2 | W86: 44866 | X86: 0.1489037 | Z86: 1.4764927 | AA86: 2 | AC86: 44866 | AD86: 15.571155 | AF86: 0.29045254 | AG86: 2 | AI86: 44866 | AJ86: 13.396861 | AL86: 1.076524 | AM86: 2 | AO86: 44866 | AP86: 3.3363275 | AR86: -0.23316062 | AS86: 2 | AU86: 44866 | AV86: 6.2840821 | AY86: 0.73949878 | BA86: 3.3779911 | BF86: 0.37793971 | BH86: 2.8161288
A87: 44867 | B87: 0.2960969 | C87: 3 | H87: -0.28902539 | I87: 3 | N87: 0.54054054 | O87: 3 | T87: 0.67751182 | U87: 3 | Z87: -0.93171666 | AA87: 3 | AF87: -0.65396114 | AG87: 3 | AL87: -1.1548826 | AM87: 3 | AR87: 1.1165931 | AS87: 3 | AY87: -0.34471547 | BF87: -0.016241246
A88: 44868 | B88: 0.77831455 | C88: 4 | D88: -0.37145131 | H88: -1.2245647 | I88: 4 | J88: -2.6345328 | N88: 0.36962366 | O88: 4 | P88: -0.79707738 | T88: 4.0377149 | U88: 4 | V88: 5.3662373 | Z88: -1.8165421 | AA88: 4 | AB88: -0.14412998 | AF88: 3.6737509 | AG88: 4 | AH88: 4.5124186 | AL88: -0.10385564 | AM88: 4 | AN88: 0.32594524 | AR88: 0.20544427 | AS88: 4 | AT88: 4.1922563 | AY88: -0.16673257 | AZ88: 1.780182 | BF88: 0.94720199 | BG88: 1.5293471
A89: 44869 | B89: 1.2250333 | C89: 5 | H89: 0.22632611 | I89: 5 | N89: 1.0378306 | O89: 5 | T89: 2.1253154 | U89: 5 | Z89: -1.1284608 | AA89: 5 | AF89: 5.3697769 | AG89: 5 | AL89: 0.66276803 | AM89: 5 | AR89: -0.69195284 | AS89: 5 | AY89: 0.35701031 | BF89: 1.289417
A90: 44872 | B90: 3.2622994 | C90: 1 | H90: 0.68288399 | I90: 1 | N90: -3.4459907 | O90: 1 | T90: -2.3942927 | U90: 1 | Z90: 2.4153948 | AA90: 1 | AF90: 1.4289813 | AG90: 1 | AL90: 2.7110767 | AM90: 1 | AR90: 0.95483871 | AS90: 1 | AY90: 0.47275648 | BF90: 0.73820129
A91: 44874 | B91: -1.477707 | C91: 3 | H91: -0.80019767 | I91: 3 | N91: -0.78929307 | O91: 3 | T91: -4.6921239 | U91: 3 | Z91: 1.0625891 | AA91: 3 | AF91: -1.8133982 | AG91: 3 | AL91: -0.18853695 | AM91: 3 | AR91: 0.23006135 | AS91: 3 | AY91: -0.25160964 | BF91: -1.1648344
A92: 44875 | B92: -0.36203776 | C92: 4 | D92: 3.4084809 | H92: -1.8463558 | I92: 4 | J92: -2.9481886 | N92: -3.0785195 | O92: 4 | P92: -5.8467742 | T92: -0.49754966 | U92: 4 | V92: -1.6528009 | Z92: -4.1159123 | AA92: 4 | AB92: -3.6588508 | AF92: -3.0915954 | AG92: 4 | AH92: 5.4291267 | AL92: -1.4859589 | AM92: 4 | AN92: 1.5578346 | AR92: -0.12751849 | AS92: 4 | AT92: 0.56497175 | AY92: -0.70936829 | AZ92: -0.30222006 | BF92: -1.7432681 | BG92: 0.88466699
A93: 44876 | B93: -1.5312743 | C93: 5 | H93: -2.2707845 | I93: 5 | N93: -8.2084226 | O93: 5 | T93: 4.5680126 | U93: 5 | Z93: 6.7932602 | AA93: 5 | AF93: -0.8205982 | AG93: 5 | AL93: 2.4031701 | AM93: 5 | AR93: 0.91930541 | AS93: 5 | AY93: 1.7833172 | BF93: 0.11618775
A94: 44879 | B94: -2.6884555 | C94: 1 | H94: -1.5074357 | I94: 1 | N94: -2.6827372 | O94: 1 | T94: -0.90245569 | U94: 1 | Z94: -2.7923867 | AA94: 1 | AF94: 1.372984 | AG94: 1 | AL94: 1.4854575 | AM94: 1 | AR94: 1.5182186 | AS94: 1 | AY94: -0.11199093 | BF94: -0.69092734
A95: 44880 | B95: 2.9523294 | C95: 2 | H95: -0.31572914 | I95: 2 | N95: -2.796644 | O95: 2 | T95: -0.45352297 | U95: 2 | Z95: 0.025763236 | AA95: 2 | AF95: -0.65945115 | AG95: 2 | AL95: -0.25830258 | AM95: 2 | AR95: 0.94715852 | AS95: 2 | AY95: 0.40509243 | BF95: 0.012514171
A96: 44881 | B96: -0.26308866 | C96: 3 | H96: -1.0470907 | I96: 3 | N96: -2.0961776 | O96: 3 | T96: -0.50297044 | U96: 3 | Z96: -2.7817128 | AA96: 3 | AF96: 1.6789212 | AG96: 3 | AL96: -1.0358861 | AM96: 3 | AR96: 1.1604938 | AS96: 3 | AY96: 0.033961116 | BF96: -0.46087506
A97: 44882 | B97: -1.0287523 | C97: 4 | D97: -2.621334 | H97: -0.65130683 | I97: 4 | J97: -5.6710023 | N97: -0.79764903 | O97: 4 | P97: -15.66738 | T97: 1.8315689 | U97: 4 | V97: 4.5153771 | Z97: -1.5631209 | AA97: 4 | AB97: -0.6285103 | AF97: 0.34253594 | AG97: 4 | AH97: 1.9028364 | AL97: 0.41121495 | AM97: 4 | AN97: 3.0039627 | AR97: -1.1959971 | AS97: 4 | AT97: 3.3707865 | AY97: -0.35714965 | AZ97: 1.7511454 | BF97: -0.28812298 | BG97: -1.2321348
A98: 44883 | B98: -2.6119403 | C98: 5 | H98: 0.50821077 | I98: 5 | N98: -2.2852306 | O98: 5 | T98: -1.55761 | U98: 5 | Z98: 8.3030548 | AA98: 5 | AF98: -2.0306938 | AG98: 5 | AL98: -0.62050137 | AM98: 5 | AR98: 0.93873518 | AS98: 5 | AY98: -0.19761338 | BF98: -0.24441013
A99: 44886 | B99: 0.46524357 | C99: 1 | H99: 1.1873787 | I99: 1 | N99: 2.5985275 | O99: 1 | T99: 0.69794636 | U99: 1 | Z99: 2.2738569 | AA99: 1 | AF99: -0.2352731 | AG99: 1 | AL99: -1.4235764 | AM99: 1 | AR99: -2.3250122 | AS99: 1 | AY99: -0.80676657 | BF99: 0.31009469
A100: 44887 | B100: 0.49032961 | C100: 2 | H100: 0.56857004 | I100: 2 | N100: 2.617138 | O100: 2 | T100: 2.1410168 | U100: 2 | Z100: -2.5756287 | AA100: 2 | AF100: 2.2776799 | AG100: 2 | AL100: -1.0134279 | AM100: 2 | AR100: -1.929341 | AS100: 2 | AY100: 0.463933 | BF100: 0.43445863
...

Sheet Part 2
E462: CUB | U462: PAGEIND | AK462: INOXWIND/NTPC Ltd. | BA462: DATAPATTNS/BEL | BQ462: POLICYBZR-SBILIFE | CG462: DALBHARAT | CW462: DLF | DM462: OIL/BPCL
A464: DATE | B464: EXPIRY DATE | C464: CLOSE PRICE | E464: DATE | F464: EXPIRY DATE | G464: CLOSE PRICE | I464: daily ret | J464: weekday | K464: weekly ret | L464: monthnum | M464: month ret | N464: cub equity adj to futs dates | Q464: DATE | R464: EXPIRY DATE | S464: CLOSE PRICE | U464: DATE | V464: EXPIRY DATE | W464: CLOSE PRICE | Y464: daily ret | Z464: weekday | AA464: weekly ret | AB464: monthnum | AC464: month ret | AD464: pageind equity adj to futs dates | AG464: DATE | AH464: EXPIRY DATE | AI464: CLOSE PRICE | AK464: DATE | AL464: EXPIRY DATE | AM464: CLOSE PRICE | AO464: daily ret | AP464: weekday | AQ464: weekly ret | AR464: monthnum | AS464: month ret | AT464: inoxwind equity adj to futs dates | AW464: DATE | AX464: EXPIRY DATE | AY464: CLOSE PRICE | BA464: DATE | BB464: EXPIRY DATE | BC464: CLOSE PRICE | BE464: daily ret | BF464: weekday | BG464: weekly ret | BH464: monthnum | BI464: month ret | BJ464: datapattns equity adj to futs dates | BM464: DATE | BN464: EXPIRY DATE | BO464: CLOSE PRICE | BQ464: DATE | BR464: EXPIRY DATE | BS464: CLOSE PRICE | BU464: daily ret | BV464: weekday | BW464: weekly ret | BX464: monthnum | BY464: month ret | BZ464: policybzr equity adj to futs dates | CC464: DATE | CD464: EXPIRY DATE | CE464: CLOSE PRICE | CG464: DATE | CH464: EXPIRY DATE | CI464: CLOSE PRICE | CK464: daily ret | CL464: weekday | CM464: weekly ret | CN464: monthnum | CO464: month ret | CP464: dalbharat equity adj to futs dates | CS464: DATE | CT464: EXPIRY DATE | CU464: CLOSE PRICE | CW464: DATE | CX464: EXPIRY DATE | CY464: CLOSE PRICE | DA464: daily ret | DB464: weekday | DC464: weekly ret | DD464: monthnum | DE464: month ret | DF464: dlf equity adj to futs dates | DI464: DATE | DJ464: EXPIRY DATE | DK464: CLOSE PRICE | DM464: DATE | DN464: EXPIRY DATE | DO464: CLOSE PRICE | DQ464: daily ret | DR464: weekday | DS464: weekly ret | DT464: monthnum | DU464: month ret | DV464: oil pf adj to futs
N465: DAILY RETURNS(%) | O465: WEEKLY RETURN(%) | P465: MONTHLY RETURN(%) | AD465: DAILY RETURNS(%) | AE465: WEEKLY RETURN(%) | AF465: MONTHLY RETURN(%) | AT465: DAILY RETURNS(%) | AU465: WEEKLY RETURN(%) | AV465: MONTHLY RETURN(%) | BJ465: DAILY RETURNS(%) | BK465: WEEKLY RETURN(%) | BL465: MONTHLY RETURN(%) | BZ465: DAILY RETURNS(%) | CA465: WEEKLY RETURN(%) | CB465: MONTHLY RETURN(%) | CP465: DAILY RETURNS(%) | CQ465: WEEKLY RETURN(%) | CR465: MONTHLY RETURNS(%) | DF465: DAILY RETURNS(%) | DG465: WEEKLY RETURN(%) | DH465: MONTHLY RETURN(%) | DV465: DAILY RETURNS(%) | DW465: WEEKLY RETURN(%) | DX465: MONTHLY RETURN(%)
A466: 45470 | B466: 45470 | C466: 167.35 | E466: {=INDEX($A$466:$A$918, ROWS($A$466:$A$918) - ROW() + ROW($A$466))} -> 44742 | F466: {=INDEX($B$466:$B$918, ROWS($B$466:$B$918) - ROW() + ROW($B$466))} -> 44742 | G466: {=INDEX($C$466:$C$918, ROWS($C$466:$C$918) - ROW() + ROW($C$466))} -> 133.3 | J466: =WEEKDAY(E466, 2) -> 4 | Q466: 45470 | R466: 45470 | S466: 40145 | U466: {=INDEX($Q$466:$Q$918, ROWS($Q$466:$Q$918) - ROW() + ROW($Q$466))} -> 44742 | V466: {=INDEX($R$466:$R$918, ROWS($R$466:$R$918) - ROW() + ROW($R$466))} -> 44742 | W466: {=INDEX($S$466:$S$918, ROWS($S$466:$S$918) - ROW() + ROW($S$466))} -> 40178.95 | Z466: =WEEKDAY(U466, 2) -> 4 | AG466: 45470 | AH466: 45470 | AI466: 376 | AK466: {=INDEX($AG$466:$AG$918, ROWS($AG$466:$AG$918) - ROW() + ROW($AG$466))} -> 44742 | AL466: {=INDEX($AH$466:$AH$918, ROWS($AH$466:$AH$918) - ROW() + ROW($AH$466))} -> 44742 | AM466: {=INDEX($AI$466:$AI$918, ROWS($AI$466:$AI$918) - ROW() + ROW($AI$466))} -> 142.55 | AP466: =WEEKDAY(AK466, 2) -> 4 | AW466: 45470 | AX466: 45470 | AY466: 304.5 | BA466: {=INDEX($AW$466:$AW$918, ROWS($AW$466:$AW$918) - ROW() + ROW($AW$466))} -> 44742 | BB466: {=INDEX($AX$466:$AX$918, ROWS($AX$466:$AX$918) - ROW() + ROW($AX$466))} -> 44742 | BC466: {=INDEX($AY$466:$AY$918, ROWS($AY$466:$AY$918) - ROW() + ROW($AY$466))} -> 233.55 | BF466: =WEEKDAY(BA466, 2) -> 4 | BM466: 45470 | BN466: 45470 | BO466: 1461.45 | BQ466: {=INDEX($AW$466:$AW$918, ROWS($AW$466:$AW$918) - ROW() + ROW($AW$466))} -> 44742 | BR466: {=INDEX($AX$466:$AX$918, ROWS($AX$466:$AX$918) - ROW() + ROW($AX$466))} -> 44742 | BS466: {=INDEX($BO$466:$BO$918, ROWS($BO$466:$BO$918) - ROW() + ROW($BO$466))} -> 1086.1 | BV466: =WEEKDAY(BQ466, 2) -> 4 | CC466: 45470 | CD466: 45470 | CE466: 1792.3 | CG466: {=INDEX($AW$466:$AW$918, ROWS($AW$466:$AW$918) - ROW() + ROW($AW$466))} -> 44742 | CH466: {=INDEX($AX$466:$AX$918, ROWS($AX$466:$AX$918) - ROW() + ROW($AX$466))} -> 44742 | CI466: {=INDEX($CE$466:$CE$918, ROWS($CE$466:$CE$918) - ROW() + ROW($CE$466))} -> 1282.35 | CL466: =WEEKDAY(CG466, 2) -> 4 | CS466: 45470 | CT466: 45470 | CU466: 817.2 | CW466: {=INDEX($AW$466:$AW$918, ROWS($AW$466:$AW$918) - ROW() + ROW($AW$466))} -> 44742 | CX466: {=INDEX($AX$466:$AX$918, ROWS($AX$466:$AX$918) - ROW() + ROW($AX$466))} -> 44742 | CY466: {=INDEX($CU$466:$CU$918, ROWS($CU$466:$CU$918) - ROW() + ROW($CU$466))} -> 313.5 | DB466: =WEEKDAY(CW466, 2) -> 4 | DI466: 45470 | DJ466: 45470 | DK466: 304.35 | DM466: {=INDEX($AW$466:$AW$918, ROWS($AW$466:$AW$918) - ROW() + ROW($AW$466))} -> 44742 | DN466: {=INDEX($AX$466:$AX$918, ROWS($AX$466:$AX$918) - ROW() + ROW($AX$466))} -> 44742 | DO466: {=INDEX($DK$466:$DK$918, ROWS($DK$466:$DK$918) - ROW() + ROW($DK$466))} -> 308.85 | DR466: =WEEKDAY(DM466, 2) -> 4
A467: 45469 | B467: 45470 | C467: 167.1 | E467: {=INDEX($A$466:$A$918, ROWS($A$466:$A$918) - ROW() + ROW($A$466))} -> 44743 | F467: {=INDEX($B$466:$B$918, ROWS($B$466:$B$918) - ROW() + ROW($B$466))} -> 44770 | G467: {=INDEX($C$466:$C$918, ROWS($C$466:$C$918) - ROW() + ROW($C$466))} -> 135 | I467: =((G467-G466)/G466)*100 -> 1.2753188 | J467: =WEEKDAY(E467, 2) -> 5 | L467: =IF(MONTH(F467)<>MONTH(F466), F467, "") -> 44770 | M467: =IF(ISNUMBER(L467), (INDEX(G:G, MATCH(EOMONTH(F467, 0), F:F, 1)) / G467 - 1) * 100, "") -> 19.444444 | N467: 1.8038331 | P467: 18.752307 | Q467: 45469 | R467: 45470 | S467: 39625.1 | U467: {=INDEX($Q$466:$Q$918, ROWS($Q$466:$Q$918) - ROW() + ROW($Q$466))} -> 44743 | V467: {=INDEX($R$466:$R$918, ROWS($R$466:$R$918) - ROW() + ROW($R$466))} -> 44770 | W467: {=INDEX($S$466:$S$918, ROWS($S$466:$S$918) - ROW() + ROW($S$466))} -> 41527.2 | Y467: =((W467-W466)/W466)*100 -> 3.3556128 | Z467: =WEEKDAY(U467, 2) -> 5 | AB467: =IF(MONTH(V467)<>MONTH(V466), V467, "") -> 44770 | AC467: =IF(ISNUMBER(AB467), (INDEX(W:W, MATCH(EOMONTH(V467, 0), V:V, 1)) / W467 - 1) * 100, "") -> 14.644016 | AD467: 3.0107179 | AF467: 18.11977 | AG467: 45469 | AH467: 45470 | AI467: 364.8 | AK467: {=INDEX($AG$466:$AG$918, ROWS($AG$466:$AG$918) - ROW() + ROW($AG$466))} -> 44743 | AL467: {=INDEX($AH$466:$AH$918, ROWS($AH$466:$AH$918) - ROW() + ROW($AH$466))} -> 44770 | AM467: {=INDEX($AI$466:$AI$918, ROWS($AI$466:$AI$918) - ROW() + ROW($AI$466))} -> 140.9 | AO467: =((AM467-AM466)/AM466)*100 -> -1.1574886 | AP467: =WEEKDAY(AK467, 2) -> 5 | AR467: =IF(MONTH(AL467)<>MONTH(AL466), AL467, "") -> 44770 | AS467: =IF(ISNUMBER(AR467), (INDEX(AM:AM, MATCH(EOMONTH(AL467, 0), AL:AL, 1)) / AM467 - 1) * 100, "") -> 6.5649397 | AT467: -1.958307 | AV467: 14.43299 | AW467: 45469 | AX467: 45470 | AY467: 306.45 | BA467: {=INDEX($AW$466:$AW$918, ROWS($AW$466:$AW$918) - ROW() + ROW($AW$466))} -> 44743 | BB467: {=INDEX($AX$466:$AX$918, ROWS($AX$466:$AX$918) - ROW() + ROW($AX$466))} -> 44770 | BC467: {=INDEX($AY$466:$AY$918, ROWS($AY$466:$AY$918) - ROW() + ROW($AY$466))} -> 230.6 | BE467: =((BC467-BC466)/BC466)*100 -> -1.2631128 | BF467: =WEEKDAY(BA467, 2) -> 5 | BH467: =IF(MONTH(BB467)<>MONTH(BB466), BB467, "") -> 44770 | BI467: =IF(ISNUMBER(BH467), (INDEX(BC:BC, MATCH(EOMONTH(BB467, 0), BB:BB, 1)) / BC467 - 1) * 100, "") -> 18.213356 | BJ467: -0.67135051 | BL467: 21.997799 | BM467: 45469 | BN467: 45470 | BO467: 1452 | BQ467: {=INDEX($AW$466:$AW$918, ROWS($AW$466:$AW$918) - ROW() + ROW($AW$466))} -> 44743 | BR467: {=INDEX($AX$466:$AX$918, ROWS($AX$466:$AX$918) - ROW() + ROW($AX$466))} -> 44770 | BS467: {=INDEX($BO$466:$BO$918, ROWS($BO$466:$BO$918) - ROW() + ROW($BO$466))} -> 1101.15 | BU467: =((BS467-BS466)/BS466)*100 -> 1.3856919 | BV467: =WEEKDAY(BQ467, 2) -> 5 | BX467: =IF(MONTH(BR467)<>MONTH(BR466), BR467, "") -> 44770 | BY467: =IF(ISNUMBER(BX467), (INDEX(BS:BS, MATCH(EOMONTH(BR467, 0), BR:BR, 1)) / BS467 - 1) * 100, "") -> 7.7782318 | BZ467: 2.635483 | CB467: -20.372417 | CC467: 45469 | CD467: 45470 | CE467: 1819.75 | CG467: {=INDEX($AW$466:$AW$918, ROWS($AW$466:$AW$918) - ROW() + ROW($AW$466))} -> 44743 | CH467: {=INDEX($AX$466:$AX$918, ROWS($AX$466:$AX$918) - ROW() + ROW($AX$466))} -> 44770 | CI467: {=INDEX($CE$466:$CE$918, ROWS($CE$466:$CE$918) - ROW() + ROW($CE$466))} -> 1328.15 | CK467: =((CI467-CI466)/CI466)*100 -> 3.5715678 | CL467: =WEEKDAY(CG467, 2) -> 5 | CN467: =IF(MONTH(CH467)<>MONTH(CH466), CH467, "") -> 44770 | CO467: =IF(ISNUMBER(CN467), (INDEX(CI:CI, MATCH(EOMONTH(CH467, 0), CH:CH, 1)) / CI467 - 1) * 100, "") -> 19.591161 | CP467: 3.3654033 | CR467: 20.559973 | CS467: 45469 | CT467: 45470 | CU467: 826.35 | CW467: {=INDEX($AW$466:$AW$918, ROWS($AW$466:$AW$918) - ROW() + ROW($AW$466))} -> 44743 | CX467: {=INDEX($AX$466:$AX$918, ROWS($AX$466:$AX$918) - ROW() + ROW($AX$466))} -> 44770 | CY467: {=INDEX($CU$466:$CU$918, ROWS($CU$466:$CU$918) - ROW() + ROW($CU$466))} -> 323.65 | DA467: =((CY467-CY466)/CY466)*100 -> 3.2376396 | DB467: =WEEKDAY(CW467, 2) -> 5 | DD467: =IF(MONTH(CX467)<>MONTH(CX466), CX467, "") -> 44770 | DE467: =IF(ISNUMBER(DD467), (INDEX(CY:CY, MATCH(EOMONTH(CX467, 0), CX:CX, 1)) / CY467 - 1) * 100, "") -> 17.997837 | DF467: 3.3418612 | DH467: 19.4337 | DI467: 45469 | DJ467: 45470 | DK467: 297.85 | DM467: {=INDEX($AW$466:$AW$918, ROWS($AW$466:$AW$918) - ROW() + ROW($AW$466))} -> 44743 | DN467: {=INDEX($AX$466:$AX$918, ROWS($AX$466:$AX$918) - ROW() + ROW($AX$466))} -> 44770 | DO467: {=INDEX($DK$466:$DK$918, ROWS($DK$466:$DK$918) - ROW() + ROW($DK$466))} -> 318.15 | DQ467: =((DO467-DO466)/DO466)*100 -> 3.0111705 | DR467: =WEEKDAY(DM467, 2) -> 5 | DT467: =IF(MONTH(DN467)<>MONTH(DN466), DN467, "") -> 44770 | DU467: =IF(ISNUMBER(DT467), (INDEX(DO:DO, MATCH(EOMONTH(DN467, 0), DN:DN, 1)) / DO467 - 1) * 100, "") -> 2.5145372 | DV467: -14.970179 | DX467: -11.152677
A468: 45468 | B468: 45470 | C468: 167.75 | E468: {=INDEX($A$466:$A$918, ROWS($A$466:$A$918) - ROW() + ROW($A$466))} -> 44746 | F468: {=INDEX($B$466:$B$918, ROWS($B$466:$B$918) - ROW() + ROW($B$466))} -> 44770 | G468: {=INDEX($C$466:$C$918, ROWS($C$466:$C$918) - ROW() + ROW($C$466))} -> 138.8 | I468: =((G468-G467)/G467)*100 -> 2.8148148 | J468: =WEEKDAY(E468, 2) -> 1 | L468: =IF(MONTH(F468)<>MONTH(F467), F468, "") | M468: =IF(ISNUMBER(L468), (INDEX(G:G, MATCH(EOMONTH(F468, 0), F:F, 1)) / G468 - 1) * 100, "") | N468: 2.1410114 | Q468: 45468 | R468: 45470 | S468: 40500.7 | U468: {=INDEX($Q$466:$Q$918, ROWS($Q$466:$Q$918) - ROW() + ROW($Q$466))} -> 44746 | V468: {=INDEX($R$466:$R$918, ROWS($R$466:$R$918) - ROW() + ROW($R$466))} -> 44770 | W468: {=INDEX($S$466:$S$918, ROWS($S$466:$S$918) - ROW() + ROW($S$466))} -> 42075.2 | Y468: =((W468-W467)/W467)*100 -> 1.319617 | Z468: =WEEKDAY(U468, 2) -> 1 | AB468: =IF(MONTH(V468)<>MONTH(V467), V468, "") | AC468: =IF(ISNUMBER(AB468), (INDEX(W:W, MATCH(EOMONTH(V468, 0), V:V, 1)) / W468 - 1) * 100, "") | AD468: 1.6357388 | AG468: 45468 | AH468: 45470 | AI468: 360.2 | AK468: {=INDEX($AG$466:$AG$918, ROWS($AG$466:$AG$918) - ROW() + ROW($AG$466))} -> 44746 | AL468: {=INDEX($AH$466:$AH$918, ROWS($AH$466:$AH$918) - ROW() + ROW($AH$466))} -> 44770 | AM468: {=INDEX($AI$466:$AI$918, ROWS($AI$466:$AI$918) - ROW() + ROW($AI$466))} -> 142.05 | AO468: =((AM468-AM467)/AM467)*100 -> 0.81618169 | AP468: =WEEKDAY(AK468, 2) -> 1 | AR468: =IF(MONTH(AL468)<>MONTH(AL467), AL468, "") | AS468: =IF(ISNUMBER(AR468), (INDEX(AM:AM, MATCH(EOMONTH(AL468, 0), AL:AL, 1)) / AM468 - 1) * 100, "") | AT468: 3.0927835 | AW468: 45468 | AX468: 45470 | AY468: 310 | BA468: {=INDEX($AW$466:$AW$918, ROWS($AW$466:$AW$918) - ROW() + ROW($AW$466))} -> 44746 | BB468: {=INDEX($AX$466:$AX$918, ROWS($AX$466:$AX$918) - ROW() + ROW($AX$466))} -> 44770 | BC468: {=INDEX($AY$466:$AY$918, ROWS($AY$466:$AY$918) - ROW() + ROW($AY$466))} -> 230.7 | BE468: =((BC468-BC467)/BC467)*100 -> 0.043365134 | BF468: =WEEKDAY(BA468, 2) -> 1 | BH468: =IF(MONTH(BB468)<>MONTH(BB467), BB468, "") | BI468: =IF(ISNUMBER(BH468), (INDEX(BC:BC, MATCH(EOMONTH(BB468, 0), BB:BB, 1)) / BC468 - 1) * 100, "") | BJ468: 0.80163471 | BM468: 45468 | BN468: 45470 | BO468: 1461.1 | BQ468: {=INDEX($AW$466:$AW$918, ROWS($AW$466:$AW$918) - ROW() + ROW($AW$466))} -> 44746 | BR468: {=INDEX($AX$466:$AX$918, ROWS($AX$466:$AX$918) - ROW() + ROW($AX$466))} -> 44770 | BS468: {=INDEX($BO$466:$BO$918, ROWS($BO$466:$BO$918) - ROW() + ROW($BO$466))} -> 1119.35 | BU468: =((BS468-BS467)/BS467)*100 -> 1.6528175 | BV468: =WEEKDAY(BQ468, 2) -> 1 | BX468: =IF(MONTH(BR468)<>MONTH(BR467), BR468, "") | BY468: =IF(ISNUMBER(BX468), (INDEX(BS:BS, MATCH(EOMONTH(BR468, 0), BR:BR, 1)) / BS468 - 1) * 100, "") | BZ468: -0.56967945 | CC468: 45468 | CD468: 45470 | CE468: 1815.3 | CG468: {=INDEX($AW$466:$AW$918, ROWS($AW$466:$AW$918) - ROW() + ROW($AW$466))} -> 44746 | CH468: {=INDEX($AX$466:$AX$918, ROWS($AX$466:$AX$918) - ROW() + ROW($AX$466))} -> 44770 | CI468: {=INDEX($CE$466:$CE$918, ROWS($CE$466:$CE$918) - ROW() + ROW($CE$466))} -> 1323.15 | CK468: =((CI468-CI467)/CI467)*100 -> -0.3764635 | CL468: =WEEKDAY(CG468, 2) -> 1 | CN468: =IF(MONTH(CH468)<>MONTH(CH467), CH468, "") | CO468: =IF(ISNUMBER(CN468), (INDEX(CI:CI, MATCH(EOMONTH(CH468, 0), CH:CH, 1)) / CI468 - 1) * 100, "") | CP468: -0.68206655 | CS468: 45468 | CT468: 45470 | CU468: 825.4 | CW468: {=INDEX($AW$466:$AW$918, ROWS($AW$466:$AW$918) - ROW() + ROW($AW$466))} -> 44746 | CX468: {=INDEX($AX$466:$AX$918, ROWS($AX$466:$AX$918) - ROW() + ROW($AX$466))} -> 44770 | CY468: {=INDEX($CU$466:$CU$918, ROWS($CU$466:$CU$918) - ROW() + ROW($CU$466))} -> 325.25 | DA468: =((CY468-CY467)/CY467)*100 -> 0.49436119 | DB468: =WEEKDAY(CW468, 2) -> 1 | DD468: =IF(MONTH(CX468)<>MONTH(CX467), CX468, "") | DE468: =IF(ISNUMBER(DD468), (INDEX(CY:CY, MATCH(EOMONTH(CX468, 0), CX:CX, 1)) / CY468 - 1) * 100, "") | DF468: 0.4951261 | DI468: 45468 | DJ468: 45470 | DK468: 296.45 | DM468: {=INDEX($AW$466:$AW$918, ROWS($AW$466:$AW$918) - ROW() + ROW($AW$466))} -> 44746 | DN468: {=INDEX($AX$466:$AX$918, ROWS($AX$466:$AX$918) - ROW() + ROW($AX$466))} -> 44770 | DO468: {=INDEX($DK$466:$DK$918, ROWS($DK$466:$DK$918) - ROW() + ROW($DK$466))} -> 317.45 | DQ468: =((DO468-DO467)/DO467)*100 -> -0.220022 | DR468: =WEEKDAY(DM468, 2) -> 1 | DT468: =IF(MONTH(DN468)<>MONTH(DN467), DN468, "") | DU468: =IF(ISNUMBER(DT468), (INDEX(DO:DO, MATCH(EOMONTH(DN468, 0), DN:DN, 1)) / DO468 - 1) * 100, "") | DV468: -5.7049334
A469: 45467 | B469: 45470 | C469: 162.2 | E469: {=INDEX($A$466:$A$918, ROWS($A$466:$A$918) - ROW() + ROW($A$466))} -> 44747 | F469: {=INDEX($B$466:$B$918, ROWS($B$466:$B$918) - ROW() + ROW($B$466))} -> 44770 | G469: {=INDEX($C$466:$C$918, ROWS($C$466:$C$918) - ROW() + ROW($C$466))} -> 140 | I469: =((G469-G468)/G468)*100 -> 0.86455331 | J469: =WEEKDAY(E469, 2) -> 2 | L469: =IF(MONTH(F469)<>MONTH(F468), F469, "") | M469: =IF(ISNUMBER(L469), (INDEX(G:G, MATCH(EOMONTH(F469, 0), F:F, 1)) / G469 - 1) * 100, "") | N469: 1.4817492 | Q469: 45467 | R469: 45470 | S469: 40218.25 | U469: {=INDEX($Q$466:$Q$918, ROWS($Q$466:$Q$918) - ROW() + ROW($Q$466))} -> 44747 | V469: {=INDEX($R$466:$R$918, ROWS($R$466:$R$918) - ROW() + ROW($R$466))} -> 44770 | W469: {=INDEX($S$466:$S$918, ROWS($S$466:$S$918) - ROW() + ROW($S$466))} -> 42343.75 | Y469: =((W469-W468)/W468)*100 -> 0.63826197 | Z469: =WEEKDAY(U469, 2) -> 2 | AB469: =IF(MONTH(V469)<>MONTH(V468), V469, "") | AC469: =IF(ISNUMBER(AB469), (INDEX(W:W, MATCH(EOMONTH(V469, 0), V:V, 1)) / W469 - 1) * 100, "") | AD469: 0.70304809 | AG469: 45467 | AH469: 45470 | AI469: 362.9 | AK469: {=INDEX($AG$466:$AG$918, ROWS($AG$466:$AG$918) - ROW() + ROW($AG$466))} -> 44747 | AL469: {=INDEX($AH$466:$AH$918, ROWS($AH$466:$AH$918) - ROW() + ROW($AH$466))} -> 44770 | AM469: {=INDEX($AI$466:$AI$918, ROWS($AI$466:$AI$918) - ROW() + ROW($AI$466))} -> 141.3 | AO469: =((AM469-AM468)/AM468)*100 -> -0.5279831 | AP469: =WEEKDAY(AK469, 2) -> 2 | AR469: =IF(MONTH(AL469)<>MONTH(AL468), AL469, "") | AS469: =IF(ISNUMBER(AR469), (INDEX(AM:AM, MATCH(EOMONTH(AL469, 0), AL:AL, 1)) / AM469 - 1) * 100, "") | AT469: -2.3125 | AW469: 45467 | AX469: 45470 | AY469: 310.25 | BA469: {=INDEX($AW$466:$AW$918, ROWS($AW$466:$AW$918) - ROW() + ROW($AW$466))} -> 44747 | BB469: {=INDEX($AX$466:$AX$918, ROWS($AX$466:$AX$918) - ROW() + ROW($AX$466))} -> 44770 | BC469: {=INDEX($AY$466:$AY$918, ROWS($AY$466:$AY$918) - ROW() + ROW($AY$466))} -> 229.8 | BE469: =((BC469-BC468)/BC468)*100 -> -0.39011704 | BF469: =WEEKDAY(BA469, 2) -> 2 | BH469: =IF(MONTH(BB469)<>MONTH(BB468), BB469, "") | BI469: =IF(ISNUMBER(BH469), (INDEX(BC:BC, MATCH(EOMONTH(BB469, 0), BB:BB, 1)) / BC469 - 1) * 100, "") | BJ469: 2.3935755 | BM469: 45467 | BN469: 45470 | BO469: 1453.65 | BQ469: {=INDEX($AW$466:$AW$918, ROWS($AW$466:$AW$918) - ROW() + ROW($AW$466))} -> 44747 | BR469: {=INDEX($AX$466:$AX$918, ROWS($AX$466:$AX$918) - ROW() + ROW($AX$466))} -> 44770 | BS469: {=INDEX($BO$466:$BO$918, ROWS($BO$466:$BO$918) - ROW() + ROW($BO$466))} -> 1113.45 | BU469: =((BS469-BS468)/BS468)*100 -> -0.52709162 | BV469: =WEEKDAY(BQ469, 2) -> 2 | BX469: =IF(MONTH(BR469)<>MONTH(BR468), BR469, "") | BY469: =IF(ISNUMBER(BX469), (INDEX(BS:BS, MATCH(EOMONTH(BR469, 0), BR:BR, 1)) / BS469 - 1) * 100, "") | BZ469: 0.19668206 | CC469: 45467 | CD469: 45470 | CE469: 1820.15 | CG469: {=INDEX($AW$466:$AW$918, ROWS($AW$466:$AW$918) - ROW() + ROW($AW$466))} -> 44747 | CH469: {=INDEX($AX$466:$AX$918, ROWS($AX$466:$AX$918) - ROW() + ROW($AX$466))} -> 44770 | CI469: {=INDEX($CE$466:$CE$918, ROWS($CE$466:$CE$918) - ROW() + ROW($CE$466))} -> 1305.25 | CK469: =((CI469-CI468)/CI468)*100 -> -1.3528323 | CL469: =WEEKDAY(CG469, 2) -> 2 | CN469: =IF(MONTH(CH469)<>MONTH(CH468), CH469, "") | CO469: =IF(ISNUMBER(CN469), (INDEX(CI:CI, MATCH(EOMONTH(CH469, 0), CH:CH, 1)) / CI469 - 1) * 100, "") | CP469: -1.2027622 | CS469: 45467 | CT469: 45470 | CU469: 840.2 | CW469: {=INDEX($AW$466:$AW$918, ROWS($AW$466:$AW$918) - ROW() + ROW($AW$466))} -> 44747 | CX469: {=INDEX($AX$466:$AX$918, ROWS($AX$466:$AX$918) - ROW() + ROW($AX$466))} -> 44770 | CY469: {=INDEX($CU$466:$CU$918, ROWS($CU$466:$CU$918) - ROW() + ROW($CU$466))} -> 322.9 | DA469: =((CY469-CY468)/CY468)*100 -> -0.72252114 | DB469: =WEEKDAY(CW469, 2) -> 2 | DD469: =IF(MONTH(CX469)<>MONTH(CX468), CX469, "") | DE469: =IF(ISNUMBER(DD469), (INDEX(CY:CY, MATCH(EOMONTH(CX469, 0), CX:CX, 1)) / CY469 - 1) * 100, "") | DF469: -0.81601232 | DI469: 45467 | DJ469: 45470 | DK469: 304.85 | DM469: {=INDEX($AW$466:$AW$918, ROWS($AW$466:$AW$918) - ROW() + ROW($AW$466))} -> 44747 | DN469: {=INDEX($AX$466:$AX$918, ROWS($AX$466:$AX$918) - ROW() + ROW($AX$466))} -> 44770 | DO469: {=INDEX($DK$466:$DK$918, ROWS($DK$466:$DK$918) - ROW() + ROW($DK$466))} -> 314.05 | DQ469: =((DO469-DO468)/DO468)*100 -> -1.0710348 | DR469: =WEEKDAY(DM469, 2) -> 2 | DT469: =IF(MONTH(DN469)<>MONTH(DN468), DN469, "") | DU469: =IF(ISNUMBER(DT469), (INDEX(DO:DO, MATCH(EOMONTH(DN469, 0), DN:DN, 1)) / DO469 - 1) * 100, "") | DV469: -5.4797917
A470: 45464 | B470: 45470 | C470: 162.9 | E470: {=INDEX($A$466:$A$918, ROWS($A$466:$A$918) - ROW() + ROW($A$466))} -> 44748 | F470: {=INDEX($B$466:$B$918, ROWS($B$466:$B$918) - ROW() + ROW($B$466))} -> 44770 | G470: {=INDEX($C$466:$C$918, ROWS($C$466:$C$918) - ROW() + ROW($C$466))} -> 140.65 | I470: =((G470-G469)/G469)*100 -> 0.46428571 | J470: =WEEKDAY(E470, 2) -> 3 | L470: =IF(MONTH(F470)<>MONTH(F469), F470, "") | M470: =IF(ISNUMBER(L470), (INDEX(G:G, MATCH(EOMONTH(F470, 0), F:F, 1)) / G470 - 1) * 100, "") | N470: 0.64102564 | Q470: 45464 | R470: 45470 | S470: 39749.9 | U470: {=INDEX($Q$466:$Q$918, ROWS($Q$466:$Q$918) - ROW() + ROW($Q$466))} -> 44748 | V470: {=INDEX($R$466:$R$918, ROWS($R$466:$R$918) - ROW() + ROW($R$466))} -> 44770 | W470: {=INDEX($S$466:$S$918, ROWS($S$466:$S$918) - ROW() + ROW($S$466))} -> 43589.2 | Y470: =((W470-W469)/W469)*100 -> 2.9412841 | Z470: =WEEKDAY(U470, 2) -> 3 | AB470: =IF(MONTH(V470)<>MONTH(V469), V470, "") | AC470: =IF(ISNUMBER(AB470), (INDEX(W:W, MATCH(EOMONTH(V470, 0), V:V, 1)) / W470 - 1) * 100, "") | AD470: 2.8871323 | AG470: 45464 | AH470: 45470 | AI470: 360.3 | AK470: {=INDEX($AG$466:$AG$918, ROWS($AG$466:$AG$918) - ROW() + ROW($AG$466))} -> 44748 | AL470: {=INDEX($AH$466:$AH$918, ROWS($AH$466:$AH$918) - ROW() + ROW($AH$466))} -> 44770 | AM470: {=INDEX($AI$466:$AI$918, ROWS($AI$466:$AI$918) - ROW() + ROW($AI$466))} -> 138.9 | AO470: =((AM470-AM469)/AM469)*100 -> -1.6985138 | AP470: =WEEKDAY(AK470, 2) -> 3 | AR470: =IF(MONTH(AL470)<>MONTH(AL469), AL470, "") | AS470: =IF(ISNUMBER(AR470), (INDEX(AM:AM, MATCH(EOMONTH(AL470, 0), AL:AL, 1)) / AM470 - 1) * 100, "") | AT470: 0.44785669 | AW470: 45464 | AX470: 45470 | AY470: 305.2 | BA470: {=INDEX($AW$466:$AW$918, ROWS($AW$466:$AW$918) - ROW() + ROW($AW$466))} -> 44748 | BB470: {=INDEX($AX$466:$AX$918, ROWS($AX$466:$AX$918) - ROW() + ROW($AX$466))} -> 44770 | BC470: {=INDEX($AY$466:$AY$918, ROWS($AY$466:$AY$918) - ROW() + ROW($AY$466))} -> 231.3 | BE470: =((BC470-BC469)/BC469)*100 -> 0.65274151 | BF470: =WEEKDAY(BA470, 2) -> 3 | BH470: =IF(MONTH(BB470)<>MONTH(BB469), BB470, "") | BI470: =IF(ISNUMBER(BH470), (INDEX(BC:BC, MATCH(EOMONTH(BB470, 0), BB:BB, 1)) / BC470 - 1) * 100, "") | BJ470: 5.7184192 | BM470: 45464 | BN470: 45470 | BO470: 1464.7 | BQ470: {=INDEX($AW$466:$AW$918, ROWS($AW$466:$AW$918) - ROW() + ROW($AW$466))} -> 44748 | BR470: {=INDEX($AX$466:$AX$918, ROWS($AX$466:$AX$918) - ROW() + ROW($AX$466))} -> 44770 | BS470: {=INDEX($BO$466:$BO$918, ROWS($BO$466:$BO$918) - ROW() + ROW($BO$466))} -> 1120.6 | BU470: =((BS470-BS469)/BS469)*100 -> 0.64214828 | BV470: =WEEKDAY(BQ470, 2) -> 3 | BX470: =IF(MONTH(BR470)<>MONTH(BR469), BR470, "") | BY470: =IF(ISNUMBER(BX470), (INDEX(BS:BS, MATCH(EOMONTH(BR470, 0), BR:BR, 1)) / BS470 - 1) * 100, "") | BZ470: -2.2702057 | CC470: 45464 | CD470: 45470 | CE470: 1817.75 | CG470: {=INDEX($AW$466:$AW$918, ROWS($AW$466:$AW$918) - ROW() + ROW($AW$466))} -> 44748 | CH470: {=INDEX($AX$466:$AX$918, ROWS($AX$466:$AX$918) - ROW() + ROW($AX$466))} -> 44770 | CI470: {=INDEX($CE$466:$CE$918, ROWS($CE$466:$CE$918) - ROW() + ROW($CE$466))} -> 1381.7 | CK470: =((CI470-CI469)/CI469)*100 -> 5.8571155 | CL470: =WEEKDAY(CG470, 2) -> 3 | CN470: =IF(MONTH(CH470)<>MONTH(CH469), CH470, "") | CO470: =IF(ISNUMBER(CN470), (INDEX(CI:CI, MATCH(EOMONTH(CH470, 0), CH:CH, 1)) / CI470 - 1) * 100, "") | CP470: 6.1100657 | CS470: 45464 | CT470: 45470 | CU470: 856.4 | CW470: {=INDEX($AW$466:$AW$918, ROWS($AW$466:$AW$918) - ROW() + ROW($AW$466))} -> 44748 | CX470: {=INDEX($AX$466:$AX$918, ROWS($AX$466:$AX$918) - ROW() + ROW($AX$466))} -> 44770 | CY470: {=INDEX($CU$466:$CU$918, ROWS($CU$466:$CU$918) - ROW() + ROW($CU$466))} -> 330.65 | DA470: =((CY470-CY469)/CY469)*100 -> 2.4001239 | DB470: =WEEKDAY(CW470, 2) -> 3 | DD470: =IF(MONTH(CX470)<>MONTH(CX469), CX470, "") | DE470: =IF(ISNUMBER(DD470), (INDEX(CY:CY, MATCH(EOMONTH(CX470, 0), CX:CX, 1)) / CY470 - 1) * 100, "") | DF470: 2.3284694 | DI470: 45464 | DJ470: 45470 | DK470: 307.35 | DM470: {=INDEX($AW$466:$AW$918, ROWS($AW$466:$AW$918) - ROW() + ROW($AW$466))} -> 44748 | DN470: {=INDEX($AX$466:$AX$918, ROWS($AX$466:$AX$918) - ROW() + ROW($AX$466))} -> 44770 | DO470: {=INDEX($DK$466:$DK$918, ROWS($DK$466:$DK$918) - ROW() + ROW($DK$466))} -> 321.2 | DQ470: =((DO470-DO469)/DO469)*100 -> 2.2767075 | DR470: =WEEKDAY(DM470, 2) -> 3 | DT470: =IF(MONTH(DN470)<>MONTH(DN469), DN470, "") | DU470: =IF(ISNUMBER(DT470), (INDEX(DO:DO, MATCH(EOMONTH(DN470, 0), DN:DN, 1)) / DO470 - 1) * 100, "") | DV470: -8.6044071
A471: 45463 | B471: 45470 | C471: 166.45 | E471: {=INDEX($A$466:$A$918, ROWS($A$466:$A$918) - ROW() + ROW($A$466))} -> 44749 | F471: {=INDEX($B$466:$B$918, ROWS($B$466:$B$918) - ROW() + ROW($B$466))} -> 44770 | G471: {=INDEX($C$466:$C$918, ROWS($C$466:$C$918) - ROW() + ROW($C$466))} -> 145.05 | I471: =((G471-G470)/G470)*100 -> 3.1283327 | J471: =WEEKDAY(E471, 2) -> 4 | K471: =IF(J471=4, ((G471 - G466) / G466)*100, "") -> 8.8147037 | L471: =IF(MONTH(F471)<>MONTH(F470), F471, "") | M471: =IF(ISNUMBER(L471), (INDEX(G:G, MATCH(EOMONTH(F471, 0), F:F, 1)) / G471 - 1) * 100, "") | N471: 2.5831564 | O471: 8.944006 | Q471: 45463 | R471: 45470 | S471: 39536.1 | U471: {=INDEX($Q$466:$Q$918, ROWS($Q$466:$Q$918) - ROW() + ROW($Q$466))} -> 44749 | V471: {=INDEX($R$466:$R$918, ROWS($R$466:$R$918) - ROW() + ROW($R$466))} -> 44770 | W471: {=INDEX($S$466:$S$918, ROWS($S$466:$S$918) - ROW() + ROW($S$466))} -> 44055.55 | Y471: =((W471-W470)/W470)*100 -> 1.0698751 | Z471: =WEEKDAY(U471, 2) -> 4 | AA471: =IF(Z471=4, ((W471 - W466) / W466)*100, "") -> 9.6483358 | AB471: =IF(MONTH(V471)<>MONTH(V470), V471, "") | AC471: =IF(ISNUMBER(AB471), (INDEX(W:W, MATCH(EOMONTH(V471, 0), V:V, 1)) / W471 - 1) * 100, "") | AD471: 1.0176517 | AE471: 9.5796248 | AG471: 45463 | AH471: 45470 | AI471: 358.4 | AK471: {=INDEX($AG$466:$AG$918, ROWS($AG$466:$AG$918) - ROW() + ROW($AG$466))} -> 44749 | AL471: {=INDEX($AH$466:$AH$918, ROWS($AH$466:$AH$918) - ROW() + ROW($AH$466))} -> 44770 | AM471: {=INDEX($AI$466:$AI$918, ROWS($AI$466:$AI$918) - ROW() + ROW($AI$466))} -> 141.1 | AO471: =((AM471-AM470)/AM470)*100 -> 1.5838733 | AP471: =WEEKDAY(AK471, 2) -> 4 | AQ471: =IF(AP471=4, ((AM471 - AM466) / AM466)*100, "") -> -1.017187 | AR471: =IF(MONTH(AL471)<>MONTH(AL470), AL471, "") | AS471: =IF(ISNUMBER(AR471), (INDEX(AM:AM, MATCH(EOMONTH(AL471, 0), AL:AL, 1)) / AM471 - 1) * 100, "") | AT471: 3.2484076 | AU471: 2.4005054 | AW471: 45463 | AX471: 45470 | AY471: 311.75 | BA471: {=INDEX($AW$466:$AW$918, ROWS($AW$466:$AW$918) - ROW() + ROW($AW$466))} -> 44749 | BB471: {=INDEX($AX$466:$AX$918, ROWS($AX$466:$AX$918) - ROW() + ROW($AX$466))} -> 44770 | BC471: {=INDEX($AY$466:$AY$918, ROWS($AY$466:$AY$918) - ROW() + ROW($AY$466))} -> 236.95 | BE471: =((BC471-BC470)/BC470)*100 -> 2.4427151 | BF471: =WEEKDAY(BA471, 2) -> 4 | BG471: =IF(BF471=4, ((BC471 - BC466) / BC466)*100, "") -> 1.4557911 | BH471: =IF(MONTH(BB471)<>MONTH(BB470), BB471, "") | BI471: =IF(ISNUMBER(BH471), (INDEX(BC:BC, MATCH(EOMONTH(BB471, 0), BB:BB, 1)) / BC471 - 1) * 100, "") | BJ471: 0.14405071 | BK471: 8.540203 | BM471: 45463 | BN471: 45470 | BO471: 1458.85 | BQ471: {=INDEX($AW$466:$AW$918, ROWS($AW$466:$AW$918) - ROW() + ROW($AW$466))} -> 44749 | BR471: {=INDEX($AX$466:$AX$918, ROWS($AX$466:$AX$918) - ROW() + ROW($AX$466))} -> 44770 | BS471: {=INDEX($BO$466:$BO$918, ROWS($BO$466:$BO$918) - ROW() + ROW($BO$466))} -> 1129.15 | BU471: =((BS471-BS470)/BS470)*100 -> 0.76298412 | BV471: =WEEKDAY(BQ471, 2) -> 4 | BW471: =IF(BV471=4, ((BS471 - BS466) / BS466)*100, "") -> 3.9637234 | BX471: =IF(MONTH(BR471)<>MONTH(BR470), BR471, "") | BY471: =IF(ISNUMBER(BX471), (INDEX(BS:BS, MATCH(EOMONTH(BR471, 0), BR:BR, 1)) / BS471 - 1) * 100, "") | BZ471: -0.4803074 | CA471: -0.54978619 | CC471: 45463 | CD471: 45470 | CE471: 1864.8 | CG471: {=INDEX($AW$466:$AW$918, ROWS($AW$466:$AW$918) - ROW() + ROW($AW$466))} -> 44749 | CH471: {=INDEX($AX$466:$AX$918, ROWS($AX$466:$AX$918) - ROW() + ROW($AX$466))} -> 44770 | CI471: {=INDEX($CE$466:$CE$918, ROWS($CE$466:$CE$918) - ROW() + ROW($CE$466))} -> 1453.5 | CK471: =((CI471-CI470)/CI470)*100 -> 5.1964971 | CL471: =WEEKDAY(CG471, 2) -> 4 | CM471: =IF(CL471=4, ((CI471 - CI466) / CI466)*100, "") -> 13.34659 | CN471: =IF(MONTH(CH471)<>MONTH(CH470), CH471, "") | CO471: =IF(ISNUMBER(CN471), (INDEX(CI:CI, MATCH(EOMONTH(CH471, 0), CH:CH, 1)) / CI471 - 1) * 100, "") | CP471: 5.1863916 | CQ471: 13.204534 | CS471: 45463 | CT471: 45470 | CU471: 874.55 | CW471: {=INDEX($AW$466:$AW$918, ROWS($AW$466:$AW$918) - ROW() + ROW($AW$466))} -> 44749 | CX471: {=INDEX($AX$466:$AX$918, ROWS($AX$466:$AX$918) - ROW() + ROW($AX$466))} -> 44770 | CY471: {=INDEX($CU$466:$CU$918, ROWS($CU$466:$CU$918) - ROW() + ROW($CU$466))} -> 337.4 | DA471: =((CY471-CY470)/CY470)*100 -> 2.0414335 | DB471: =WEEKDAY(CW471, 2) -> 4 | DC471: =IF(DB471=4, ((CY471 - CY466) / CY466)*100, "") -> 7.6236045 | DD471: =IF(MONTH(CX471)<>MONTH(CX470), CX471, "") | DE471: =IF(ISNUMBER(DD471), (INDEX(CY:CY, MATCH(EOMONTH(CX471, 0), CX:CX, 1)) / CY471 - 1) * 100, "") | DF471: 2.2148058 | DG471: 7.739047 | DI471: 45463 | DJ471: 45470 | DK471: 627.1 | DM471: {=INDEX($AW$466:$AW$918, ROWS($AW$466:$AW$918) - ROW() + ROW($AW$466))} -> 44749 | DN471: {=INDEX($AX$466:$AX$918, ROWS($AX$466:$AX$918) - ROW() + ROW($AX$466))} -> 44770 | DO471: {=INDEX($DK$466:$DK$918, ROWS($DK$466:$DK$918) - ROW() + ROW($DK$466))} -> 328.8 | DQ471: =((DO471-DO470)/DO470)*100 -> 2.366127 | DR471: =WEEKDAY(DM471, 2) -> 4 | DS471: =IF(DR471=4, ((DO471 - DO466) / DO466)*100, "") -> 6.4594463 | DT471: =IF(MONTH(DN471)<>MONTH(DN470), DN471, "") | DU471: =IF(ISNUMBER(DT471), (INDEX(DO:DO, MATCH(EOMONTH(DN471, 0), DN:DN, 1)) / DO471 - 1) * 100, "") | DV471: 1.3490241 | DW471: -29.801193
A472: 45462 | B472: 45470 | C472: 157.5 | E472: {=INDEX($A$466:$A$918, ROWS($A$466:$A$918) - ROW() + ROW($A$466))} -> 44750 | F472: {=INDEX($B$466:$B$918, ROWS($B$466:$B$918) - ROW() + ROW($B$466))} -> 44770 | G472: {=INDEX($C$466:$C$918, ROWS($C$466:$C$918) - ROW() + ROW($C$466))} -> 145.2 | I472: =((G472-G471)/G471)*100 -> 0.10341262 | J472: =WEEKDAY(E472, 2) -> 5 | K472: =IF(J472=4, ((G472 - G467) / G467)*100, "") | L472: =IF(MONTH(F472)<>MONTH(F471), F472, "") | M472: =IF(ISNUMBER(L472), (INDEX(G:G, MATCH(EOMONTH(F472, 0), F:F, 1)) / G472 - 1) * 100, "") | N472: -0.068989307 | Q472: 45462 | R472: 45470 | S472: 38810.45 | U472: {=INDEX($Q$466:$Q$918, ROWS($Q$466:$Q$918) - ROW() + ROW($Q$466))} -> 44750 | V472: {=INDEX($R$466:$R$918, ROWS($R$466:$R$918) - ROW() + ROW($R$466))} -> 44770 | W472: {=INDEX($S$466:$S$918, ROWS($S$466:$S$918) - ROW() + ROW($S$466))} -> 43732.75 | Y472: =((W472-W471)/W471)*100 -> -0.73271132 | Z472: =WEEKDAY(U472, 2) -> 5 | AA472: =IF(Z472=4, ((W472 - W467) / W467)*100, "") | AB472: =IF(MONTH(V472)<>MONTH(V471), V472, "") | AC472: =IF(ISNUMBER(AB472), (INDEX(W:W, MATCH(EOMONTH(V472, 0), V:V, 1)) / W472 - 1) * 100, "") | AD472: -0.99649432 | AG472: 45462 | AH472: 45470 | AI472: 363.2 | AK472: {=INDEX($AG$466:$AG$918, ROWS($AG$466:$AG$918) - ROW() + ROW($AG$466))} -> 44750 | AL472: {=INDEX($AH$466:$AH$918, ROWS($AH$466:$AH$918) - ROW() + ROW($AH$466))} -> 44770 | AM472: {=INDEX($AI$466:$AI$918, ROWS($AI$466:$AI$918) - ROW() + ROW($AI$466))} -> 144.2 | AO472: =((AM472-AM471)/AM471)*100 -> 2.1970234 | AP472: =WEEKDAY(AK472, 2) -> 5 | AQ472: =IF(AP472=4, ((AM472 - AM467) / AM467)*100, "") | AR472: =IF(MONTH(AL472)<>MONTH(AL471), AL472, "") | AS472: =IF(ISNUMBER(AR472), (INDEX(AM:AM, MATCH(EOMONTH(AL472, 0), AL:AL, 1)) / AM472 - 1) * 100, "") | AT472: 1.1104257 | AW472: 45462 | AX472: 45470 | AY472: 309.2 | BA472: {=INDEX($AW$466:$AW$918, ROWS($AW$466:$AW$918) - ROW() + ROW($AW$466))} -> 44750 | BB472: {=INDEX($AX$466:$AX$918, ROWS($AX$466:$AX$918) - ROW() + ROW($AX$466))} -> 44770 | BC472: {=INDEX($AY$466:$AY$918, ROWS($AY$466:$AY$918) - ROW() + ROW($AY$466))} -> 236.8 | BE472: =((BC472-BC471)/BC471)*100 -> -0.063304495 | BF472: =WEEKDAY(BA472, 2) -> 5 | BG472: =IF(BF472=4, ((BC472 - BC467) / BC467)*100, "") | BH472: =IF(MONTH(BB472)<>MONTH(BB471), BB472, "") | BI472: =IF(ISNUMBER(BH472), (INDEX(BC:BC, MATCH(EOMONTH(BB472, 0), BB:BB, 1)) / BC472 - 1) * 100, "") | BJ472: 1.9490794 | BM472: 45462 | BN472: 45470 | BO472: 1448.75 | BQ472: {=INDEX($AW$466:$AW$918, ROWS($AW$466:$AW$918) - ROW() + ROW($AW$466))} -> 44750 | BR472: {=INDEX($AX$466:$AX$918, ROWS($AX$466:$AX$918) - ROW() + ROW($AX$466))} -> 44770 | BS472: {=INDEX($BO$466:$BO$918, ROWS($BO$466:$BO$918) - ROW() + ROW($BO$466))} -> 1147.7 | BU472: =((BS472-BS471)/BS471)*100 -> 1.6428287 | BV472: =WEEKDAY(BQ472, 2) -> 5 | BW472: =IF(BV472=4, ((BS472 - BS467) / BS467)*100, "") | BX472: =IF(MONTH(BR472)<>MONTH(BR471), BR472, "") | BY472: =IF(ISNUMBER(BX472), (INDEX(BS:BS, MATCH(EOMONTH(BR472, 0), BR:BR, 1)) / BS472 - 1) * 100, "") | BZ472: -1.009126 | CC472: 45462 | CD472: 45470 | CE472: 1856.65 | CG472: {=INDEX($AW$466:$AW$918, ROWS($AW$466:$AW$918) - ROW() + ROW($AW$466))} -> 44750 | CH472: {=INDEX($AX$466:$AX$918, ROWS($AX$466:$AX$918) - ROW() + ROW($AX$466))} -> 44770 | CI472: {=INDEX($CE$466:$CE$918, ROWS($CE$466:$CE$918) - ROW() + ROW($CE$466))} -> 1437.1 | CK472: =((CI472-CI471)/CI471)*100 -> -1.128311 | CL472: =WEEKDAY(CG472, 2) -> 5 | CM472: =IF(CL472=4, ((CI472 - CI467) / CI467)*100, "") | CN472: =IF(MONTH(CH472)<>MONTH(CH471), CH472, "") | CO472: =IF(ISNUMBER(CN472), (INDEX(CI:CI, MATCH(EOMONTH(CH472, 0), CH:CH, 1)) / CI472 - 1) * 100, "") | CP472: -1.3419124 | CS472: 45462 | CT472: 45470 | CU472: 859.9 | CW472: {=INDEX($AW$466:$AW$918, ROWS($AW$466:$AW$918) - ROW() + ROW($AW$466))} -> 44750 | CX472: {=INDEX($AX$466:$AX$918, ROWS($AX$466:$AX$918) - ROW() + ROW($AX$466))} -> 44770 | CY472: {=INDEX($CU$466:$CU$918, ROWS($CU$466:$CU$918) - ROW() + ROW($CU$466))} -> 340.75 | DA472: =((CY472-CY471)/CY471)*100 -> 0.99288678 | DB472: =WEEKDAY(CW472, 2) -> 5 | DC472: =IF(DB472=4, ((CY472 - CY467) / CY467)*100, "") | DD472: =IF(MONTH(CX472)<>MONTH(CX471), CX472, "") | DE472: =IF(ISNUMBER(DD472), (INDEX(CY:CY, MATCH(EOMONTH(CX472, 0), CX:CX, 1)) / CY472 - 1) * 100, "") | DF472: 1.0388839 | DI472: 45462 | DJ472: 45470 | DK472: 615.65 | DM472: {=INDEX($AW$466:$AW$918, ROWS($AW$466:$AW$918) - ROW() + ROW($AW$466))} -> 44750 | DN472: {=INDEX($AX$466:$AX$918, ROWS($AX$466:$AX$918) - ROW() + ROW($AX$466))} -> 44770 | DO472: {=INDEX($DK$466:$DK$918, ROWS($DK$466:$DK$918) - ROW() + ROW($DK$466))} -> 326.3 | DQ472: =((DO472-DO471)/DO471)*100 -> -0.76034063 | DR472: =WEEKDAY(DM472, 2) -> 5 | DS472: =IF(DR472=4, ((DO472 - DO467) / DO467)*100, "") | DT472: =IF(MONTH(DN472)<>MONTH(DN471), DN472, "") | DU472: =IF(ISNUMBER(DT472), (INDEX(DO:DO, MATCH(EOMONTH(DN472, 0), DN:DN, 1)) / DO472 - 1) * 100, "") | DV472: 4.3330501
A473: 45461 | B473: 45470 | C473: 157.85 | E473: {=INDEX($A$466:$A$918, ROWS($A$466:$A$918) - ROW() + ROW($A$466))} -> 44753 | F473: {=INDEX($B$466:$B$918, ROWS($B$466:$B$918) - ROW() + ROW($B$466))} -> 44770 | G473: {=INDEX($C$466:$C$918, ROWS($C$466:$C$918) - ROW() + ROW($C$466))} -> 148.7 | I473: =((G473-G472)/G472)*100 -> 2.4104683 | J473: =WEEKDAY(E473, 2) -> 1 | K473: =IF(J473=4, ((G473 - G468) / G468)*100, "") | L473: =IF(MONTH(F473)<>MONTH(F472), F473, "") | M473: =IF(ISNUMBER(L473), (INDEX(G:G, MATCH(EOMONTH(F473, 0), F:F, 1)) / G473 - 1) * 100, "") | N473: 2.9340697 | Q473: 45461 | R473: 45470 | S473: 38517.9 | U473: {=INDEX($Q$466:$Q$918, ROWS($Q$466:$Q$918) - ROW() + ROW($Q$466))} -> 44753 | V473: {=INDEX($R$466:$R$918, ROWS($R$466:$R$918) - ROW() + ROW($R$466))} -> 44770 | W473: {=INDEX($S$466:$S$918, ROWS($S$466:$S$918) - ROW() + ROW($S$466))} -> 43534.7 | Y473: =((W473-W472)/W472)*100 -> -0.45286427 | Z473: =WEEKDAY(U473, 2) -> 1 | AA473: =IF(Z473=4, ((W473 - W468) / W468)*100, "") | AB473: =IF(MONTH(V473)<>MONTH(V472), V473, "") | AC473: =IF(ISNUMBER(AB473), (INDEX(W:W, MATCH(EOMONTH(V473, 0), V:V, 1)) / W473 - 1) * 100, "") | AD473: -0.40527175 | AG473: 45461 | AH473: 45470 | AI473: 370.75 | AK473: {=INDEX($AG$466:$AG$918, ROWS($AG$466:$AG$918) - ROW() + ROW($AG$466))} -> 44753 | AL473: {=INDEX($AH$466:$AH$918, ROWS($AH$466:$AH$918) - ROW() + ROW($AH$466))} -> 44770 | AM473: {=INDEX($AI$466:$AI$918, ROWS($AI$466:$AI$918) - ROW() + ROW($AI$466))} -> 145 | AO473: =((AM473-AM472)/AM472)*100 -> 0.55478502 | AP473: =WEEKDAY(AK473, 2) -> 1 | AQ473: =IF(AP473=4, ((AM473 - AM468) / AM468)*100, "") | AR473: =IF(MONTH(AL473)<>MONTH(AL472), AL473, "") | AS473: =IF(ISNUMBER(AR473), (INDEX(AM:AM, MATCH(EOMONTH(AL473, 0), AL:AL, 1)) / AM473 - 1) * 100, "") | AT473: -0.12202563 | AW473: 45461 | AX473: 45470 | AY473: 319.15 | BA473: {=INDEX($AW$466:$AW$918, ROWS($AW$466:$AW$918) - ROW() + ROW($AW$466))} -> 44753 | BB473: {=INDEX($AX$466:$AX$918, ROWS($AX$466:$AX$918) - ROW() + ROW($AX$466))} -> 44770 | BC473: {=INDEX($AY$466:$AY$918, ROWS($AY$466:$AY$918) - ROW() + ROW($AY$466))} -> 235.6 | BE473: =((BC473-BC472)/BC472)*100 -> -0.50675676 | BF473: =WEEKDAY(BA473, 2) -> 1 | BG473: =IF(BF473=4, ((BC473 - BC468) / BC468)*100, "") | BH473: =IF(MONTH(BB473)<>MONTH(BB472), BB473, "") | BI473: =IF(ISNUMBER(BH473), (INDEX(BC:BC, MATCH(EOMONTH(BB473, 0), BB:BB, 1)) / BC473 - 1) * 100, "") | BJ473: 3.2592593 | BM473: 45461 | BN473: 45470 | BO473: 1473.65 | BQ473: {=INDEX($AW$466:$AW$918, ROWS($AW$466:$AW$918) - ROW() + ROW($AW$466))} -> 44753 | BR473: {=INDEX($AX$466:$AX$918, ROWS($AX$466:$AX$918) - ROW() + ROW($AX$466))} -> 44770 | BS473: {=INDEX($BO$466:$BO$918, ROWS($BO$466:$BO$918) - ROW() + ROW($BO$466))} -> 1148.2 | BU473: =((BS473-BS472)/BS472)*100 -> 0.043565392 | BV473: =WEEKDAY(BQ473, 2) -> 1 | BW473: =IF(BV473=4, ((BS473 - BS468) / BS468)*100, "") | BX473: =IF(MONTH(BR473)<>MONTH(BR472), BR473, "") | BY473: =IF(ISNUMBER(BX473), (INDEX(BS:BS, MATCH(EOMONTH(BR473, 0), BR:BR, 1)) / BS473 - 1) * 100, "") | BZ473: -1.0105487 | CC473: 45461 | CD473: 45470 | CE473: 1889.3 | CG473: {=INDEX($AW$466:$AW$918, ROWS($AW$466:$AW$918) - ROW() + ROW($AW$466))} -> 44753 | CH473: {=INDEX($AX$466:$AX$918, ROWS($AX$466:$AX$918) - ROW() + ROW($AX$466))} -> 44770 | CI473: {=INDEX($CE$466:$CE$918, ROWS($CE$466:$CE$918) - ROW() + ROW($CE$466))} -> 1453.7 | CK473: =((CI473-CI472)/CI472)*100 -> 1.155104 | CL473: =WEEKDAY(CG473, 2) -> 1 | CM473: =IF(CL473=4, ((CI473 - CI468) / CI468)*100, "") | CN473: =IF(MONTH(CH473)<>MONTH(CH472), CH473, "") | CO473: =IF(ISNUMBER(CN473), (INDEX(CI:CI, MATCH(EOMONTH(CH473, 0), CH:CH, 1)) / CI473 - 1) * 100, "") | CP473: 1.1753217 | CS473: 45461 | CT473: 45470 | CU473: 881.05 | CW473: {=INDEX($AW$466:$AW$918, ROWS($AW$466:$AW$918) - ROW() + ROW($AW$466))} -> 44753 | CX473: {=INDEX($AX$466:$AX$918, ROWS($AX$466:$AX$918) - ROW() + ROW($AX$466))} -> 44770 | CY473: {=INDEX($CU$466:$CU$918, ROWS($CU$466:$CU$918) - ROW() + ROW($CU$466))} -> 346.55 | DA473: =((CY473-CY472)/CY472)*100 -> 1.7021277 | DB473: =WEEKDAY(CW473, 2) -> 1 | DC473: =IF(DB473=4, ((CY473 - CY468) / CY468)*100, "") | DD473: =IF(MONTH(CX473)<>MONTH(CX472), CX473, "") | DE473: =IF(ISNUMBER(DD473), (INDEX(CY:CY, MATCH(EOMONTH(CX473, 0), CX:CX, 1)) / CY473 - 1) * 100, "") | DF473: 1.6891892 | DI473: 45461 | DJ473: 45470 | DK473: 631.15 | DM473: {=INDEX($AW$466:$AW$918, ROWS($AW$466:$AW$918) - ROW() + ROW($AW$466))} -> 44753 | DN473: {=INDEX($AX$466:$AX$918, ROWS($AX$466:$AX$918) - ROW() + ROW($AX$466))} -> 44770 | DO473: {=INDEX($DK$466:$DK$918, ROWS($DK$466:$DK$918) - ROW() + ROW($DK$466))} -> 317.1 | DQ473: =((DO473-DO472)/DO472)*100 -> -2.8194913 | DR473: =WEEKDAY(DM473, 2) -> 1 | DS473: =IF(DR473=4, ((DO473 - DO468) / DO468)*100, "") | DT473: =IF(MONTH(DN473)<>MONTH(DN472), DN473, "") | DU473: =IF(ISNUMBER(DT473), (INDEX(DO:DO, MATCH(EOMONTH(DN473, 0), DN:DN, 1)) / DO473 - 1) * 100, "") | DV473: 1.3029316
A474: 45457 | B474: 45470 | C474: 151.8 | E474: {=INDEX($A$466:$A$918, ROWS($A$466:$A$918) - ROW() + ROW($A$466))} -> 44754 | F474: {=INDEX($B$466:$B$918, ROWS($B$466:$B$918) - ROW() + ROW($B$466))} -> 44770 | G474: {=INDEX($C$466:$C$918, ROWS($C$466:$C$918) - ROW() + ROW($C$466))} -> 148.3 | I474: =((G474-G473)/G473)*100 -> -0.26899798 | J474: =WEEKDAY(E474, 2) -> 2 | K474: =IF(J474=4, ((G474 - G469) / G469)*100, "") | L474: =IF(MONTH(F474)<>MONTH(F473), F474, "") | M474: =IF(ISNUMBER(L474), (INDEX(G:G, MATCH(EOMONTH(F474, 0), F:F, 1)) / G474 - 1) * 100, "") | N474: -0.46948357 | Q474: 45457 | R474: 45470 | S474: 38424.1 | U474: {=INDEX($Q$466:$Q$918, ROWS($Q$466:$Q$918) - ROW() + ROW($Q$466))} -> 44754 | V474: {=INDEX($R$466:$R$918, ROWS($R$466:$R$918) - ROW() + ROW($R$466))} -> 44770 | W474: {=INDEX($S$466:$S$918, ROWS($S$466:$S$918) - ROW() + ROW($S$466))} -> 43236.7 | Y474: =((W474-W473)/W473)*100 -> -0.68451144 | Z474: =WEEKDAY(U474, 2) -> 2 | AA474: =IF(Z474=4, ((W474 - W469) / W469)*100, "") | AB474: =IF(MONTH(V474)<>MONTH(V473), V474, "") | AC474: =IF(ISNUMBER(AB474), (INDEX(W:W, MATCH(EOMONTH(V474, 0), V:V, 1)) / W474 - 1) * 100, "") | AD474: -0.71487658 | AG474: 45457 | AH474: 45470 | AI474: 368.45 | AK474: {=INDEX($AG$466:$AG$918, ROWS($AG$466:$AG$918) - ROW() + ROW($AG$466))} -> 44754 | AL474: {=INDEX($AH$466:$AH$918, ROWS($AH$466:$AH$918) - ROW() + ROW($AH$466))} -> 44770 | AM474: {=INDEX($AI$466:$AI$918, ROWS($AI$466:$AI$918) - ROW() + ROW($AI$466))} -> 147.15 | AO474: =((AM474-AM473)/AM473)*100 -> 1.4827586 | AP474: =WEEKDAY(AK474, 2) -> 2 | AQ474: =IF(AP474=4, ((AM474 - AM469) / AM469)*100, "") | AR474: =IF(MONTH(AL474)<>MONTH(AL473), AL474, "") | AS474: =IF(ISNUMBER(AR474), (INDEX(AM:AM, MATCH(EOMONTH(AL474, 0), AL:AL, 1)) / AM474 - 1) * 100, "") | AT474: -2.3824068 | AW474: 45457 | AX474: 45470 | AY474: 309.9 | BA474: {=INDEX($AW$466:$AW$918, ROWS($AW$466:$AW$918) - ROW() + ROW($AW$466))} -> 44754 | BB474: {=INDEX($AX$466:$AX$918, ROWS($AX$466:$AX$918) - ROW() + ROW($AX$466))} -> 44770 | BC474: {=INDEX($AY$466:$AY$918, ROWS($AY$466:$AY$918) - ROW() + ROW($AY$466))} -> 232.45 | BE474: =((BC474-BC473)/BC473)*100 -> -1.3370119 | BF474: =WEEKDAY(BA474, 2) -> 2 | BG474: =IF(BF474=4, ((BC474 - BC469) / BC469)*100, "") | BH474: =IF(MONTH(BB474)<>MONTH(BB473), BB474, "") | BI474: =IF(ISNUMBER(BH474), (INDEX(BC:BC, MATCH(EOMONTH(BB474, 0), BB:BB, 1)) / BC474 - 1) * 100, "") | BJ474: -1.9471203 | BM474: 45457 | BN474: 45470 | BO474: 1469.6 | BQ474: {=INDEX($AW$466:$AW$918, ROWS($AW$466:$AW$918) - ROW() + ROW($AW$466))} -> 44754 | BR474: {=INDEX($AX$466:$AX$918, ROWS($AX$466:$AX$918) - ROW() + ROW($AX$466))} -> 44770 | BS474: {=INDEX($BO$466:$BO$918, ROWS($BO$466:$BO$918) - ROW() + ROW($BO$466))} -> 1140.95 | BU474: =((BS474-BS473)/BS473)*100 -> -0.6314231 | BV474: =WEEKDAY(BQ474, 2) -> 2 | BW474: =IF(BV474=4, ((BS474 - BS469) / BS469)*100, "") | BX474: =IF(MONTH(BR474)<>MONTH(BR473), BR474, "") | BY474: =IF(ISNUMBER(BX474), (INDEX(BS:BS, MATCH(EOMONTH(BR474, 0), BR:BR, 1)) / BS474 - 1) * 100, "") | BZ474: 0.34028835 | CC474: 45457 | CD474: 45470 | CE474: 1878.25 | CG474: {=INDEX($AW$466:$AW$918, ROWS($AW$466:$AW$918) - ROW() + ROW($AW$466))} -> 44754 | CH474: {=INDEX($AX$466:$AX$918, ROWS($AX$466:$AX$918) - ROW() + ROW($AX$466))} -> 44770 | CI474: {=INDEX($CE$466:$CE$918, ROWS($CE$466:$CE$918) - ROW() + ROW($CE$466))} -> 1437.6 | CK474: =((CI474-CI473)/CI473)*100 -> -1.1075187 | CL474: =WEEKDAY(CG474, 2) -> 2 | CM474: =IF(CL474=4, ((CI474 - CI469) / CI469)*100, "") | CN474: =IF(MONTH(CH474)<>MONTH(CH473), CH474, "") | CO474: =IF(ISNUMBER(CN474), (INDEX(CI:CI, MATCH(EOMONTH(CH474, 0), CH:CH, 1)) / CI474 - 1) * 100, "") | CP474: -0.85143054 | CS474: 45457 | CT474: 45470 | CU474: 878.65 | CW474: {=INDEX($AW$466:$AW$918, ROWS($AW$466:$AW$918) - ROW() + ROW($AW$466))} -> 44754 | CX474: {=INDEX($AX$466:$AX$918, ROWS($AX$466:$AX$918) - ROW() + ROW($AX$466))} -> 44770 | CY474: {=INDEX($CU$466:$CU$918, ROWS($CU$466:$CU$918) - ROW() + ROW($CU$466))} -> 347.7 | DA474: =((CY474-CY473)/CY473)*100 -> 0.33184245 | DB474: =WEEKDAY(CW474, 2) -> 2 | DC474: =IF(DB474=4, ((CY474 - CY469) / CY469)*100, "") | DD474: =IF(MONTH(CX474)<>MONTH(CX473), CX474, "") | DE474: =IF(ISNUMBER(DD474), (INDEX(CY:CY, MATCH(EOMONTH(CX474, 0), CX:CX, 1)) / CY474 - 1) * 100, "") | DF474: 0.18777986 | DI474: 45457 | DJ474: 45470 | DK474: 627.8 | DM474: {=INDEX($AW$466:$AW$918, ROWS($AW$466:$AW$918) - ROW() + ROW($AW$466))} -> 44754 | DN474: {=INDEX($AX$466:$AX$918, ROWS($AX$466:$AX$918) - ROW() + ROW($AX$466))} -> 44770 | DO474: {=INDEX($DK$466:$DK$918, ROWS($DK$466:$DK$918) - ROW() + ROW($DK$466))} -> 309.6 | DQ474: =((DO474-DO473)/DO473)*100 -> -2.3651845 | DR474: =WEEKDAY(DM474, 2) -> 2 | DS474: =IF(DR474=4, ((DO474 - DO469) / DO469)*100, "") | DT474: =IF(MONTH(DN474)<>MONTH(DN473), DN474, "") | DU474: =IF(ISNUMBER(DT474), (INDEX(DO:DO, MATCH(EOMONTH(DN474, 0), DN:DN, 1)) / DO474 - 1) * 100, "") | DV474: -1.6881029
A475: 45456 | B475: 45470 | C475: 148.85 | E475: {=INDEX($A$466:$A$918, ROWS($A$466:$A$918) - ROW() + ROW($A$466))} -> 44755 | F475: {=INDEX($B$466:$B$918, ROWS($B$466:$B$918) - ROW() + ROW($B$466))} -> 44770 | G475: {=INDEX($C$466:$C$918, ROWS($C$466:$C$918) - ROW() + ROW($C$466))} -> 150.65 | I475: =((G475-G474)/G474)*100 -> 1.5846258 | J475: =WEEKDAY(E475, 2) -> 3 | K475: =IF(J475=4, ((G475 - G470) / G470)*100, "") | L475: =IF(MONTH(F475)<>MONTH(F474), F475, "") | M475: =IF(ISNUMBER(L475), (INDEX(G:G, MATCH(EOMONTH(F475, 0), F:F, 1)) / G475 - 1) * 100, "") | N475: 1.5498652 | Q475: 45456 | R475: 45470 | S475: 38748.35 | U475: {=INDEX($Q$466:$Q$918, ROWS($Q$466:$Q$918) - ROW() + ROW($Q$466))} -> 44755 | V475: {=INDEX($R$466:$R$918, ROWS($R$466:$R$918) - ROW() + ROW($R$466))} -> 44770 | W475: {=INDEX($S$466:$S$918, ROWS($S$466:$S$918) - ROW() + ROW($S$466))} -> 43516.8 | Y475: =((W475-W474)/W474)*100 -> 0.64782927 | Z475: =WEEKDAY(U475, 2) -> 3 | AA475: =IF(Z475=4, ((W475 - W470) / W470)*100, "") | AB475: =IF(MONTH(V475)<>MONTH(V474), V475, "") | AC475: =IF(ISNUMBER(AB475), (INDEX(W:W, MATCH(EOMONTH(V475, 0), V:V, 1)) / W475 - 1) * 100, "") | AD475: 0.95349493 | AG475: 45456 | AH475: 45470 | AI475: 370.25 | AK475: {=INDEX($AG$466:$AG$918, ROWS($AG$466:$AG$918) - ROW() + ROW($AG$466))} -> 44755 | AL475: {=INDEX($AH$466:$AH$918, ROWS($AH$466:$AH$918) - ROW() + ROW($AH$466))} -> 44770 | AM475: {=INDEX($AI$466:$AI$918, ROWS($AI$466:$AI$918) - ROW() + ROW($AI$466))} -> 148.7 | AO475: =((AM475-AM474)/AM474)*100 -> 1.0533469 | AP475: =WEEKDAY(AK475, 2) -> 3 | AQ475: =IF(AP475=4, ((AM475 - AM470) / AM470)*100, "") | AR475: =IF(MONTH(AL475)<>MONTH(AL474), AL475, "") | AS475: =IF(ISNUMBER(AR475), (INDEX(AM:AM, MATCH(EOMONTH(AL475, 0), AL:AL, 1)) / AM475 - 1) * 100, "") | AT475: -0.8135169 | AW475: 45456 | AX475: 45470 | AY475: 302.05 | BA475: {=INDEX($AW$466:$AW$918, ROWS($AW$466:$AW$918) - ROW() + ROW($AW$466))} -> 44755 | BB475: {=INDEX($AX$466:$AX$918, ROWS($AX$466:$AX$918) - ROW() + ROW($AX$466))} -> 44770 | BC475: {=INDEX($AY$466:$AY$918, ROWS($AY$466:$AY$918) - ROW() + ROW($AY$466))} -> 233.6 | BE475: =((BC475-BC474)/BC474)*100 -> 0.49473005 | BF475: =WEEKDAY(BA475, 2) -> 3 | BG475: =IF(BF475=4, ((BC475 - BC470) / BC470)*100, "") | BH475: =IF(MONTH(BB475)<>MONTH(BB474), BB475, "") | BI475: =IF(ISNUMBER(BH475), (INDEX(BC:BC, MATCH(EOMONTH(BB475, 0), BB:BB, 1)) / BC475 - 1) * 100, "") | BJ475: 0.02090301 | BM475: 45456 | BN475: 45470 | BO475: 1450.85 | BQ475: {=INDEX($AW$466:$AW$918, ROWS($AW$466:$AW$918) - ROW() + ROW($AW$466))} -> 44755 | BR475: {=INDEX($AX$466:$AX$918, ROWS($AX$466:$AX$918) - ROW() + ROW($AX$466))} -> 44770 | BS475: {=INDEX($BO$466:$BO$918, ROWS($BO$466:$BO$918) - ROW() + ROW($BO$466))} -> 1143.05 | BU475: =((BS475-BS474)/BS474)*100 -> 0.18405715 | BV475: =WEEKDAY(BQ475, 2) -> 3 | BW475: =IF(BV475=4, ((BS475 - BS470) / BS470)*100, "") | BX475: =IF(MONTH(BR475)<>MONTH(BR474), BR475, "") | BY475: =IF(ISNUMBER(BX475), (INDEX(BS:BS, MATCH(EOMONTH(BR475, 0), BR:BR, 1)) / BS475 - 1) * 100, "") | BZ475: -0.09817046 | CC475: 45456 | CD475: 45470 | CE475: 1904.65 | CG475: {=INDEX($AW$466:$AW$918, ROWS($AW$466:$AW$918) - ROW() + ROW($AW$466))} -> 44755 | CH475: {=INDEX($AX$466:$AX$918, ROWS($AX$466:$AX$918) - ROW() + ROW($AX$466))} -> 44770 | CI475: {=INDEX($CE$466:$CE$918, ROWS($CE$466:$CE$918) - ROW() + ROW($CE$466))} -> 1479.05 | CK475: =((CI475-CI474)/CI474)*100 -> 2.8832777 | CL475: =WEEKDAY(CG475, 2) -> 3 | CM475: =IF(CL475=4, ((CI475 - CI470) / CI470)*100, "") | CN475: =IF(MONTH(CH475)<>MONTH(CH474), CH475, "") | CO475: =IF(ISNUMBER(CN475), (INDEX(CI:CI, MATCH(EOMONTH(CH475, 0), CH:CH, 1)) / CI475 - 1) * 100, "") | CP475: 2.7118173 | CS475: 45456 | CT475: 45470 | CU475: 875.4 | CW475: {=INDEX($AW$466:$AW$918, ROWS($AW$466:$AW$918) - ROW() + ROW($AW$466))} -> 44755 | CX475: {=INDEX($AX$466:$AX$918, ROWS($AX$466:$AX$918) - ROW() + ROW($AX$466))} -> 44770 | CY475: {=INDEX($CU$466:$CU$918, ROWS($CU$466:$CU$918) - ROW() + ROW($CU$466))} -> 347.85 | DA475: =((CY475-CY474)/CY474)*100 -> 0.043140638 | DB475: =WEEKDAY(CW475, 2) -> 3 | DC475: =IF(DB475=4, ((CY475 - CY470) / CY470)*100, "") | DD475: =IF(MONTH(CX475)<>MONTH(CX474), CX475, "") | DE475: =IF(ISNUMBER(DD475), (INDEX(CY:CY, MATCH(EOMONTH(CX475, 0), CX:CX, 1)) / CY475 - 1) * 100, "") | DF475: 0.18742791 | DI475: 45456 | DJ475: 45470 | DK475: 620.6 | DM475: {=INDEX($AW$466:$AW$918, ROWS($AW$466:$AW$918) - ROW() + ROW($AW$466))} -> 44755 | DN475: {=INDEX($AX$466:$AX$918, ROWS($AX$466:$AX$918) - ROW() + ROW($AX$466))} -> 44770 | DO475: {=INDEX($DK$466:$DK$918, ROWS($DK$466:$DK$918) - ROW() + ROW($DK$466))} -> 311.75 | DQ475: =((DO475-DO474)/DO474)*100 -> 0.69444444 | DR475: =WEEKDAY(DM475, 2) -> 3 | DS475: =IF(DR475=4, ((DO475 - DO470) / DO470)*100, "") | DT475: =IF(MONTH(DN475)<>MONTH(DN474), DN475, "") | DU475: =IF(ISNUMBER(DT475), (INDEX(DO:DO, MATCH(EOMONTH(DN475, 0), DN:DN, 1)) / DO475 - 1) * 100, "") | DV475: 1.0902153
A476: 45455 | B476: 45470 | C476: 149.9 | E476: {=INDEX($A$466:$A$918, ROWS($A$466:$A$918) - ROW() + ROW($A$466))} -> 44756 | F476: {=INDEX($B$466:$B$918, ROWS($B$466:$B$918) - ROW() + ROW($B$466))} -> 44770 | G476: {=INDEX($C$466:$C$918, ROWS($C$466:$C$918) - ROW() + ROW($C$466))} -> 150.45 | I476: =((G476-G475)/G475)*100 -> -0.13275805 | J476: =WEEKDAY(E476, 2) -> 4 | K476: =IF(J476=4, ((G476 - G471) / G471)*100, "") -> 3.7228542 | L476: =IF(MONTH(F476)<>MONTH(F475), F476, "") | M476: =IF(ISNUMBER(L476), (INDEX(G:G, MATCH(EOMONTH(F476, 0), F:F, 1)) / G476 - 1) * 100, "") | N476: -0.2986065 | O476: 3.6564333 | Q476: 45455 | R476: 45470 | S476: 38548.4 | U476: {=INDEX($Q$466:$Q$918, ROWS($Q$466:$Q$918) - ROW() + ROW($Q$466))} -> 44756 | V476: {=INDEX($R$466:$R$918, ROWS($R$466:$R$918) - ROW() + ROW($R$466))} -> 44770 | W476: {=INDEX($S$466:$S$918, ROWS($S$466:$S$918) - ROW() + ROW($S$466))} -> 43710.95 | Y476: =((W476-W475)/W475)*100 -> 0.44614953 | Z476: =WEEKDAY(U476, 2) -> 4 | AA476: =IF(Z476=4, ((W476 - W471) / W471)*100, "") -> -0.7821943 | AB476: =IF(MONTH(V476)<>MONTH(V475), V476, "") | AC476: =IF(ISNUMBER(AB476), (INDEX(W:W, MATCH(EOMONTH(V476, 0), V:V, 1)) / W476 - 1) * 100, "") | AD476: 0.42448569 | AE476: -0.74964273 | AG476: 45455 | AH476: 45470 | AI476: 371.95 | AK476: {=INDEX($AG$466:$AG$918, ROWS($AG$466:$AG$918) - ROW() + ROW($AG$466))} -> 44756 | AL476: {=INDEX($AH$466:$AH$918, ROWS($AH$466:$AH$918) - ROW() + ROW($AH$466))} -> 44770 | AM476: {=INDEX($AI$466:$AI$918, ROWS($AI$466:$AI$918) - ROW() + ROW($AI$466))} -> 148.35 | AO476: =((AM476-AM475)/AM475)*100 -> -0.23537323 | AP476: =WEEKDAY(AK476, 2) -> 4 | AQ476: =IF(AP476=4, ((AM476 - AM471) / AM471)*100, "") -> 5.1381999 | AR476: =IF(MONTH(AL476)<>MONTH(AL475), AL476, "") | AS476: =IF(ISNUMBER(AR476), (INDEX(AM:AM, MATCH(EOMONTH(AL476, 0), AL:AL, 1)) / AM476 - 1) * 100, "") | AT476: 0.3785489 | AU476: -1.8507094 | AW476: 45455 | AX476: 45470 | AY476: 291.15 | BA476: {=INDEX($AW$466:$AW$918, ROWS($AW$466:$AW$918) - ROW() + ROW($AW$466))} -> 44756 | BB476: {=INDEX($AX$466:$AX$918, ROWS($AX$466:$AX$918) - ROW() + ROW($AX$466))} -> 44770 | BC476: {=INDEX($AY$466:$AY$918, ROWS($AY$466:$AY$918) - ROW() + ROW($AY$466))} -> 237.55 | BE476: =((BC476-BC475)/BC475)*100 -> 1.6909247 | BF476: =WEEKDAY(BA476, 2) -> 4 | BG476: =IF(BF476=4, ((BC476 - BC471) / BC471)*100, "") -> 0.25321798 | BH476: =IF(MONTH(BB476)<>MONTH(BB475), BB476, "") | BI476: =IF(ISNUMBER(BH476), (INDEX(BC:BC, MATCH(EOMONTH(BB476, 0), BB:BB, 1)) / BC476 - 1) * 100, "") | BJ476: 1.6858238 | BK476: 4.9841772 | BM476: 45455 | BN476: 45470 | BO476: 1458.95 | BQ476: {=INDEX($AW$466:$AW$918, ROWS($AW$466:$AW$918) - ROW() + ROW($AW$466))} -> 44756 | BR476: {=INDEX($AX$466:$AX$918, ROWS($AX$466:$AX$918) - ROW() + ROW($AX$466))} -> 44770 | BS476: {=INDEX($BO$466:$BO$918, ROWS($BO$466:$BO$918) - ROW() + ROW($BO$466))} -> 1139.25 | BU476: =((BS476-BS475)/BS475)*100 -> -0.3324439 | BV476: =WEEKDAY(BQ476, 2) -> 4 | BW476: =IF(BV476=4, ((BS476 - BS471) / BS471)*100, "") -> 0.89447815 | BX476: =IF(MONTH(BR476)<>MONTH(BR475), BR476, "") | BY476: =IF(ISNUMBER(BX476), (INDEX(BS:BS, MATCH(EOMONTH(BR476, 0), BR:BR, 1)) / BS476 - 1) * 100, "") | BZ476: -2.6442737 | CA476: -4.3699544 | CC476: 45455 | CD476: 45470 | CE476: 1901.1 | CG476: {=INDEX($AW$466:$AW$918, ROWS($AW$466:$AW$918) - ROW() + ROW($AW$466))} -> 44756 | CH476: {=INDEX($AX$466:$AX$918, ROWS($AX$466:$AX$918) - ROW() + ROW($AX$466))} -> 44770 | CI476: {=INDEX($CE$466:$CE$918, ROWS($CE$466:$CE$918) - ROW() + ROW($CE$466))} -> 1444.9 | CK476: =((CI476-CI475)/CI475)*100 -> -2.3089145 | CL476: =WEEKDAY(CG476, 2) -> 4 | CM476: =IF(CL476=4, ((CI476 - CI471) / CI471)*100, "") -> -0.59167527 | CN476: =IF(MONTH(CH476)<>MONTH(CH475), CH476, "") | CO476: =IF(ISNUMBER(CN476), (INDEX(CI:CI, MATCH(EOMONTH(CH476, 0), CH:CH, 1)) / CI476 - 1) * 100, "") | CP476: -2.5082084 | CQ476: -0.89804907 | CS476: 45455 | CT476: 45470 | CU476: 860.65 | CW476: {=INDEX($AW$466:$AW$918, ROWS($AW$466:$AW$918) - ROW() + ROW($AW$466))} -> 44756 | CX476: {=INDEX($AX$466:$AX$918, ROWS($AX$466:$AX$918) - ROW() + ROW($AX$466))} -> 44770 | CY476: {=INDEX($CU$466:$CU$918, ROWS($CU$466:$CU$918) - ROW() + ROW($CU$466))} -> 348.6 | DA476: =((CY476-CY475)/CY475)*100 -> 0.21561018 | DB476: =WEEKDAY(CW476, 2) -> 4 | DC476: =IF(DB476=4, ((CY476 - CY471) / CY471)*100, "") -> 3.3195021 | DD476: =IF(MONTH(CX476)<>MONTH(CX475), CX476, "") | DE476: =IF(ISNUMBER(DD476), (INDEX(CY:CY, MATCH(EOMONTH(CX476, 0), CX:CX, 1)) / CY476 - 1) * 100, "") | DF476: 0.31659232 | DG476: 3.4579994 | DI476: 45455 | DJ476: 45470 | DK476: 615.25 | DM476: {=INDEX($AW$466:$AW$918, ROWS($AW$466:$AW$918) - ROW() + ROW($AW$466))} -> 44756 | DN476: {=INDEX($AX$466:$AX$918, ROWS($AX$466:$AX$918) - ROW() + ROW($AX$466))} -> 44770 | DO476: {=INDEX($DK$466:$DK$918, ROWS($DK$466:$DK$918) - ROW() + ROW($DK$466))} -> 307.3 | DQ476: =((DO476-DO475)/DO475)*100 -> -1.4274258 | DR476: =WEEKDAY(DM476, 2) -> 4 | DS476: =IF(DR476=4, ((DO476 - DO471) / DO471)*100, "") -> -6.5389294 | DT476: =IF(MONTH(DN476)<>MONTH(DN475), DN476, "") | DU476: =IF(ISNUMBER(DT476), (INDEX(DO:DO, MATCH(EOMONTH(DN476, 0), DN:DN, 1)) / DO476 - 1) * 100, "") | DV476: -4.0172553 | DW476: 0.82129708
A477: 45454 | B477: 45470 | C477: 150.15 | E477: {=INDEX($A$466:$A$918, ROWS($A$466:$A$918) - ROW() + ROW($A$466))} -> 44757 | F477: {=INDEX($B$466:$B$918, ROWS($B$466:$B$918) - ROW() + ROW($B$466))} -> 44770 | G477: {=INDEX($C$466:$C$918, ROWS($C$466:$C$918) - ROW() + ROW($C$466))} -> 152.1 | I477: =((G477-G476)/G476)*100 -> 1.0967099 | J477: =WEEKDAY(E477, 2) -> 5 | K477: =IF(J477=4, ((G477 - G472) / G472)*100, "") | L477: =IF(MONTH(F477)<>MONTH(F476), F477, "") | M477: =IF(ISNUMBER(L477), (INDEX(G:G, MATCH(EOMONTH(F477, 0), F:F, 1)) / G477 - 1) * 100, "") | N477: 0.86522463 | Q477: 45454 | R477: 45470 | S477: 38904.3 | U477: {=INDEX($Q$466:$Q$918, ROWS($Q$466:$Q$918) - ROW() + ROW($Q$466))} -> 44757 | V477: {=INDEX($R$466:$R$918, ROWS($R$466:$R$918) - ROW() + ROW($R$466))} -> 44770 | W477: {=INDEX($S$466:$S$918, ROWS($S$466:$S$918) - ROW() + ROW($S$466))} -> 44533.85 | Y477: =((W477-W476)/W476)*100 -> 1.8825946 | Z477: =WEEKDAY(U477, 2) -> 5 | AA477: =IF(Z477=4, ((W477 - W472) / W472)*100, "") | AB477: =IF(MONTH(V477)<>MONTH(V476), V477, "") | AC477: =IF(ISNUMBER(AB477), (INDEX(W:W, MATCH(EOMONTH(V477, 0), V:V, 1)) / W477 - 1) * 100, "") | AD477: 1.5661215 | AG477: 45454 | AH477: 45470 | AI477: 368.6 | AK477: {=INDEX($AG$466:$AG$918, ROWS($AG$466:$AG$918) - ROW() + ROW($AG$466))} -> 44757 | AL477: {=INDEX($AH$466:$AH$918, ROWS($AH$466:$AH$918) - ROW() + ROW($AH$466))} -> 44770 | AM477: {=INDEX($AI$466:$AI$918, ROWS($AI$466:$AI$918) - ROW() + ROW($AI$466))} -> 149.7 | AO477: =((AM477-AM476)/AM476)*100 -> 0.91001011 | AP477: =WEEKDAY(AK477, 2) -> 5 | AQ477: =IF(AP477=4, ((AM477 - AM472) / AM472)*100, "") | AR477: =IF(MONTH(AL477)<>MONTH(AL476), AL477, "") | AS477: =IF(ISNUMBER(AR477), (INDEX(AM:AM, MATCH(EOMONTH(AL477, 0), AL:AL, 1)) / AM477 - 1) * 100, "") | AT477: -1.9484601 | AW477: 45454 | AX477: 45470 | AY477: 287.35 | BA477: {=INDEX($AW$466:$AW$918, ROWS($AW$466:$AW$918) - ROW() + ROW($AW$466))} -> 44757 | BB477: {=INDEX($AX$466:$AX$918, ROWS($AX$466:$AX$918) - ROW() + ROW($AX$466))} -> 44770 | BC477: {=INDEX($AY$466:$AY$918, ROWS($AY$466:$AY$918) - ROW() + ROW($AY$466))} -> 245.9 | BE477: =((BC477-BC476)/BC476)*100 -> 3.5150495 | BF477: =WEEKDAY(BA477, 2) -> 5 | BG477: =IF(BF477=4, ((BC477 - BC472) / BC472)*100, "") | BH477: =IF(MONTH(BB477)<>MONTH(BB476), BB477, "") | BI477: =IF(ISNUMBER(BH477), (INDEX(BC:BC, MATCH(EOMONTH(BB477, 0), BB:BB, 1)) / BC477 - 1) * 100, "") | BJ477: -1.8496951 | BM477: 45454 | BN477: 45470 | BO477: 1430.15 | BQ477: {=INDEX($AW$466:$AW$918, ROWS($AW$466:$AW$918) - ROW() + ROW($AW$466))} -> 44757 | BR477: {=INDEX($AX$466:$AX$918, ROWS($AX$466:$AX$918) - ROW() + ROW($AX$466))} -> 44770 | BS477: {=INDEX($BO$466:$BO$918, ROWS($BO$466:$BO$918) - ROW() + ROW($BO$466))} -> 1156.5 | BU477: =((BS477-BS476)/BS476)*100 -> 1.514154 | BV477: =WEEKDAY(BQ477, 2) -> 5 | BW477: =IF(BV477=4, ((BS477 - BS472) / BS472)*100, "") | BX477: =IF(MONTH(BR477)<>MONTH(BR476), BR477, "") | BY477: =IF(ISNUMBER(BX477), (INDEX(BS:BS, MATCH(EOMONTH(BR477, 0), BR:BR, 1)) / BS477 - 1) * 100, "") | BZ477: -3.8080382 | CC477: 45454 | CD477: 45470 | CE477: 1886.5 | CG477: {=INDEX($AW$466:$AW$918, ROWS($AW$466:$AW$918) - ROW() + ROW($AW$466))} -> 44757 | CH477: {=INDEX($AX$466:$AX$918, ROWS($AX$466:$AX$918) - ROW() + ROW($AX$466))} -> 44770 | CI477: {=INDEX($CE$466:$CE$918, ROWS($CE$466:$CE$918) - ROW() + ROW($CE$466))} -> 1454.75 | CK477: =((CI477-CI476)/CI476)*100 -> 0.68170808 | CL477: =WEEKDAY(CG477, 2) -> 5 | CM477: =IF(CL477=4, ((CI477 - CI472) / CI472)*100, "") | CN477: =IF(MONTH(CH477)<>MONTH(CH476), CH477, "") | CO477: =IF(ISNUMBER(CN477), (INDEX(CI:CI, MATCH(EOMONTH(CH477, 0), CH:CH, 1)) / CI477 - 1) * 100, "") | CP477: 0.57287688 | CS477: 45454 | CT477: 45470 | CU477: 857 | CW477: {=INDEX($AW$466:$AW$918, ROWS($AW$466:$AW$918) - ROW() + ROW($AW$466))} -> 44757 | CX477: {=INDEX($AX$466:$AX$918, ROWS($AX$466:$AX$918) - ROW() + ROW($AX$466))} -> 44770 | CY477: {=INDEX($CU$466:$CU$918, ROWS($CU$466:$CU$918) - ROW() + ROW($CU$466))} -> 354.95 | DA477: =((CY477-CY476)/CY476)*100 -> 1.821572 | DB477: =WEEKDAY(CW477, 2) -> 5 | DC477: =IF(DB477=4, ((CY477 - CY472) / CY472)*100, "") | DD477: =IF(MONTH(CX477)<>MONTH(CX476), CX477, "") | DE477: =IF(ISNUMBER(DD477), (INDEX(CY:CY, MATCH(EOMONTH(CX477, 0), CX:CX, 1)) / CY477 - 1) * 100, "") | DF477: 1.4632047 | DI477: 45454 | DJ477: 45470 | DK477: 609.25 | DM477: {=INDEX($AW$466:$AW$918, ROWS($AW$466:$AW$918) - ROW() + ROW($AW$466))} -> 44757 | DN477: {=INDEX($AX$466:$AX$918, ROWS($AX$466:$AX$918) - ROW() + ROW($AX$466))} -> 44770 | DO477: {=INDEX($DK$466:$DK$918, ROWS($DK$466:$DK$918) - ROW() + ROW($DK$466))} -> 312.5 | DQ477: =((DO477-DO476)/DO476)*100 -> 1.6921575 | DR477: =WEEKDAY(DM477, 2) -> 5 | DS477: =IF(DR477=4, ((DO477 - DO472) / DO472)*100, "") | DT477: =IF(MONTH(DN477)<>MONTH(DN476), DN477, "") | DU477: =IF(ISNUMBER(DT477), (INDEX(DO:DO, MATCH(EOMONTH(DN477, 0), DN:DN, 1)) / DO477 - 1) * 100, "") | DV477: 2.3876404
A478: 45453 | B478: 45470 | C478: 147.8 | E478: {=INDEX($A$466:$A$918, ROWS($A$466:$A$918) - ROW() + ROW($A$466))} -> 44760 | F478: {=INDEX($B$466:$B$918, ROWS($B$466:$B$918) - ROW() + ROW($B$466))} -> 44770 | G478: {=INDEX($C$466:$C$918, ROWS($C$466:$C$918) - ROW() + ROW($C$466))} -> 154.55 | I478: =((G478-G477)/G477)*100 -> 1.6107824 | J478: =WEEKDAY(E478, 2) -> 1 | K478: =IF(J478=4, ((G478 - G473) / G473)*100, "") | L478: =IF(MONTH(F478)<>MONTH(F477), F478, "") | M478: =IF(ISNUMBER(L478), (INDEX(G:G, MATCH(EOMONTH(F478, 0), F:F, 1)) / G478 - 1) * 100, "") | N478: 1.682613 | Q478: 45453 | R478: 45470 | S478: 38633.6 | U478: {=INDEX($Q$466:$Q$918, ROWS($Q$466:$Q$918) - ROW() + ROW($Q$466))} -> 44760 | V478: {=INDEX($R$466:$R$918, ROWS($R$466:$R$918) - ROW() + ROW($R$466))} -> 44770 | W478: {=INDEX($S$466:$S$918, ROWS($S$466:$S$918) - ROW() + ROW($S$466))} -> 44119.55 | Y478: =((W478-W477)/W477)*100 -> -0.93030358 | Z478: =WEEKDAY(U478, 2) -> 1 | AA478: =IF(Z478=4, ((W478 - W473) / W473)*100, "") | AB478: =IF(MONTH(V478)<>MONTH(V477), V478, "") | AC478: =IF(ISNUMBER(AB478), (INDEX(W:W, MATCH(EOMONTH(V478, 0), V:V, 1)) / W478 - 1) * 100, "") | AD478: -0.66195612 | AG478: 45453 | AH478: 45470 | AI478: 365.55 | AK478: {=INDEX($AG$466:$AG$918, ROWS($AG$466:$AG$918) - ROW() + ROW($AG$466))} -> 44760 | AL478: {=INDEX($AH$466:$AH$918, ROWS($AH$466:$AH$918) - ROW() + ROW($AH$466))} -> 44770 | AM478: {=INDEX($AI$466:$AI$918, ROWS($AI$466:$AI$918) - ROW() + ROW($AI$466))} -> 150.4 | AO478: =((AM478-AM477)/AM477)*100 -> 0.46760187 | AP478: =WEEKDAY(AK478, 2) -> 1 | AQ478: =IF(AP478=4, ((AM478 - AM473) / AM473)*100, "") | AR478: =IF(MONTH(AL478)<>MONTH(AL477), AL478, "") | AS478: =IF(ISNUMBER(AR478), (INDEX(AM:AM, MATCH(EOMONTH(AL478, 0), AL:AL, 1)) / AM478 - 1) * 100, "") | AT478: 2.5 | AW478: 45453 | AX478: 45470 | AY478: 283.75 | BA478: {=INDEX($AW$466:$AW$918, ROWS($AW$466:$AW$918) - ROW() + ROW($AW$466))} -> 44760 | BB478: {=INDEX($AX$466:$AX$918, ROWS($AX$466:$AX$918) - ROW() + ROW($AX$466))} -> 44770 | BC478: {=INDEX($AY$466:$AY$918, ROWS($AY$466:$AY$918) - ROW() + ROW($AY$466))} -> 255.2 | BE478: =((BC478-BC477)/BC477)*100 -> 3.7820252 | BF478: =WEEKDAY(BA478, 2) -> 1 | BG478: =IF(BF478=4, ((BC478 - BC473) / BC473)*100, "") | BH478: =IF(MONTH(BB478)<>MONTH(BB477), BB478, "") | BI478: =IF(ISNUMBER(BH478), (INDEX(BC:BC, MATCH(EOMONTH(BB478, 0), BB:BB, 1)) / BC478 - 1) * 100, "") | BJ478: -0.10469742 | BM478: 45453 | BN478: 45470 | BO478: 1432.55 | BQ478: {=INDEX($AW$466:$AW$918, ROWS($AW$466:$AW$918) - ROW() + ROW($AW$466))} -> 44760 | BR478: {=INDEX($AX$466:$AX$918, ROWS($AX$466:$AX$918) - ROW() + ROW($AX$466))} -> 44770 | BS478: {=INDEX($BO$466:$BO$918, ROWS($BO$466:$BO$918) - ROW() + ROW($BO$466))} -> 1178.95 | BU478: =((BS478-BS477)/BS477)*100 -> 1.9412019 | BV478: =WEEKDAY(BQ478, 2) -> 1 | BW478: =IF(BV478=4, ((BS478 - BS473) / BS473)*100, "") | BX478: =IF(MONTH(BR478)<>MONTH(BR477), BR478, "") | BY478: =IF(ISNUMBER(BX478), (INDEX(BS:BS, MATCH(EOMONTH(BR478, 0), BR:BR, 1)) / BS478 - 1) * 100, "") | BZ478: 0.15262806 | CC478: 45453 | CD478: 45470 | CE478: 1876.6 | CG478: {=INDEX($AW$466:$AW$918, ROWS($AW$466:$AW$918) - ROW() + ROW($AW$466))} -> 44760 | CH478: {=INDEX($AX$466:$AX$918, ROWS($AX$466:$AX$918) - ROW() + ROW($AX$466))} -> 44770 | CI478: {=INDEX($CE$466:$CE$918, ROWS($CE$466:$CE$918) - ROW() + ROW($CE$466))} -> 1497 | CK478: =((CI478-CI477)/CI477)*100 -> 2.9042791 | CL478: =WEEKDAY(CG478, 2) -> 1 | CM478: =IF(CL478=4, ((CI478 - CI473) / CI473)*100, "") | CN478: =IF(MONTH(CH478)<>MONTH(CH477), CH478, "") | CO478: =IF(ISNUMBER(CN478), (INDEX(CI:CI, MATCH(EOMONTH(CH478, 0), CH:CH, 1)) / CI478 - 1) * 100, "") | CP478: 2.9033038 | CS478: 45453 | CT478: 45470 | CU478: 848.4 | CW478: {=INDEX($AW$466:$AW$918, ROWS($AW$466:$AW$918) - ROW() + ROW($AW$466))} -> 44760 | CX478: {=INDEX($AX$466:$AX$918, ROWS($AX$466:$AX$918) - ROW() + ROW($AX$466))} -> 44770 | CY478: {=INDEX($CU$466:$CU$918, ROWS($CU$466:$CU$918) - ROW() + ROW($CU$466))} -> 354.65 | DA478: =((CY478-CY477)/CY477)*100 -> -0.084518946 | DB478: =WEEKDAY(CW478, 2) -> 1 | DC478: =IF(DB478=4, ((CY478 - CY473) / CY473)*100, "") | DD478: =IF(MONTH(CX478)<>MONTH(CX477), CX478, "") | DE478: =IF(ISNUMBER(DD478), (INDEX(CY:CY, MATCH(EOMONTH(CX478, 0), CX:CX, 1)) / CY478 - 1) * 100, "") | DF478: -0.12724445 | DI478: 45453 | DJ478: 45470 | DK478: 604.65 | DM478: {=INDEX($AW$466:$AW$918, ROWS($AW$466:$AW$918) - ROW() + ROW($AW$466))} -> 44760 | DN478: {=INDEX($AX$466:$AX$918, ROWS($AX$466:$AX$918) - ROW() + ROW($AX$466))} -> 44770 | DO478: {=INDEX($DK$466:$DK$918, ROWS($DK$466:$DK$918) - ROW() + ROW($DK$466))} -> 316.2 | DQ478: =((DO478-DO477)/DO477)*100 -> 1.184 | DR478: =WEEKDAY(DM478, 2) -> 1 | DS478: =IF(DR478=4, ((DO478 - DO473) / DO473)*100, "") | DT478: =IF(MONTH(DN478)<>MONTH(DN477), DN478, "") | DU478: =IF(ISNUMBER(DT478), (INDEX(DO:DO, MATCH(EOMONTH(DN478, 0), DN:DN, 1)) / DO478 - 1) * 100, "") | DV478: 1.2620027
A479: 45450 | B479: 45470 | C479: 147.4 | E479: {=INDEX($A$466:$A$918, ROWS($A$466:$A$918) - ROW() + ROW($A$466))} -> 44761 | F479: {=INDEX($B$466:$B$918, ROWS($B$466:$B$918) - ROW() + ROW($B$466))} -> 44770 | G479: {=INDEX($C$466:$C$918, ROWS($C$466:$C$918) - ROW() + ROW($C$466))} -> 158.75 | I479: =((G479-G478)/G478)*100 -> 2.7175671 | J479: =WEEKDAY(E479, 2) -> 2 | K479: =IF(J479=4, ((G479 - G474) / G474)*100, "") | L479: =IF(MONTH(F479)<>MONTH(F478), F479, "") | M479: =IF(ISNUMBER(L479), (INDEX(G:G, MATCH(EOMONTH(F479, 0), F:F, 1)) / G479 - 1) * 100, "") | N479: 2.5308241 | Q479: 45450 | R479: 45470 | S479: 38522.65 | U479: {=INDEX($Q$466:$Q$918, ROWS($Q$466:$Q$918) - ROW() + ROW($Q$466))} -> 44761 | V479: {=INDEX($R$466:$R$918, ROWS($R$466:$R$918) - ROW() + ROW($R$466))} -> 44770 | W479: {=INDEX($S$466:$S$918, ROWS($S$466:$S$918) - ROW() + ROW($S$466))} -> 43914.7 | Y479: =((W479-W478)/W478)*100 -> -0.46430664 | Z479: =WEEKDAY(U479, 2) -> 2 | AA479: =IF(Z479=4, ((W479 - W474) / W474)*100, "") | AB479: =IF(MONTH(V479)<>MONTH(V478), V479, "") | AC479: =IF(ISNUMBER(AB479), (INDEX(W:W, MATCH(EOMONTH(V479, 0), V:V, 1)) / W479 - 1) * 100, "") | AD479: -0.7350005 | AG479: 45450 | AH479: 45470 | AI479: 361.2 | AK479: {=INDEX($AG$466:$AG$918, ROWS($AG$466:$AG$918) - ROW() + ROW($AG$466))} -> 44761 | AL479: {=INDEX($AH$466:$AH$918, ROWS($AH$466:$AH$918) - ROW() + ROW($AH$466))} -> 44770 | AM479: {=INDEX($AI$466:$AI$918, ROWS($AI$466:$AI$918) - ROW() + ROW($AI$466))} -> 150.9 | AO479: =((AM479-AM478)/AM478)*100 -> 0.33244681 | AP479: =WEEKDAY(AK479, 2) -> 2 | AQ479: =IF(AP479=4, ((AM479 - AM474) / AM474)*100, "") | AR479: =IF(MONTH(AL479)<>MONTH(AL478), AL479, "") | AS479: =IF(ISNUMBER(AR479), (INDEX(AM:AM, MATCH(EOMONTH(AL479, 0), AL:AL, 1)) / AM479 - 1) * 100, "") | AT479: 1.6260163 | AW479: 45450 | AX479: 45470 | AY479: 283.8 | BA479: {=INDEX($AW$466:$AW$918, ROWS($AW$466:$AW$918) - ROW() + ROW($AW$466))} -> 44761 | BB479: {=INDEX($AX$466:$AX$918, ROWS($AX$466:$AX$918) - ROW() + ROW($AX$466))} -> 44770 | BC479: {=INDEX($AY$466:$AY$918, ROWS($AY$466:$AY$918) - ROW() + ROW($AY$466))} -> 255.95 | BE479: =((BC479-BC478)/BC478)*100 -> 0.29388715 | BF479: =WEEKDAY(BA479, 2) -> 2 | BG479: =IF(BF479=4, ((BC479 - BC474) / BC474)*100, "") | BH479: =IF(MONTH(BB479)<>MONTH(BB478), BB479, "") | BI479: =IF(ISNUMBER(BH479), (INDEX(BC:BC, MATCH(EOMONTH(BB479, 0), BB:BB, 1)) / BC479 - 1) * 100, "") | BJ479: 4.1154276 | BM479: 45450 | BN479: 45470 | BO479: 1429.1 | BQ479: {=INDEX($AW$466:$AW$918, ROWS($AW$466:$AW$918) - ROW() + ROW($AW$466))} -> 44761 | BR479: {=INDEX($AX$466:$AX$918, ROWS($AX$466:$AX$918) - ROW() + ROW($AX$466))} -> 44770 | BS479: {=INDEX($BO$466:$BO$918, ROWS($BO$466:$BO$918) - ROW() + ROW($BO$466))} -> 1169.75 | BU479: =((BS479-BS478)/BS478)*100 -> -0.7803554 | BV479: =WEEKDAY(BQ479, 2) -> 2 | BW479: =IF(BV479=4, ((BS479 - BS474) / BS474)*100, "") | BX479: =IF(MONTH(BR479)<>MONTH(BR478), BR479, "") | BY479: =IF(ISNUMBER(BX479), (INDEX(BS:BS, MATCH(EOMONTH(BR479, 0), BR:BR, 1)) / BS479 - 1) * 100, "") | BZ479: 0.46671112 | CC479: 45450 | CD479: 45470 | CE479: 1812.45 | CG479: {=INDEX($AW$466:$AW$918, ROWS($AW$466:$AW$918) - ROW() + ROW($AW$466))} -> 44761 | CH479: {=INDEX($AX$466:$AX$918, ROWS($AX$466:$AX$918) - ROW() + ROW($AX$466))} -> 44770 | CI479: {=INDEX($CE$466:$CE$918, ROWS($CE$466:$CE$918) - ROW() + ROW($CE$466))} -> 1518.05 | CK479: =((CI479-CI478)/CI478)*100 -> 1.4061456 | CL479: =WEEKDAY(CG479, 2) -> 2 | CM479: =IF(CL479=4, ((CI479 - CI474) / CI474)*100, "") | CN479: =IF(MONTH(CH479)<>MONTH(CH478), CH479, "") | CO479: =IF(ISNUMBER(CN479), (INDEX(CI:CI, MATCH(EOMONTH(CH479, 0), CH:CH, 1)) / CI479 - 1) * 100, "") | CP479: 1.6304348 | CS479: 45450 | CT479: 45470 | CU479: 845.55 | CW479: {=INDEX($AW$466:$AW$918, ROWS($AW$466:$AW$918) - ROW() + ROW($AW$466))} -> 44761 | CX479: {=INDEX($AX$466:$AX$918, ROWS($AX$466:$AX$918) - ROW() + ROW($AX$466))} -> 44770 | CY479: {=INDEX($CU$466:$CU$918, ROWS($CU$466:$CU$918) - ROW() + ROW($CU$466))} -> 361.25 | DA479: =((CY479-CY478)/CY478)*100 -> 1.8609897 | DB479: =WEEKDAY(CW479, 2) -> 2 | DC479: =IF(DB479=4, ((CY479 - CY474) / CY474)*100, "") | DD479: =IF(MONTH(CX479)<>MONTH(CX478), CX479, "") | DE479: =IF(ISNUMBER(DD479), (INDEX(CY:CY, MATCH(EOMONTH(CX479, 0), CX:CX, 1)) / CY479 - 1) * 100, "") | DF479: 1.882786 | DI479: 45450 | DJ479: 45470 | DK479: 601.1 | DM479: {=INDEX($AW$466:$AW$918, ROWS($AW$466:$AW$918) - ROW() + ROW($AW$466))} -> 44761 | DN479: {=INDEX($AX$466:$AX$918, ROWS($AX$466:$AX$918) - ROW() + ROW($AX$466))} -> 44770 | DO479: {=INDEX($DK$466:$DK$918, ROWS($DK$466:$DK$918) - ROW() + ROW($DK$466))} -> 317.45 | DQ479: =((DO479-DO478)/DO478)*100 -> 0.39531942 | DR479: =WEEKDAY(DM479, 2) -> 2 | DS479: =IF(DR479=4, ((DO479 - DO474) / DO474)*100, "") | DT479: =IF(MONTH(DN479)<>MONTH(DN478), DN479, "") | DU479: =IF(ISNUMBER(DT479), (INDEX(DO:DO, MATCH(EOMONTH(DN479, 0), DN:DN, 1)) / DO479 - 1) * 100, "") | DV479: 1.1108101
A480: 45449 | B480: 45470 | C480: 145.95 | E480: {=INDEX($A$466:$A$918, ROWS($A$466:$A$918) - ROW() + ROW($A$466))} -> 44762 | F480: {=INDEX($B$466:$B$918, ROWS($B$466:$B$918) - ROW() + ROW($B$466))} -> 44770 | G480: {=INDEX($C$466:$C$918, ROWS($C$466:$C$918) - ROW() + ROW($C$466))} -> 158.15 | I480: =((G480-G479)/G479)*100 -> -0.37795276 | J480: =WEEKDAY(E480, 2) -> 3 | K480: =IF(J480=4, ((G480 - G475) / G475)*100, "") | L480: =IF(MONTH(F480)<>MONTH(F479), F480, "") | M480: =IF(ISNUMBER(L480), (INDEX(G:G, MATCH(EOMONTH(F480, 0), F:F, 1)) / G480 - 1) * 100, "") | N480: -0.15822785 | Q480: 45449 | R480: 45470 | S480: 38670.3 | U480: {=INDEX($Q$466:$Q$918, ROWS($Q$466:$Q$918) - ROW() + ROW($Q$466))} -> 44762 | V480: {=INDEX($R$466:$R$918, ROWS($R$466:$R$918) - ROW() + ROW($R$466))} -> 44770 | W480: {=INDEX($S$466:$S$918, ROWS($S$466:$S$918) - ROW() + ROW($S$466))} -> 44113.3 | Y480: =((W480-W479)/W479)*100 -> 0.45224037 | Z480: =WEEKDAY(U480, 2) -> 3 | AA480: =IF(Z480=4, ((W480 - W475) / W475)*100, "") | AB480: =IF(MONTH(V480)<>MONTH(V479), V480, "") | AC480: =IF(ISNUMBER(AB480), (INDEX(W:W, MATCH(EOMONTH(V480, 0), V:V, 1)) / W480 - 1) * 100, "") | AD480: 0.54844649 | AG480: 45449 | AH480: 45470 | AI480: 350.95 | AK480: {=INDEX($AG$466:$AG$918, ROWS($AG$466:$AG$918) - ROW() + ROW($AG$466))} -> 44762 | AL480: {=INDEX($AH$466:$AH$918, ROWS($AH$466:$AH$918) - ROW() + ROW($AH$466))} -> 44770 | AM480: {=INDEX($AI$466:$AI$918, ROWS($AI$466:$AI$918) - ROW() + ROW($AI$466))} -> 150.5 | AO480: =((AM480-AM479)/AM479)*100 -> -0.26507621 | AP480: =WEEKDAY(AK480, 2) -> 3 | AQ480: =IF(AP480=4, ((AM480 - AM475) / AM475)*100, "") | AR480: =IF(MONTH(AL480)<>MONTH(AL479), AL480, "") | AS480: =IF(ISNUMBER(AR480), (INDEX(AM:AM, MATCH(EOMONTH(AL480, 0), AL:AL, 1)) / AM480 - 1) * 100, "") | AT480: 0.86153846 | AW480: 45449 | AX480: 45470 | AY480: 274.55 | BA480: {=INDEX($AW$466:$AW$918, ROWS($AW$466:$AW$918) - ROW() + ROW($AW$466))} -> 44762 | BB480: {=INDEX($AX$466:$AX$918, ROWS($AX$466:$AX$918) - ROW() + ROW($AX$466))} -> 44770 | BC480: {=INDEX($AY$466:$AY$918, ROWS($AY$466:$AY$918) - ROW() + ROW($AY$466))} -> 255.2 | BE480: =((BC480-BC479)/BC479)*100 -> -0.29302598 | BF480: =WEEKDAY(BA480, 2) -> 3 | BG480: =IF(BF480=4, ((BC480 - BC475) / BC475)*100, "") | BH480: =IF(MONTH(BB480)<>MONTH(BB479), BB480, "") | BI480: =IF(ISNUMBER(BH480), (INDEX(BC:BC, MATCH(EOMONTH(BB480, 0), BB:BB, 1)) / BC480 - 1) * 100, "") | BJ480: 0.51674384 | BM480: 45449 | BN480: 45470 | BO480: 1445.85 | BQ480: {=INDEX($AW$466:$AW$918, ROWS($AW$466:$AW$918) - ROW() + ROW($AW$466))} -> 44762 | BR480: {=INDEX($AX$466:$AX$918, ROWS($AX$466:$AX$918) - ROW() + ROW($AX$466))} -> 44770 | BS480: {=INDEX($BO$466:$BO$918, ROWS($BO$466:$BO$918) - ROW() + ROW($BO$466))} -> 1185.45 | BU480: =((BS480-BS479)/BS479)*100 -> 1.3421671 | BV480: =WEEKDAY(BQ480, 2) -> 3 | BW480: =IF(BV480=4, ((BS480 - BS475) / BS475)*100, "") | BX480: =IF(MONTH(BR480)<>MONTH(BR479), BR480, "") | BY480: =IF(ISNUMBER(BX480), (INDEX(BS:BS, MATCH(EOMONTH(BR480, 0), BR:BR, 1)) / BS480 - 1) * 100, "") | BZ480: -0.58778915 | CC480: 45449 | CD480: 45470 | CE480: 1774.8 | CG480: {=INDEX($AW$466:$AW$918, ROWS($AW$466:$AW$918) - ROW() + ROW($AW$466))} -> 44762 | CH480: {=INDEX($AX$466:$AX$918, ROWS($AX$466:$AX$918) - ROW() + ROW($AX$466))} -> 44770 | CI480: {=INDEX($CE$466:$CE$918, ROWS($CE$466:$CE$918) - ROW() + ROW($CE$466))} -> 1516.35 | CK480: =((CI480-CI479)/CI479)*100 -> -0.11198577 | CL480: =WEEKDAY(CG480, 2) -> 3 | CM480: =IF(CL480=4, ((CI480 - CI475) / CI475)*100, "") | CN480: =IF(MONTH(CH480)<>MONTH(CH479), CH480, "") | CO480: =IF(ISNUMBER(CN480), (INDEX(CI:CI, MATCH(EOMONTH(CH480, 0), CH:CH, 1)) / CI480 - 1) * 100, "") | CP480: -0.11883541 | CS480: 45449 | CT480: 45470 | CU480: 832.1 | CW480: {=INDEX($AW$466:$AW$918, ROWS($AW$466:$AW$918) - ROW() + ROW($AW$466))} -> 44762 | CX480: {=INDEX($AX$466:$AX$918, ROWS($AX$466:$AX$918) - ROW() + ROW($AX$466))} -> 44770 | CY480: {=INDEX($CU$466:$CU$918, ROWS($CU$466:$CU$918) - ROW() + ROW($CU$466))} -> 357.25 | DA480: =((CY480-CY479)/CY479)*100 -> -1.1072664 | DB480: =WEEKDAY(CW480, 2) -> 3 | DC480: =IF(DB480=4, ((CY480 - CY475) / CY475)*100, "") | DD480: =IF(MONTH(CX480)<>MONTH(CX479), CX480, "") | DE480: =IF(ISNUMBER(DD480), (INDEX(CY:CY, MATCH(EOMONTH(CX480, 0), CX:CX, 1)) / CY480 - 1) * 100, "") | DF480: -0.95873281 | DI480: 45449 | DJ480: 45470 | DK480: 587.25 | DM480: {=INDEX($AW$466:$AW$918, ROWS($AW$466:$AW$918) - ROW() + ROW($AW$466))} -> 44762 | DN480: {=INDEX($AX$466:$AX$918, ROWS($AX$466:$AX$918) - ROW() + ROW($AX$466))} -> 44770 | DO480: {=INDEX($DK$466:$DK$918, ROWS($DK$466:$DK$918) - ROW() + ROW($DK$466))} -> 317.35 | DQ480: =((DO480-DO479)/DO479)*100 -> -0.031501024 | DR480: =WEEKDAY(DM480, 2) -> 3 | DS480: =IF(DR480=4, ((DO480 - DO475) / DO475)*100, "") | DT480: =IF(MONTH(DN480)<>MONTH(DN479), DN480, "") | DU480: =IF(ISNUMBER(DT480), (INDEX(DO:DO, MATCH(EOMONTH(DN480, 0), DN:DN, 1)) / DO480 - 1) * 100, "") | DV480: 5.8145766
A481: 45448 | B481: 45470 | C481: 144.7 | E481: {=INDEX($A$466:$A$918, ROWS($A$466:$A$918) - ROW() + ROW($A$466))} -> 44763 | F481: {=INDEX($B$466:$B$918, ROWS($B$466:$B$918) - ROW() + ROW($B$466))} -> 44770 | G481: {=INDEX($C$466:$C$918, ROWS($C$466:$C$918) - ROW() + ROW($C$466))} -> 160.2 | I481: =((G481-G480)/G480)*100 -> 1.2962377 | J481: =WEEKDAY(E481, 2) -> 4 | K481: =IF(J481=4, ((G481 - G476) / G476)*100, "") -> 6.4805583 | L481: =IF(MONTH(F481)<>MONTH(F480), F481, "") | M481: =IF(ISNUMBER(L481), (INDEX(G:G, MATCH(EOMONTH(F481, 0), F:F, 1)) / G481 - 1) * 100, "") | N481: 1.4896989 | O481: 6.5557404 | Q481: 45448 | R481: 45470 | S481: 38697.25 | U481: {=INDEX($Q$466:$Q$918, ROWS($Q$466:$Q$918) - ROW() + ROW($Q$466))} -> 44763 | V481: {=INDEX($R$466:$R$918, ROWS($R$466:$R$918) - ROW() + ROW($R$466))} -> 44770 | W481: {=INDEX($S$466:$S$918, ROWS($S$466:$S$918) - ROW() + ROW($S$466))} -> 45120.5 | Y481: =((W481-W480)/W480)*100 -> 2.2832116 | Z481: =WEEKDAY(U481, 2) -> 4 | AA481: =IF(Z481=4, ((W481 - W476) / W476)*100, "") -> 3.2247069 | AB481: =IF(MONTH(V481)<>MONTH(V480), V481, "") | AC481: =IF(ISNUMBER(AB481), (INDEX(W:W, MATCH(EOMONTH(V481, 0), V:V, 1)) / W481 - 1) * 100, "") | AD481: 2.5816762 | AE481: 3.3012967 | AG481: 45448 | AH481: 45470 | AI481: 341.55 | AK481: {=INDEX($AG$466:$AG$918, ROWS($AG$466:$AG$918) - ROW() + ROW($AG$466))} -> 44763 | AL481: {=INDEX($AH$466:$AH$918, ROWS($AH$466:$AH$918) - ROW() + ROW($AH$466))} -> 44770 | AM481: {=INDEX($AI$466:$AI$918, ROWS($AI$466:$AI$918) - ROW() + ROW($AI$466))} -> 150.85 | AO481: =((AM481-AM480)/AM480)*100 -> 0.23255814 | AP481: =WEEKDAY(AK481, 2) -> 4 | AQ481: =IF(AP481=4, ((AM481 - AM476) / AM476)*100, "") -> 1.6852039 | AR481: =IF(MONTH(AL481)<>MONTH(AL480), AL481, "") | AS481: =IF(ISNUMBER(AR481), (INDEX(AM:AM, MATCH(EOMONTH(AL481, 0), AL:AL, 1)) / AM481 - 1) * 100, "") | AT481: -0.18303844 | AU481: 2.8284098 | AW481: 45448 | AX481: 45470 | AY481: 261.7 | BA481: {=INDEX($AW$466:$AW$918, ROWS($AW$466:$AW$918) - ROW() + ROW($AW$466))} -> 44763 | BB481: {=INDEX($AX$466:$AX$918, ROWS($AX$466:$AX$918) - ROW() + ROW($AX$466))} -> 44770 | BC481: {=INDEX($AY$466:$AY$918, ROWS($AY$466:$AY$918) - ROW() + ROW($AY$466))} -> 269.3 | BE481: =((BC481-BC480)/BC480)*100 -> 5.5250784 | BF481: =WEEKDAY(BA481, 2) -> 4 | BG481: =IF(BF481=4, ((BC481 - BC476) / BC476)*100, "") -> 13.365607 | BH481: =IF(MONTH(BB481)<>MONTH(BB480), BB481, "") | BI481: =IF(ISNUMBER(BH481), (INDEX(BC:BC, MATCH(EOMONTH(BB481, 0), BB:BB, 1)) / BC481 - 1) * 100, "") | BJ481: 1.1416745 | BK481: 3.781599 | BM481: 45448 | BN481: 45470 | BO481: 1393.9 | BQ481: {=INDEX($AW$466:$AW$918, ROWS($AW$466:$AW$918) - ROW() + ROW($AW$466))} -> 44763 | BR481: {=INDEX($AX$466:$AX$918, ROWS($AX$466:$AX$918) - ROW() + ROW($AX$466))} -> 44770 | BS481: {=INDEX($BO$466:$BO$918, ROWS($BO$466:$BO$918) - ROW() + ROW($BO$466))} -> 1171 | BU481: =((BS481-BS480)/BS480)*100 -> -1.2189464 | BV481: =WEEKDAY(BQ481, 2) -> 4 | BW481: =IF(BV481=4, ((BS481 - BS476) / BS476)*100, "") -> 2.7869212 | BX481: =IF(MONTH(BR481)<>MONTH(BR480), BR481, "") | BY481: =IF(ISNUMBER(BX481), (INDEX(BS:BS, MATCH(EOMONTH(BR481, 0), BR:BR, 1)) / BS481 - 1) * 100, "") | BZ481: 0.54358192 | CA481: -3.2574784 | CC481: 45448 | CD481: 45470 | CE481: 1736.75 | CG481: {=INDEX($AW$466:$AW$918, ROWS($AW$466:$AW$918) - ROW() + ROW($AW$466))} -> 44763 | CH481: {=INDEX($AX$466:$AX$918, ROWS($AX$466:$AX$918) - ROW() + ROW($AX$466))} -> 44770 | CI481: {=INDEX($CE$466:$CE$918, ROWS($CE$466:$CE$918) - ROW() + ROW($CE$466))} -> 1545.6 | CK481: =((CI481-CI480)/CI480)*100 -> 1.9289742 | CL481: =WEEKDAY(CG481, 2) -> 4 | CM481: =IF(CL481=4, ((CI481 - CI476) / CI476)*100, "") -> 6.9693404 | CN481: =IF(MONTH(CH481)<>MONTH(CH480), CH481, "") | CO481: =IF(ISNUMBER(CN481), (INDEX(CI:CI, MATCH(EOMONTH(CH481, 0), CH:CH, 1)) / CI481 - 1) * 100, "") | CP481: 1.7747373 | CQ481: 6.9196584 | CS481: 45448 | CT481: 45470 | CU481: 797.95 | CW481: {=INDEX($AW$466:$AW$918, ROWS($AW$466:$AW$918) - ROW() + ROW($AW$466))} -> 44763 | CX481: {=INDEX($AX$466:$AX$918, ROWS($AX$466:$AX$918) - ROW() + ROW($AX$466))} -> 44770 | CY481: {=INDEX($CU$466:$CU$918, ROWS($CU$466:$CU$918) - ROW() + ROW($CU$466))} -> 360.35 | DA481: =((CY481-CY480)/CY480)*100 -> 0.86773968 | DB481: =WEEKDAY(CW481, 2) -> 4 | DC481: =IF(DB481=4, ((CY481 - CY476) / CY476)*100, "") -> 3.3706254 | DD481: =IF(MONTH(CX481)<>MONTH(CX480), CX481, "") | DE481: =IF(ISNUMBER(DD481), (INDEX(CY:CY, MATCH(EOMONTH(CX481, 0), CX:CX, 1)) / CY481 - 1) * 100, "") | DF481: 1.1784512 | DG481: 3.4571797 | DI481: 45448 | DJ481: 45470 | DK481: 583.5 | DM481: {=INDEX($AW$466:$AW$918, ROWS($AW$466:$AW$918) - ROW() + ROW($AW$466))} -> 44763 | DN481: {=INDEX($AX$466:$AX$918, ROWS($AX$466:$AX$918) - ROW() + ROW($AX$466))} -> 44770 | DO481: {=INDEX($DK$466:$DK$918, ROWS($DK$466:$DK$918) - ROW() + ROW($DK$466))} -> 323.05 | DQ481: =((DO481-DO480)/DO480)*100 -> 1.7961242 | DR481: =WEEKDAY(DM481, 2) -> 4 | DS481: =IF(DR481=4, ((DO481 - DO476) / DO476)*100, "") -> 5.1252847 | DT481: =IF(MONTH(DN481)<>MONTH(DN480), DN481, "") | DU481: =IF(ISNUMBER(DT481), (INDEX(DO:DO, MATCH(EOMONTH(DN481, 0), DN:DN, 1)) / DO481 - 1) * 100, "") | DV481: 1.6713092 | DW481: 12.780899
A482: 45447 | B482: 45470 | C482: 135.8 | E482: {=INDEX($A$466:$A$918, ROWS($A$466:$A$918) - ROW() + ROW($A$466))} -> 44764 | F482: {=INDEX($B$466:$B$918, ROWS($B$466:$B$918) - ROW() + ROW($B$466))} -> 44770 | G482: {=INDEX($C$466:$C$918, ROWS($C$466:$C$918) - ROW() + ROW($C$466))} -> 164.35 | I482: =((G482-G481)/G481)*100 -> 2.5905119 | J482: =WEEKDAY(E482, 2) -> 5 | K482: =IF(J482=4, ((G482 - G477) / G477)*100, "") | L482: =IF(MONTH(F482)<>MONTH(F481), F482, "") | M482: =IF(ISNUMBER(L482), (INDEX(G:G, MATCH(EOMONTH(F482, 0), F:F, 1)) / G482 - 1) * 100, "") | N482: 2.467208 | Q482: 45447 | R482: 45470 | S482: 36305.8 | U482: {=INDEX($Q$466:$Q$918, ROWS($Q$466:$Q$918) - ROW() + ROW($Q$466))} -> 44764 | V482: {=INDEX($R$466:$R$918, ROWS($R$466:$R$918) - ROW() + ROW($R$466))} -> 44770 | W482: {=INDEX($S$466:$S$918, ROWS($S$466:$S$918) - ROW() + ROW($S$466))} -> 45475.65 | Y482: =((W482-W481)/W481)*100 -> 0.7871145 | Z482: =WEEKDAY(U482, 2) -> 5 | AA482: =IF(Z482=4, ((W482 - W477) / W477)*100, "") | AB482: =IF(MONTH(V482)<>MONTH(V481), V482, "") | AC482: =IF(ISNUMBER(AB482), (INDEX(W:W, MATCH(EOMONTH(V482, 0), V:V, 1)) / W482 - 1) * 100, "") | AD482: 0.47854365 | AG482: 45447 | AH482: 45470 | AI482: 332.75 | AK482: {=INDEX($AG$466:$AG$918, ROWS($AG$466:$AG$918) - ROW() + ROW($AG$466))} -> 44764 | AL482: {=INDEX($AH$466:$AH$918, ROWS($AH$466:$AH$918) - ROW() + ROW($AH$466))} -> 44770 | AM482: {=INDEX($AI$466:$AI$918, ROWS($AI$466:$AI$918) - ROW() + ROW($AI$466))} -> 149.1 | AO482: =((AM482-AM481)/AM481)*100 -> -1.1600928 | AP482: =WEEKDAY(AK482, 2) -> 5 | AQ482: =IF(AP482=4, ((AM482 - AM477) / AM477)*100, "") | AR482: =IF(MONTH(AL482)<>MONTH(AL481), AL482, "") | AS482: =IF(ISNUMBER(AR482), (INDEX(AM:AM, MATCH(EOMONTH(AL482, 0), AL:AL, 1)) / AM482 - 1) * 100, "") | AT482: -0.85574572 | AW482: 45447 | AX482: 45470 | AY482: 256.4 | BA482: {=INDEX($AW$466:$AW$918, ROWS($AW$466:$AW$918) - ROW() + ROW($AW$466))} -> 44764 | BB482: {=INDEX($AX$466:$AX$918, ROWS($AX$466:$AX$918) - ROW() + ROW($AX$466))} -> 44770 | BC482: {=INDEX($AY$466:$AY$918, ROWS($AY$466:$AY$918) - ROW() + ROW($AY$466))} -> 267.5 | BE482: =((BC482-BC481)/BC481)*100 -> -0.66839955 | BF482: =WEEKDAY(BA482, 2) -> 5 | BG482: =IF(BF482=4, ((BC482 - BC477) / BC477)*100, "") | BH482: =IF(MONTH(BB482)<>MONTH(BB481), BB482, "") | BI482: =IF(ISNUMBER(BH482), (INDEX(BC:BC, MATCH(EOMONTH(BB482, 0), BB:BB, 1)) / BC482 - 1) * 100, "") | BJ482: -0.88454683 | BM482: 45447 | BN482: 45470 | BO482: 1341.3 | BQ482: {=INDEX($AW$466:$AW$918, ROWS($AW$466:$AW$918) - ROW() + ROW($AW$466))} -> 44764 | BR482: {=INDEX($AX$466:$AX$918, ROWS($AX$466:$AX$918) - ROW() + ROW($AX$466))} -> 44770 | BS482: {=INDEX($BO$466:$BO$918, ROWS($BO$466:$BO$918) - ROW() + ROW($BO$466))} -> 1167 | BU482: =((BS482-BS481)/BS481)*100 -> -0.34158839 | BV482: =WEEKDAY(BQ482, 2) -> 5 | BW482: =IF(BV482=4, ((BS482 - BS477) / BS477)*100, "") | BX482: =IF(MONTH(BR482)<>MONTH(BR481), BR482, "") | BY482: =IF(ISNUMBER(BX482), (INDEX(BS:BS, MATCH(EOMONTH(BR482, 0), BR:BR, 1)) / BS482 - 1) * 100, "") | BZ482: -1.3373803 | CC482: 45447 | CD482: 45470 | CE482: 1692.55 | CG482: {=INDEX($AW$466:$AW$918, ROWS($AW$466:$AW$918) - ROW() + ROW($AW$466))} -> 44764 | CH482: {=INDEX($AX$466:$AX$918, ROWS($AX$466:$AX$918) - ROW() + ROW($AX$466))} -> 44770 | CI482: {=INDEX($CE$466:$CE$918, ROWS($CE$466:$CE$918) - ROW() + ROW($CE$466))} -> 1596.15 | CK482: =((CI482-CI481)/CI481)*100 -> 3.2705745 | CL482: =WEEKDAY(CG482, 2) -> 5 | CM482: =IF(CL482=4, ((CI482 - CI477) / CI477)*100, "") | CN482: =IF(MONTH(CH482)<>MONTH(CH481), CH482, "") | CO482: =IF(ISNUMBER(CN482), (INDEX(CI:CI, MATCH(EOMONTH(CH482, 0), CH:CH, 1)) / CI482 - 1) * 100, "") | CP482: 3.6174704 | CS482: 45447 | CT482: 45470 | CU482: 765.15 | CW482: {=INDEX($AW$466:$AW$918, ROWS($AW$466:$AW$918) - ROW() + ROW($AW$466))} -> 44764 | CX482: {=INDEX($AX$466:$AX$918, ROWS($AX$466:$AX$918) - ROW() + ROW($AX$466))} -> 44770 | CY482: {=INDEX($CU$466:$CU$918, ROWS($CU$466:$CU$918) - ROW() + ROW($CU$466))} -> 361 | DA482: =((CY482-CY481)/CY481)*100 -> 0.18038019 | DB482: =WEEKDAY(CW482, 2) -> 5 | DC482: =IF(DB482=4, ((CY482 - CY477) / CY477)*100, "") | DD482: =IF(MONTH(CX482)<>MONTH(CX481), CX482, "") | DE482: =IF(ISNUMBER(DD482), (INDEX(CY:CY, MATCH(EOMONTH(CX482, 0), CX:CX, 1)) / CY482 - 1) * 100, "") | DF482: -0.12479201 | DI482: 45447 | DJ482: 45470 | DK482: 582.1 | DM482: {=INDEX($AW$466:$AW$918, ROWS($AW$466:$AW$918) - ROW() + ROW($AW$466))} -> 44764 | DN482: {=INDEX($AX$466:$AX$918, ROWS($AX$466:$AX$918) - ROW() + ROW($AX$466))} -> 44770 | DO482: {=INDEX($DK$466:$DK$918, ROWS($DK$466:$DK$918) - ROW() + ROW($DK$466))} -> 320.55 | DQ482: =((DO482-DO481)/DO481)*100 -> -0.77387401 | DR482: =WEEKDAY(DM482, 2) -> 5 | DS482: =IF(DR482=4, ((DO482 - DO477) / DO477)*100, "") | DT482: =IF(MONTH(DN482)<>MONTH(DN481), DN482, "") | DU482: =IF(ISNUMBER(DT482), (INDEX(DO:DO, MATCH(EOMONTH(DN482, 0), DN:DN, 1)) / DO482 - 1) * 100, "") | DV482: -2.5902864
A483: 45446 | B483: 45470 | C483: 147.95 | E483: {=INDEX($A$466:$A$918, ROWS($A$466:$A$918) - ROW() + ROW($A$466))} -> 44767 | F483: {=INDEX($B$466:$B$918, ROWS($B$466:$B$918) - ROW() + ROW($B$466))} -> 44770 | G483: {=INDEX($C$466:$C$918, ROWS($C$466:$C$918) - ROW() + ROW($C$466))} -> 162.3 | I483: =((G483-G482)/G482)*100 -> -1.247338 | J483: =WEEKDAY(E483, 2) -> 1 | K483: =IF(J483=4, ((G483 - G478) / G478)*100, "") | L483: =IF(MONTH(F483)<>MONTH(F482), F483, "") | M483: =IF(ISNUMBER(L483), (INDEX(G:G, MATCH(EOMONTH(F483, 0), F:F, 1)) / G483 - 1) * 100, "") | N483: -1.5239256 | Q483: 45446 | R483: 45470 | S483: 36573.65 | U483: {=INDEX($Q$466:$Q$918, ROWS($Q$466:$Q$918) - ROW() + ROW($Q$466))} -> 44767 | V483: {=INDEX($R$466:$R$918, ROWS($R$466:$R$918) - ROW() + ROW($R$466))} -> 44770 | W483: {=INDEX($S$466:$S$918, ROWS($S$466:$S$918) - ROW() + ROW($S$466))} -> 45640.05 | Y483: =((W483-W482)/W482)*100 -> 0.36151215 | Z483: =WEEKDAY(U483, 2) -> 1 | AA483: =IF(Z483=4, ((W483 - W478) / W478)*100, "") | AB483: =IF(MONTH(V483)<>MONTH(V482), V483, "") | AC483: =IF(ISNUMBER(AB483), (INDEX(W:W, MATCH(EOMONTH(V483, 0), V:V, 1)) / W483 - 1) * 100, "") | AD483: 0.60506214 | AG483: 45446 | AH483: 45470 | AI483: 394.1 | AK483: {=INDEX($AG$466:$AG$918, ROWS($AG$466:$AG$918) - ROW() + ROW($AG$466))} -> 44767 | AL483: {=INDEX($AH$466:$AH$918, ROWS($AH$466:$AH$918) - ROW() + ROW($AH$466))} -> 44770 | AM483: {=INDEX($AI$466:$AI$918, ROWS($AI$466:$AI$918) - ROW() + ROW($AI$466))} -> 149.95 | AO483: =((AM483-AM482)/AM482)*100 -> 0.57008719 | AP483: =WEEKDAY(AK483, 2) -> 1 | AQ483: =IF(AP483=4, ((AM483 - AM478) / AM478)*100, "") | AR483: =IF(MONTH(AL483)<>MONTH(AL482), AL483, "") | AS483: =IF(ISNUMBER(AR483), (INDEX(AM:AM, MATCH(EOMONTH(AL483, 0), AL:AL, 1)) / AM483 - 1) * 100, "") | AT483: -1.541307 | AW483: 45446 | AX483: 45470 | AY483: 320.4 | BA483: {=INDEX($AW$466:$AW$918, ROWS($AW$466:$AW$918) - ROW() + ROW($AW$466))} -> 44767 | BB483: {=INDEX($AX$466:$AX$918, ROWS($AX$466:$AX$918) - ROW() + ROW($AX$466))} -> 44770 | BC483: {=INDEX($AY$466:$AY$918, ROWS($AY$466:$AY$918) - ROW() + ROW($AY$466))} -> 270.5 | BE483: =((BC483-BC482)/BC482)*100 -> 1.1214953 | BF483: =WEEKDAY(BA483, 2) -> 1 | BG483: =IF(BF483=4, ((BC483 - BC478) / BC478)*100, "") | BH483: =IF(MONTH(BB483)<>MONTH(BB482), BB483, "") | BI483: =IF(ISNUMBER(BH483), (INDEX(BC:BC, MATCH(EOMONTH(BB483, 0), BB:BB, 1)) / BC483 - 1) * 100, "") | BJ483: -0.97236097 | BM483: 45446 | BN483: 45470 | BO483: 1401.8 | BQ483: {=INDEX($AW$466:$AW$918, ROWS($AW$466:$AW$918) - ROW() + ROW($AW$466))} -> 44767 | BR483: {=INDEX($AX$466:$AX$918, ROWS($AX$466:$AX$918) - ROW() + ROW($AX$466))} -> 44770 | BS483: {=INDEX($BO$466:$BO$918, ROWS($BO$466:$BO$918) - ROW() + ROW($BO$466))} -> 1147.25 | BU483: =((BS483-BS482)/BS482)*100 -> -1.6923736 | BV483: =WEEKDAY(BQ483, 2) -> 1 | BW483: =IF(BV483=4, ((BS483 - BS478) / BS478)*100, "") | BX483: =IF(MONTH(BR483)<>MONTH(BR482), BR483, "") | BY483: =IF(ISNUMBER(BX483), (INDEX(BS:BS, MATCH(EOMONTH(BR483, 0), BR:BR, 1)) / BS483 - 1) * 100, "") | BZ483: -3.9223226 | CC483: 45446 | CD483: 45470 | CE483: 1867.75 | CG483: {=INDEX($AW$466:$AW$918, ROWS($AW$466:$AW$918) - ROW() + ROW($AW$466))} -> 44767 | CH483: {=INDEX($AX$466:$AX$918, ROWS($AX$466:$AX$918) - ROW() + ROW($AX$466))} -> 44770 | CI483: {=INDEX($CE$466:$CE$918, ROWS($CE$466:$CE$918) - ROW() + ROW($CE$466))} -> 1551.45 | CK483: =((CI483-CI482)/CI482)*100 -> -2.8004887 | CL483: =WEEKDAY(CG483, 2) -> 1 | CM483: =IF(CL483=4, ((CI483 - CI478) / CI478)*100, "") | CN483: =IF(MONTH(CH483)<>MONTH(CH482), CH483, "") | CO483: =IF(ISNUMBER(CN483), (INDEX(CI:CI, MATCH(EOMONTH(CH483, 0), CH:CH, 1)) / CI483 - 1) * 100, "") | CP483: -2.8643956 | CS483: 45446 | CT483: 45470 | CU483: 873.35 | CW483: {=INDEX($AW$466:$AW$918, ROWS($AW$466:$AW$918) - ROW() + ROW($AW$466))} -> 44767 | CX483: {=INDEX($AX$466:$AX$918, ROWS($AX$466:$AX$918) - ROW() + ROW($AX$466))} -> 44770 | CY483: {=INDEX($CU$466:$CU$918, ROWS($CU$466:$CU$918) - ROW() + ROW($CU$466))} -> 358.15 | DA483: =((CY483-CY482)/CY482)*100 -> -0.78947368 | DB483: =WEEKDAY(CW483, 2) -> 1 | DC483: =IF(DB483=4, ((CY483 - CY478) / CY478)*100, "") | DD483: =IF(MONTH(CX483)<>MONTH(CX482), CX483, "") | DE483: =IF(ISNUMBER(DD483), (INDEX(CY:CY, MATCH(EOMONTH(CX483, 0), CX:CX, 1)) / CY483 - 1) * 100, "") | DF483: -0.77745384 | DI483: 45446 | DJ483: 45470 | DK483: 671.3 | DM483: {=INDEX($AW$466:$AW$918, ROWS($AW$466:$AW$918) - ROW() + ROW($AW$466))} -> 44767 | DN483: {=INDEX($AX$466:$AX$918, ROWS($AX$466:$AX$918) - ROW() + ROW($AX$466))} -> 44770 | DO483: {=INDEX($DK$466:$DK$918, ROWS($DK$466:$DK$918) - ROW() + ROW($DK$466))} -> 317.75 | DQ483: =((DO483-DO482)/DO482)*100 -> -0.87349867 | DR483: =WEEKDAY(DM483, 2) -> 1 | DS483: =IF(DR483=4, ((DO483 - DO478) / DO478)*100, "") | DT483: =IF(MONTH(DN483)<>MONTH(DN482), DN483, "") | DU483: =IF(ISNUMBER(DT483), (INDEX(DO:DO, MATCH(EOMONTH(DN483, 0), DN:DN, 1)) / DO483 - 1) * 100, "") | DV483: -4.6279724
A484: 45442 | B484: 45442 | C484: 142.4 | E484: {=INDEX($A$466:$A$918, ROWS($A$466:$A$918) - ROW() + ROW($A$466))} -> 44768 | F484: {=INDEX($B$466:$B$918, ROWS($B$466:$B$918) - ROW() + ROW($B$466))} -> 44770 | G484: {=INDEX($C$466:$C$918, ROWS($C$466:$C$918) - ROW() + ROW($C$466))} -> 162.75 | I484: =((G484-G483)/G483)*100 -> 0.27726433 | J484: =WEEKDAY(E484, 2) -> 2 | K484: =IF(J484=4, ((G484 - G479) / G479)*100, "") | L484: =IF(MONTH(F484)<>MONTH(F483), F484, "") | M484: =IF(ISNUMBER(L484), (INDEX(G:G, MATCH(EOMONTH(F484, 0), F:F, 1)) / G484 - 1) * 100, "") | N484: 0.40235221 | Q484: 45442 | R484: 45442 | S484: 38084.4 | U484: {=INDEX($Q$466:$Q$918, ROWS($Q$466:$Q$918) - ROW() + ROW($Q$466))} -> 44768 | V484: {=INDEX($R$466:$R$918, ROWS($R$466:$R$918) - ROW() + ROW($R$466))} -> 44770 | W484: {=INDEX($S$466:$S$918, ROWS($S$466:$S$918) - ROW() + ROW($S$466))} -> 46235.5 | Y484: =((W484-W483)/W483)*100 -> 1.3046655 | Z484: =WEEKDAY(U484, 2) -> 2 | AA484: =IF(Z484=4, ((W484 - W479) / W479)*100, "") | AB484: =IF(MONTH(V484)<>MONTH(V483), V484, "") | AC484: =IF(ISNUMBER(AB484), (INDEX(W:W, MATCH(EOMONTH(V484, 0), V:V, 1)) / W484 - 1) * 100, "") | AD484: 1.2651041 | AG484: 45442 | AH484: 45442 | AI484: 359.9 | AK484: {=INDEX($AG$466:$AG$918, ROWS($AG$466:$AG$918) - ROW() + ROW($AG$466))} -> 44768 | AL484: {=INDEX($AH$466:$AH$918, ROWS($AH$466:$AH$918) - ROW() + ROW($AH$466))} -> 44770 | AM484: {=INDEX($AI$466:$AI$918, ROWS($AI$466:$AI$918) - ROW() + ROW($AI$466))} -> 149.85 | AO484: =((AM484-AM483)/AM483)*100 -> -0.066688896 | AP484: =WEEKDAY(AK484, 2) -> 2 | AQ484: =IF(AP484=4, ((AM484 - AM479) / AM479)*100, "") | AR484: =IF(MONTH(AL484)<>MONTH(AL483), AL484, "") | AS484: =IF(ISNUMBER(AR484), (INDEX(AM:AM, MATCH(EOMONTH(AL484, 0), AL:AL, 1)) / AM484 - 1) * 100, "") | AT484: 9.6430808 | AW484: 45442 | AX484: 45442 | AY484: 290.85 | BA484: {=INDEX($AW$466:$AW$918, ROWS($AW$466:$AW$918) - ROW() + ROW($AW$466))} -> 44768 | BB484: {=INDEX($AX$466:$AX$918, ROWS($AX$466:$AX$918) - ROW() + ROW($AX$466))} -> 44770 | BC484: {=INDEX($AY$466:$AY$918, ROWS($AY$466:$AY$918) - ROW() + ROW($AY$466))} -> 267.15 | BE484: =((BC484-BC483)/BC483)*100 -> -1.2384473 | BF484: =WEEKDAY(BA484, 2) -> 2 | BG484: =IF(BF484=4, ((BC484 - BC479) / BC479)*100, "") | BH484: =IF(MONTH(BB484)<>MONTH(BB483), BB484, "") | BI484: =IF(ISNUMBER(BH484), (INDEX(BC:BC, MATCH(EOMONTH(BB484, 0), BB:BB, 1)) / BC484 - 1) * 100, "") | BJ484: -1.7687807 | BM484: 45442 | BN484: 45442 | BO484: 1376.55 | BQ484: {=INDEX($AW$466:$AW$918, ROWS($AW$466:$AW$918) - ROW() + ROW($AW$466))} -> 44768 | BR484: {=INDEX($AX$466:$AX$918, ROWS($AX$466:$AX$918) - ROW() + ROW($AX$466))} -> 44770 | BS484: {=INDEX($BO$466:$BO$918, ROWS($BO$466:$BO$918) - ROW() + ROW($BO$466))} -> 1140.6 | BU484: =((BS484-BS483)/BS483)*100 -> -0.57964698 | BV484: =WEEKDAY(BQ484, 2) -> 2 | BW484: =IF(BV484=4, ((BS484 - BS479) / BS479)*100, "") | BX484: =IF(MONTH(BR484)<>MONTH(BR483), BR484, "") | BY484: =IF(ISNUMBER(BX484), (INDEX(BS:BS, MATCH(EOMONTH(BR484, 0), BR:BR, 1)) / BS484 - 1) * 100, "") | BZ484: -5.573344 | CC484: 45442 | CD484: 45442 | CE484: 1762.5 | CG484: {=INDEX($AW$466:$AW$918, ROWS($AW$466:$AW$918) - ROW() + ROW($AW$466))} -> 44768 | CH484: {=INDEX($AX$466:$AX$918, ROWS($AX$466:$AX$918) - ROW() + ROW($AX$466))} -> 44770 | CI484: {=INDEX($CE$466:$CE$918, ROWS($CE$466:$CE$918) - ROW() + ROW($CE$466))} -> 1538.5 | CK484: =((CI484-CI483)/CI483)*100 -> -0.83470302 | CL484: =WEEKDAY(CG484, 2) -> 2 | CM484: =IF(CL484=4, ((CI484 - CI479) / CI479)*100, "") | CN484: =IF(MONTH(CH484)<>MONTH(CH483), CH484, "") | CO484: =IF(ISNUMBER(CN484), (INDEX(CI:CI, MATCH(EOMONTH(CH484, 0), CH:CH, 1)) / CI484 - 1) * 100, "") | CP484: -0.98725601 | CS484: 45442 | CT484: 45442 | CU484: 801.5 | CW484: {=INDEX($AW$466:$AW$918, ROWS($AW$466:$AW$918) - ROW() + ROW($AW$466))} -> 44768 | CX484: {=INDEX($AX$466:$AX$918, ROWS($AX$466:$AX$918) - ROW() + ROW($AX$466))} -> 44770 | CY484: {=INDEX($CU$466:$CU$918, ROWS($CU$466:$CU$918) - ROW() + ROW($CU$466))} -> 361 | DA484: =((CY484-CY483)/CY483)*100 -> 0.79575597 | DB484: =WEEKDAY(CW484, 2) -> 2 | DC484: =IF(DB484=4, ((CY484 - CY479) / CY479)*100, "") | DD484: =IF(MONTH(CX484)<>MONTH(CX483), CX484, "") | DE484: =IF(ISNUMBER(DD484), (INDEX(CY:CY, MATCH(EOMONTH(CX484, 0), CX:CX, 1)) / CY484 - 1) * 100, "") | DF484: 0.96544004 | DI484: 45442 | DJ484: 45442 | DK484: 625.6 | DM484: {=INDEX($AW$466:$AW$918, ROWS($AW$466:$AW$918) - ROW() + ROW($AW$466))} -> 44768 | DN484: {=INDEX($AX$466:$AX$918, ROWS($AX$466:$AX$918) - ROW() + ROW($AX$466))} -> 44770 | DO484: {=INDEX($DK$466:$DK$918, ROWS($DK$466:$DK$918) - ROW() + ROW($DK$466))} -> 318.2 | DQ484: =((DO484-DO483)/DO483)*100 -> 0.14162077 | DR484: =WEEKDAY(DM484, 2) -> 2 | DS484: =IF(DR484=4, ((DO484 - DO479) / DO479)*100, "") | DT484: =IF(MONTH(DN484)<>MONTH(DN483), DN484, "") | DU484: =IF(ISNUMBER(DT484), (INDEX(DO:DO, MATCH(EOMONTH(DN484, 0), DN:DN, 1)) / DO484 - 1) * 100, "") | DV484: -1.0991957
A485: 45441 | B485: 45442 | C485: 142.35 | E485: {=INDEX($A$466:$A$918, ROWS($A$466:$A$918) - ROW() + ROW($A$466))} -> 44769 | F485: {=INDEX($B$466:$B$918, ROWS($B$466:$B$918) - ROW() + ROW($B$466))} -> 44770 | G485: {=INDEX($C$466:$C$918, ROWS($C$466:$C$918) - ROW() + ROW($C$466))} -> 161.9 | I485: =((G485-G484)/G484)*100 -> -0.52227343 | J485: =WEEKDAY(E485, 2) -> 3 | K485: =IF(J485=4, ((G485 - G480) / G480)*100, "") | L485: =IF(MONTH(F485)<>MONTH(F484), F485, "") | M485: =IF(ISNUMBER(L485), (INDEX(G:G, MATCH(EOMONTH(F485, 0), F:F, 1)) / G485 - 1) * 100, "") | N485: -0.18495684 | Q485: 45441 | R485: 45442 | S485: 36679.1 | U485: {=INDEX($Q$466:$Q$918, ROWS($Q$466:$Q$918) - ROW() + ROW($Q$466))} -> 44769 | V485: {=INDEX($R$466:$R$918, ROWS($R$466:$R$918) - ROW() + ROW($R$466))} -> 44770 | W485: {=INDEX($S$466:$S$918, ROWS($S$466:$S$918) - ROW() + ROW($S$466))} -> 47244 | Y485: =((W485-W484)/W484)*100 -> 2.1812244 | Z485: =WEEKDAY(U485, 2) -> 3 | AA485: =IF(Z485=4, ((W485 - W480) / W480)*100, "") | AB485: =IF(MONTH(V485)<>MONTH(V484), V485, "") | AC485: =IF(ISNUMBER(AB485), (INDEX(W:W, MATCH(EOMONTH(V485, 0), V:V, 1)) / W485 - 1) * 100, "") | AD485: 2.3021438 | AG485: 45441 | AH485: 45442 | AI485: 364.45 | AK485: {=INDEX($AG$466:$AG$918, ROWS($AG$466:$AG$918) - ROW() + ROW($AG$466))} -> 44769 | AL485: {=INDEX($AH$466:$AH$918, ROWS($AH$466:$AH$918) - ROW() + ROW($AH$466))} -> 44770 | AM485: {=INDEX($AI$466:$AI$918, ROWS($AI$466:$AI$918) - ROW() + ROW($AI$466))} -> 149.75 | AO485: =((AM485-AM484)/AM484)*100 -> -0.0667334 | AP485: =WEEKDAY(AK485, 2) -> 3 | AQ485: =IF(AP485=4, ((AM485 - AM480) / AM480)*100, "") | AR485: =IF(MONTH(AL485)<>MONTH(AL484), AL485, "") | AS485: =IF(ISNUMBER(AR485), (INDEX(AM:AM, MATCH(EOMONTH(AL485, 0), AL:AL, 1)) / AM485 - 1) * 100, "") | AT485: -3.2552827 | AW485: 45441 | AX485: 45442 | AY485: 292.15 | BA485: {=INDEX($AW$466:$AW$918, ROWS($AW$466:$AW$918) - ROW() + ROW($AW$466))} -> 44769 | BB485: {=INDEX($AX$466:$AX$918, ROWS($AX$466:$AX$918) - ROW() + ROW($AX$466))} -> 44770 | BC485: {=INDEX($AY$466:$AY$918, ROWS($AY$466:$AY$918) - ROW() + ROW($AY$466))} -> 273.25 | BE485: =((BC485-BC484)/BC484)*100 -> 2.2833614 | BF485: =WEEKDAY(BA485, 2) -> 3 | BG485: =IF(BF485=4, ((BC485 - BC480) / BC480)*100, "") | BH485: =IF(MONTH(BB485)<>MONTH(BB484), BB485, "") | BI485: =IF(ISNUMBER(BH485), (INDEX(BC:BC, MATCH(EOMONTH(BB485, 0), BB:BB, 1)) / BC485 - 1) * 100, "") | BJ485: 5.0732576 | BM485: 45441 | BN485: 45442 | BO485: 1412.9 | BQ485: {=INDEX($AW$466:$AW$918, ROWS($AW$466:$AW$918) - ROW() + ROW($AW$466))} -> 44769 | BR485: {=INDEX($AX$466:$AX$918, ROWS($AX$466:$AX$918) - ROW() + ROW($AX$466))} -> 44770 | BS485: {=INDEX($BO$466:$BO$918, ROWS($BO$466:$BO$918) - ROW() + ROW($BO$466))} -> 1146.95 | BU485: =((BS485-BS484)/BS484)*100 -> 0.55672453 | BV485: =WEEKDAY(BQ485, 2) -> 3 | BW485: =IF(BV485=4, ((BS485 - BS480) / BS480)*100, "") | BX485: =IF(MONTH(BR485)<>MONTH(BR484), BR485, "") | BY485: =IF(ISNUMBER(BX485), (INDEX(BS:BS, MATCH(EOMONTH(BR485, 0), BR:BR, 1)) / BS485 - 1) * 100, "") | BZ485: -2.9246583 | CC485: 45441 | CD485: 45442 | CE485: 1781.2 | CG485: {=INDEX($AW$466:$AW$918, ROWS($AW$466:$AW$918) - ROW() + ROW($AW$466))} -> 44769 | CH485: {=INDEX($AX$466:$AX$918, ROWS($AX$466:$AX$918) - ROW() + ROW($AX$466))} -> 44770 | CI485: {=INDEX($CE$466:$CE$918, ROWS($CE$466:$CE$918) - ROW() + ROW($CE$466))} -> 1578.8 | CK485: =((CI485-CI484)/CI484)*100 -> 2.6194345 | CL485: =WEEKDAY(CG485, 2) -> 3 | CM485: =IF(CL485=4, ((CI485 - CI480) / CI480)*100, "") | CN485: =IF(MONTH(CH485)<>MONTH(CH484), CH485, "") | CO485: =IF(ISNUMBER(CN485), (INDEX(CI:CI, MATCH(EOMONTH(CH485, 0), CH:CH, 1)) / CI485 - 1) * 100, "") | CP485: 2.7371371 | CS485: 45441 | CT485: 45442 | CU485: 820.35 | CW485: {=INDEX($AW$466:$AW$918, ROWS($AW$466:$AW$918) - ROW() + ROW($AW$466))} -> 44769 | CX485: {=INDEX($AX$466:$AX$918, ROWS($AX$466:$AX$918) - ROW() + ROW($AX$466))} -> 44770 | CY485: {=INDEX($CU$466:$CU$918, ROWS($CU$466:$CU$918) - ROW() + ROW($CU$466))} -> 369.5 | DA485: =((CY485-CY484)/CY484)*100 -> 2.3545706 | DB485: =WEEKDAY(CW485, 2) -> 3 | DC485: =IF(DB485=4, ((CY485 - CY480) / CY480)*100, "") | DD485: =IF(MONTH(CX485)<>MONTH(CX484), CX485, "") | DE485: =IF(ISNUMBER(DD485), (INDEX(CY:CY, MATCH(EOMONTH(CX485, 0), CX:CX, 1)) / CY485 - 1) * 100, "") | DF485: 2.1757206 | DI485: 45441 | DJ485: 45442 | DK485: 634.8 | DM485: {=INDEX($AW$466:$AW$918, ROWS($AW$466:$AW$918) - ROW() + ROW($AW$466))} -> 44769 | DN485: {=INDEX($AX$466:$AX$918, ROWS($AX$466:$AX$918) - ROW() + ROW($AX$466))} -> 44770 | DO485: {=INDEX($DK$466:$DK$918, ROWS($DK$466:$DK$918) - ROW() + ROW($DK$466))} -> 324.65 | DQ485: =((DO485-DO484)/DO484)*100 -> 2.027027 | DR485: =WEEKDAY(DM485, 2) -> 3 | DS485: =IF(DR485=4, ((DO485 - DO480) / DO480)*100, "") | DT485: =IF(MONTH(DN485)<>MONTH(DN484), DN485, "") | DU485: =IF(ISNUMBER(DT485), (INDEX(DO:DO, MATCH(EOMONTH(DN485, 0), DN:DN, 1)) / DO485 - 1) * 100, "") | DV485: 1.3282732
A486: 45440 | B486: 45442 | C486: 144.15 | E486: {=INDEX($A$466:$A$918, ROWS($A$466:$A$918) - ROW() + ROW($A$466))} -> 44770 | F486: {=INDEX($B$466:$B$918, ROWS($B$466:$B$918) - ROW() + ROW($B$466))} -> 44770 | G486: {=INDEX($C$466:$C$918, ROWS($C$466:$C$918) - ROW() + ROW($C$466))} -> 161.25 | I486: =((G486-G485)/G485)*100 -> -0.4014824 | J486: =WEEKDAY(E486, 2) -> 4 | K486: =IF(J486=4, ((G486 - G481) / G481)*100, "") -> 0.65543071 | L486: =IF(MONTH(F486)<>MONTH(F485), F486, "") | M486: =IF(ISNUMBER(L486), (INDEX(G:G, MATCH(EOMONTH(F486, 0), F:F, 1)) / G486 - 1) * 100, "") | N486: -0.46324892 | O486: 0.6558401 | Q486: 45440 | R486: 45442 | S486: 36434.6 | U486: {=INDEX($Q$466:$Q$918, ROWS($Q$466:$Q$918) - ROW() + ROW($Q$466))} -> 44770 | V486: {=INDEX($R$466:$R$918, ROWS($R$466:$R$918) - ROW() + ROW($R$466))} -> 44770 | W486: {=INDEX($S$466:$S$918, ROWS($S$466:$S$918) - ROW() + ROW($S$466))} -> 47608.45 | Y486: =((W486-W485)/W485)*100 -> 0.77142071 | Z486: =WEEKDAY(U486, 2) -> 4 | AA486: =IF(Z486=4, ((W486 - W481) / W481)*100, "") -> 5.5140125 | AB486: =IF(MONTH(V486)<>MONTH(V485), V486, "") | AC486: =IF(ISNUMBER(AB486), (INDEX(W:W, MATCH(EOMONTH(V486, 0), V:V, 1)) / W486 - 1) * 100, "") | AD486: 1.0647021 | AE486: 5.8369251 | AG486: 45440 | AH486: 45442 | AI486: 366.35 | AK486: {=INDEX($AG$466:$AG$918, ROWS($AG$466:$AG$918) - ROW() + ROW($AG$466))} -> 44770 | AL486: {=INDEX($AH$466:$AH$918, ROWS($AH$466:$AH$918) - ROW() + ROW($AH$466))} -> 44770 | AM486: {=INDEX($AI$466:$AI$918, ROWS($AI$466:$AI$918) - ROW() + ROW($AI$466))} -> 150.15 | AO486: =((AM486-AM485)/AM485)*100 -> 0.26711185 | AP486: =WEEKDAY(AK486, 2) -> 4 | AQ486: =IF(AP486=4, ((AM486 - AM481) / AM481)*100, "") -> -0.46403712 | AR486: =IF(MONTH(AL486)<>MONTH(AL485), AL486, "") | AS486: =IF(ISNUMBER(AR486), (INDEX(AM:AM, MATCH(EOMONTH(AL486, 0), AL:AL, 1)) / AM486 - 1) * 100, "") | AT486: 2.7154664 | AU486: 6.3569682 | AW486: 45440 | AX486: 45442 | AY486: 289.85 | BA486: {=INDEX($AW$466:$AW$918, ROWS($AW$466:$AW$918) - ROW() + ROW($AW$466))} -> 44770 | BB486: {=INDEX($AX$466:$AX$918, ROWS($AX$466:$AX$918) - ROW() + ROW($AX$466))} -> 44770 | BC486: {=INDEX($AY$466:$AY$918, ROWS($AY$466:$AY$918) - ROW() + ROW($AY$466))} -> 272.6 | BE486: =((BC486-BC485)/BC485)*100 -> -0.2378774 | BF486: =WEEKDAY(BA486, 2) -> 4 | BG486: =IF(BF486=4, ((BC486 - BC481) / BC481)*100, "") -> 1.2253992 | BH486: =IF(MONTH(BB486)<>MONTH(BB485), BB486, "") | BI486: =IF(ISNUMBER(BH486), (INDEX(BC:BC, MATCH(EOMONTH(BB486, 0), BB:BB, 1)) / BC486 - 1) * 100, "") | BJ486: -1.3357659 | BK486: -0.04620767 | BM486: 45440 | BN486: 45442 | BO486: 1454.4 | BQ486: {=INDEX($AW$466:$AW$918, ROWS($AW$466:$AW$918) - ROW() + ROW($AW$466))} -> 44770 | BR486: {=INDEX($AX$466:$AX$918, ROWS($AX$466:$AX$918) - ROW() + ROW($AX$466))} -> 44770 | BS486: {=INDEX($BO$466:$BO$918, ROWS($BO$466:$BO$918) - ROW() + ROW($BO$466))} -> 1186.8 | BU486: =((BS486-BS485)/BS485)*100 -> 3.4744322 | BV486: =WEEKDAY(BQ486, 2) -> 4 | BW486: =IF(BV486=4, ((BS486 - BS481) / BS481)*100, "") -> 1.3492741 | BX486: =IF(MONTH(BR486)<>MONTH(BR485), BR486, "") | BY486: =IF(ISNUMBER(BX486), (INDEX(BS:BS, MATCH(EOMONTH(BR486, 0), BR:BR, 1)) / BS486 - 1) * 100, "") | BZ486: 0.31655933 | CA486: -12.833159 | CC486: 45440 | CD486: 45442 | CE486: 1801.05 | CG486: {=INDEX($AW$466:$AW$918, ROWS($AW$466:$AW$918) - ROW() + ROW($AW$466))} -> 44770 | CH486: {=INDEX($AX$466:$AX$918, ROWS($AX$466:$AX$918) - ROW() + ROW($AX$466))} -> 44770 | CI486: {=INDEX($CE$466:$CE$918, ROWS($CE$466:$CE$918) - ROW() + ROW($CE$466))} -> 1588.35 | CK486: =((CI486-CI485)/CI485)*100 -> 0.60488979 | CL486: =WEEKDAY(CG486, 2) -> 4 | CM486: =IF(CL486=4, ((CI486 - CI481) / CI481)*100, "") -> 2.7659161 | CN486: =IF(MONTH(CH486)<>MONTH(CH485), CH486, "") | CO486: =IF(ISNUMBER(CN486), (INDEX(CI:CI, MATCH(EOMONTH(CH486, 0), CH:CH, 1)) / CI486 - 1) * 100, "") | CP486: 0.56138793 | CQ486: 2.9582724 | CS486: 45440 | CT486: 45442 | CU486: 822.95 | CW486: {=INDEX($AW$466:$AW$918, ROWS($AW$466:$AW$918) - ROW() + ROW($AW$466))} -> 44770 | CX486: {=INDEX($AX$466:$AX$918, ROWS($AX$466:$AX$918) - ROW() + ROW($AX$466))} -> 44770 | CY486: {=INDEX($CU$466:$CU$918, ROWS($CU$466:$CU$918) - ROW() + ROW($CU$466))} -> 381.9 | DA486: =((CY486-CY485)/CY485)*100 -> 3.3558863 | DB486: =WEEKDAY(CW486, 2) -> 4 | DC486: =IF(DB486=4, ((CY486 - CY481) / CY481)*100, "") -> 5.9802969 | DD486: =IF(MONTH(CX486)<>MONTH(CX485), CX486, "") | DE486: =IF(ISNUMBER(DD486), (INDEX(CY:CY, MATCH(EOMONTH(CX486, 0), CX:CX, 1)) / CY486 - 1) * 100, "") | DF486: 3.621321 | DG486: 5.9345535 | DI486: 45440 | DJ486: 45442 | DK486: 647.95 | DM486: {=INDEX($AW$466:$AW$918, ROWS($AW$466:$AW$918) - ROW() + ROW($AW$466))} -> 44770 | DN486: {=INDEX($AX$466:$AX$918, ROWS($AX$466:$AX$918) - ROW() + ROW($AX$466))} -> 44770 | DO486: {=INDEX($DK$466:$DK$918, ROWS($DK$466:$DK$918) - ROW() + ROW($DK$466))} -> 326.15 | DQ486: =((DO486-DO485)/DO485)*100 -> 0.46203604 | DR486: =WEEKDAY(DM486, 2) -> 4 | DS486: =IF(DR486=4, ((DO486 - DO481) / DO481)*100, "") -> 0.95960378 | DT486: =IF(MONTH(DN486)<>MONTH(DN485), DN486, "") | DU486: =IF(ISNUMBER(DT486), (INDEX(DO:DO, MATCH(EOMONTH(DN486, 0), DN:DN, 1)) / DO486 - 1) * 100, "") | DV486: -0.16051364 | DW486: -7.0485679
A487: 45439 | B487: 45442 | C487: 144.8 | E487: {=INDEX($A$466:$A$918, ROWS($A$466:$A$918) - ROW() + ROW($A$466))} -> 44774 | F487: {=INDEX($B$466:$B$918, ROWS($B$466:$B$918) - ROW() + ROW($B$466))} -> 44798 | G487: {=INDEX($C$466:$C$918, ROWS($C$466:$C$918) - ROW() + ROW($C$466))} -> 161.2 | I487: =((G487-G486)/G486)*100 -> -0.031007752 | J487: =WEEKDAY(E487, 2) -> 1 | K487: =IF(J487=4, ((G487 - G482) / G482)*100, "") | L487: =IF(MONTH(F487)<>MONTH(F486), F487, "") -> 44798 | M487: =IF(ISNUMBER(L487), (INDEX(G:G, MATCH(EOMONTH(F487, 0), F:F, 1)) / G487 - 1) * 100, "") -> 16.470223 | N487: 0.15542431 | P487: 11.700807 | Q487: 45439 | R487: 45442 | S487: 36821.15 | U487: {=INDEX($Q$466:$Q$918, ROWS($Q$466:$Q$918) - ROW() + ROW($Q$466))} -> 44774 | V487: {=INDEX($R$466:$R$918, ROWS($R$466:$R$918) - ROW() + ROW($R$466))} -> 44798 | W487: {=INDEX($S$466:$S$918, ROWS($S$466:$S$918) - ROW() + ROW($S$466))} -> 49221.05 | Y487: =((W487-W486)/W486)*100 -> 3.3872138 | Z487: =WEEKDAY(U487, 2) -> 1 | AA487: =IF(Z487=4, ((W487 - W482) / W482)*100, "") | AB487: =IF(MONTH(V487)<>MONTH(V486), V487, "") -> 44798 | AC487: =IF(ISNUMBER(AB487), (INDEX(W:W, MATCH(EOMONTH(V487, 0), V:V, 1)) / W487 - 1) * 100, "") -> 1.1149701 | AD487: 0.71573261 | AF487: 3.6981846 | AG487: 45439 | AH487: 45442 | AI487: 370.55 | AK487: {=INDEX($AG$466:$AG$918, ROWS($AG$466:$AG$918) - ROW() + ROW($AG$466))} -> 44774 | AL487: {=INDEX($AH$466:$AH$918, ROWS($AH$466:$AH$918) - ROW() + ROW($AH$466))} -> 44798 | AM487: {=INDEX($AI$466:$AI$918, ROWS($AI$466:$AI$918) - ROW() + ROW($AI$466))} -> 154.45 | AO487: =((AM487-AM486)/AM486)*100 -> 2.8638029 | AP487: =WEEKDAY(AK487, 2) -> 1 | AQ487: =IF(AP487=4, ((AM487 - AM482) / AM482)*100, "") | AR487: =IF(MONTH(AL487)<>MONTH(AL486), AL487, "") -> 44798 | AS487: =IF(ISNUMBER(AR487), (INDEX(AM:AM, MATCH(EOMONTH(AL487, 0), AL:AL, 1)) / AM487 - 1) * 100, "") -> 2.8811913 | AT487: 5.9684685 | AV487: 18.756642 | AW487: 45439 | AX487: 45442 | AY487: 295 | BA487: {=INDEX($AW$466:$AW$918, ROWS($AW$466:$AW$918) - ROW() + ROW($AW$466))} -> 44774 | BB487: {=INDEX($AX$466:$AX$918, ROWS($AX$466:$AX$918) - ROW() + ROW($AX$466))} -> 44798 | BC487: {=INDEX($AY$466:$AY$918, ROWS($AY$466:$AY$918) - ROW() + ROW($AY$466))} -> 283 | BE487: =((BC487-BC486)/BC486)*100 -> 3.8151137 | BF487: =WEEKDAY(BA487, 2) -> 1 | BG487: =IF(BF487=4, ((BC487 - BC482) / BC482)*100, "") | BH487: =IF(MONTH(BB487)<>MONTH(BB486), BB487, "") -> 44798 | BI487: =IF(ISNUMBER(BH487), (INDEX(BC:BC, MATCH(EOMONTH(BB487, 0), BB:BB, 1)) / BC487 - 1) * 100, "") -> 4.8233216 | BJ487: 2.7378728 | BL487: 33.834964 | BM487: 45439 | BN487: 45442 | BO487: 1415.4 | BQ487: {=INDEX($AW$466:$AW$918, ROWS($AW$466:$AW$918) - ROW() + ROW($AW$466))} -> 44774 | BR487: {=INDEX($AX$466:$AX$918, ROWS($AX$466:$AX$918) - ROW() + ROW($AX$466))} -> 44798 | BS487: {=INDEX($BO$466:$BO$918, ROWS($BO$466:$BO$918) - ROW() + ROW($BO$466))} -> 1318.25 | BU487: =((BS487-BS486)/BS486)*100 -> 11.076003 | BV487: =WEEKDAY(BQ487, 2) -> 1 | BW487: =IF(BV487=4, ((BS487 - BS482) / BS482)*100, "") | BX487: =IF(MONTH(BR487)<>MONTH(BR486), BR487, "") -> 44798 | BY487: =IF(ISNUMBER(BX487), (INDEX(BS:BS, MATCH(EOMONTH(BR487, 0), BR:BR, 1)) / BS487 - 1) * 100, "") -> -1.5664707 | BZ487: 7.6775227 | CB487: -0.22808409 | CC487: 45439 | CD487: 45442 | CE487: 1803.4 | CG487: {=INDEX($AW$466:$AW$918, ROWS($AW$466:$AW$918) - ROW() + ROW($AW$466))} -> 44774 | CH487: {=INDEX($AX$466:$AX$918, ROWS($AX$466:$AX$918) - ROW() + ROW($AX$466))} -> 44798 | CI487: {=INDEX($CE$466:$CE$918, ROWS($CE$466:$CE$918) - ROW() + ROW($CE$466))} -> 1597.7 | CK487: =((CI487-CI486)/CI486)*100 -> 0.58866119 | CL487: =WEEKDAY(CG487, 2) -> 1 | CM487: =IF(CL487=4, ((CI487 - CI482) / CI482)*100, "") | CN487: =IF(MONTH(CH487)<>MONTH(CH486), CH487, "") -> 44798 | CO487: =IF(ISNUMBER(CN487), (INDEX(CI:CI, MATCH(EOMONTH(CH487, 0), CH:CH, 1)) / CI487 - 1) * 100, "") -> -3.8336359 | CP487: -0.83455756 | CR487: -3.1488369 | CS487: 45439 | CT487: 45442 | CU487: 842.95 | CW487: {=INDEX($AW$466:$AW$918, ROWS($AW$466:$AW$918) - ROW() + ROW($AW$466))} -> 44774 | CX487: {=INDEX($AX$466:$AX$918, ROWS($AX$466:$AX$918) - ROW() + ROW($AX$466))} -> 44798 | CY487: {=INDEX($CU$466:$CU$918, ROWS($CU$466:$CU$918) - ROW() + ROW($CU$466))} -> 383.1 | DA487: =((CY487-CY486)/CY486)*100 -> 0.31421838 | DB487: =WEEKDAY(CW487, 2) -> 1 | DC487: =IF(DB487=4, ((CY487 - CY482) / CY482)*100, "") | DD487: =IF(MONTH(CX487)<>MONTH(CX486), CX487, "") -> 44798 | DE487: =IF(ISNUMBER(DD487), (INDEX(CY:CY, MATCH(EOMONTH(CX487, 0), CX:CX, 1)) / CY487 - 1) * 100, "") -> -1.5270164 | DF487: -0.44047156 | DH487: 1.4964216 | DI487: 45439 | DJ487: 45442 | DK487: 658.2 | DM487: {=INDEX($AW$466:$AW$918, ROWS($AW$466:$AW$918) - ROW() + ROW($AW$466))} -> 44774 | DN487: {=INDEX($AX$466:$AX$918, ROWS($AX$466:$AX$918) - ROW() + ROW($AX$466))} -> 44798 | DO487: {=INDEX($DK$466:$DK$918, ROWS($DK$466:$DK$918) - ROW() + ROW($DK$466))} -> 330.5 | DQ487: =((DO487-DO486)/DO486)*100 -> 1.3337421 | DR487: =WEEKDAY(DM487, 2) -> 1 | DS487: =IF(DR487=4, ((DO487 - DO482) / DO482)*100, "") | DT487: =IF(MONTH(DN487)<>MONTH(DN486), DN487, "") -> 44798 | DU487: =IF(ISNUMBER(DT487), (INDEX(DO:DO, MATCH(EOMONTH(DN487, 0), DN:DN, 1)) / DO487 - 1) * 100, "") -> 0 | DV487: 2.0263158 | DX487: -0.54165592
A488: 45436 | B488: 45442 | C488: 144.85 | E488: {=INDEX($A$466:$A$918, ROWS($A$466:$A$918) - ROW() + ROW($A$466))} -> 44775 | F488: {=INDEX($B$466:$B$918, ROWS($B$466:$B$918) - ROW() + ROW($B$466))} -> 44798 | G488: {=INDEX($C$466:$C$918, ROWS($C$466:$C$918) - ROW() + ROW($C$466))} -> 162.9 | I488: =((G488-G487)/G487)*100 -> 1.0545906 | J488: =WEEKDAY(E488, 2) -> 2 | K488: =IF(J488=4, ((G488 - G483) / G483)*100, "") | L488: =IF(MONTH(F488)<>MONTH(F487), F488, "") | M488: =IF(ISNUMBER(L488), (INDEX(G:G, MATCH(EOMONTH(F488, 0), F:F, 1)) / G488 - 1) * 100, "") | N488: 1.3345748 | Q488: 45436 | R488: 45442 | S488: 35585.65 | U488: {=INDEX($Q$466:$Q$918, ROWS($Q$466:$Q$918) - ROW() + ROW($Q$466))} -> 44775 | V488: {=INDEX($R$466:$R$918, ROWS($R$466:$R$918) - ROW() + ROW($R$466))} -> 44798 | W488: {=INDEX($S$466:$S$918, ROWS($S$466:$S$918) - ROW() + ROW($S$466))} -> 49198.05 | Y488: =((W488-W487)/W487)*100 -> -0.046727975 | Z488: =WEEKDAY(U488, 2) -> 2 | AA488: =IF(Z488=4, ((W488 - W483) / W483)*100, "") | AB488: =IF(MONTH(V488)<>MONTH(V487), V488, "") | AC488: =IF(ISNUMBER(AB488), (INDEX(W:W, MATCH(EOMONTH(V488, 0), V:V, 1)) / W488 - 1) * 100, "") | AD488: -0.47803051 | AG488: 45436 | AH488: 45442 | AI488: 375.1 | AK488: {=INDEX($AG$466:$AG$918, ROWS($AG$466:$AG$918) - ROW() + ROW($AG$466))} -> 44775 | AL488: {=INDEX($AH$466:$AH$918, ROWS($AH$466:$AH$918) - ROW() + ROW($AH$466))} -> 44798 | AM488: {=INDEX($AI$466:$AI$918, ROWS($AI$466:$AI$918) - ROW() + ROW($AI$466))} -> 157.05 | AO488: =((AM488-AM487)/AM487)*100 -> 1.6833927 | AP488: =WEEKDAY(AK488, 2) -> 2 | AQ488: =IF(AP488=4, ((AM488 - AM483) / AM483)*100, "") | AR488: =IF(MONTH(AL488)<>MONTH(AL487), AL488, "") | AS488: =IF(ISNUMBER(AR488), (INDEX(AM:AM, MATCH(EOMONTH(AL488, 0), AL:AL, 1)) / AM488 - 1) * 100, "") | AT488: 3.8788523 | AW488: 45436 | AX488: 45442 | AY488: 297.15 | BA488: {=INDEX($AW$466:$AW$918, ROWS($AW$466:$AW$918) - ROW() + ROW($AW$466))} -> 44775 | BB488: {=INDEX($AX$466:$AX$918, ROWS($AX$466:$AX$918) - ROW() + ROW($AX$466))} -> 44798 | BC488: {=INDEX($AY$466:$AY$918, ROWS($AY$466:$AY$918) - ROW() + ROW($AY$466))} -> 281.5 | BE488: =((BC488-BC487)/BC487)*100 -> -0.53003534 | BF488: =WEEKDAY(BA488, 2) -> 2 | BG488: =IF(BF488=4, ((BC488 - BC483) / BC483)*100, "") | BH488: =IF(MONTH(BB488)<>MONTH(BB487), BB488, "") | BI488: =IF(ISNUMBER(BH488), (INDEX(BC:BC, MATCH(EOMONTH(BB488, 0), BB:BB, 1)) / BC488 - 1) * 100, "") | BJ488: -5.8251818 | BM488: 45436 | BN488: 45442 | BO488: 1439.25 | BQ488: {=INDEX($AW$466:$AW$918, ROWS($AW$466:$AW$918) - ROW() + ROW($AW$466))} -> 44775 | BR488: {=INDEX($AX$466:$AX$918, ROWS($AX$466:$AX$918) - ROW() + ROW($AX$466))} -> 44798 | BS488: {=INDEX($BO$466:$BO$918, ROWS($BO$466:$BO$918) - ROW() + ROW($BO$466))} -> 1291.45 | BU488: =((BS488-BS487)/BS487)*100 -> -2.0329983 | BV488: =WEEKDAY(BQ488, 2) -> 2 | BW488: =IF(BV488=4, ((BS488 - BS483) / BS483)*100, "") | BX488: =IF(MONTH(BR488)<>MONTH(BR487), BR488, "") | BY488: =IF(ISNUMBER(BX488), (INDEX(BS:BS, MATCH(EOMONTH(BR488, 0), BR:BR, 1)) / BS488 - 1) * 100, "") | BZ488: 10.948036 | CC488: 45436 | CD488: 45442 | CE488: 1790.85 | CG488: {=INDEX($AW$466:$AW$918, ROWS($AW$466:$AW$918) - ROW() + ROW($AW$466))} -> 44775 | CH488: {=INDEX($AX$466:$AX$918, ROWS($AX$466:$AX$918) - ROW() + ROW($AX$466))} -> 44798 | CI488: {=INDEX($CE$466:$CE$918, ROWS($CE$466:$CE$918) - ROW() + ROW($CE$466))} -> 1588.55 | CK488: =((CI488-CI487)/CI487)*100 -> -0.57269825 | CL488: =WEEKDAY(CG488, 2) -> 2 | CM488: =IF(CL488=4, ((CI488 - CI483) / CI483)*100, "") | CN488: =IF(MONTH(CH488)<>MONTH(CH487), CH488, "") | CO488: =IF(ISNUMBER(CN488), (INDEX(CI:CI, MATCH(EOMONTH(CH488, 0), CH:CH, 1)) / CI488 - 1) * 100, "") | CP488: -0.24270315 | CS488: 45436 | CT488: 45442 | CU488: 842.2 | CW488: {=INDEX($AW$466:$AW$918, ROWS($AW$466:$AW$918) - ROW() + ROW($AW$466))} -> 44775 | CX488: {=INDEX($AX$466:$AX$918, ROWS($AX$466:$AX$918) - ROW() + ROW($AX$466))} -> 44798 | CY488: {=INDEX($CU$466:$CU$918, ROWS($CU$466:$CU$918) - ROW() + ROW($CU$466))} -> 378.05 | DA488: =((CY488-CY487)/CY487)*100 -> -1.3181937 | DB488: =WEEKDAY(CW488, 2) -> 2 | DC488: =IF(DB488=4, ((CY488 - CY483) / CY483)*100, "") | DD488: =IF(MONTH(CX488)<>MONTH(CX487), CX488, "") | DE488: =IF(ISNUMBER(DD488), (INDEX(CY:CY, MATCH(EOMONTH(CX488, 0), CX:CX, 1)) / CY488 - 1) * 100, "") | DF488: -1.977879 | DI488: 45436 | DJ488: 45442 | DK488: 654.75 | DM488: {=INDEX($AW$466:$AW$918, ROWS($AW$466:$AW$918) - ROW() + ROW($AW$466))} -> 44775 | DN488: {=INDEX($AX$466:$AX$918, ROWS($AX$466:$AX$918) - ROW() + ROW($AX$466))} -> 44798 | DO488: {=INDEX($DK$466:$DK$918, ROWS($DK$466:$DK$918) - ROW() + ROW($DK$466))} -> 330.55 | DQ488: =((DO488-DO487)/DO487)*100 -> 0.015128593 | DR488: =WEEKDAY(DM488, 2) -> 2 | DS488: =IF(DR488=4, ((DO488 - DO483) / DO483)*100, "") | DT488: =IF(MONTH(DN488)<>MONTH(DN487), DN488, "") | DU488: =IF(ISNUMBER(DT488), (INDEX(DO:DO, MATCH(EOMONTH(DN488, 0), DN:DN, 1)) / DO488 - 1) * 100, "") | DV488: -1.7539335
A489: 45435 | B489: 45442 | C489: 144.25 | E489: {=INDEX($A$466:$A$918, ROWS($A$466:$A$918) - ROW() + ROW($A$466))} -> 44776 | F489: {=INDEX($B$466:$B$918, ROWS($B$466:$B$918) - ROW() + ROW($B$466))} -> 44798 | G489: {=INDEX($C$466:$C$918, ROWS($C$466:$C$918) - ROW() + ROW($C$466))} -> 162.3 | I489: =((G489-G488)/G488)*100 -> -0.36832413 | J489: =WEEKDAY(E489, 2) -> 3 | K489: =IF(J489=4, ((G489 - G484) / G484)*100, "") | L489: =IF(MONTH(F489)<>MONTH(F488), F489, "") | M489: =IF(ISNUMBER(L489), (INDEX(G:G, MATCH(EOMONTH(F489, 0), F:F, 1)) / G489 - 1) * 100, "") | N489: -0.4287902 | Q489: 45435 | R489: 45442 | S489: 35266.7 | U489: {=INDEX($Q$466:$Q$918, ROWS($Q$466:$Q$918) - ROW() + ROW($Q$466))} -> 44776 | V489: {=INDEX($R$466:$R$918, ROWS($R$466:$R$918) - ROW() + ROW($R$466))} -> 44798 | W489: {=INDEX($S$466:$S$918, ROWS($S$466:$S$918) - ROW() + ROW($S$466))} -> 48213.65 | Y489: =((W489-W488)/W488)*100 -> -2.0008923 | Z489: =WEEKDAY(U489, 2) -> 3 | AA489: =IF(Z489=4, ((W489 - W484) / W484)*100, "") | AB489: =IF(MONTH(V489)<>MONTH(V488), V489, "") | AC489: =IF(ISNUMBER(AB489), (INDEX(W:W, MATCH(EOMONTH(V489, 0), V:V, 1)) / W489 - 1) * 100, "") | AD489: -1.9798928 | AG489: 45435 | AH489: 45442 | AI489: 372.6 | AK489: {=INDEX($AG$466:$AG$918, ROWS($AG$466:$AG$918) - ROW() + ROW($AG$466))} -> 44776 | AL489: {=INDEX($AH$466:$AH$918, ROWS($AH$466:$AH$918) - ROW() + ROW($AH$466))} -> 44798 | AM489: {=INDEX($AI$466:$AI$918, ROWS($AI$466:$AI$918) - ROW() + ROW($AI$466))} -> 157.1 | AO489: =((AM489-AM488)/AM488)*100 -> 0.031836995 | AP489: =WEEKDAY(AK489, 2) -> 3 | AQ489: =IF(AP489=4, ((AM489 - AM484) / AM484)*100, "") | AR489: =IF(MONTH(AL489)<>MONTH(AL488), AL489, "") | AS489: =IF(ISNUMBER(AR489), (INDEX(AM:AM, MATCH(EOMONTH(AL489, 0), AL:AL, 1)) / AM489 - 1) * 100, "") | AT489: 4.5524297 | AW489: 45435 | AX489: 45442 | AY489: 288.7 | BA489: {=INDEX($AW$466:$AW$918, ROWS($AW$466:$AW$918) - ROW() + ROW($AW$466))} -> 44776 | BB489: {=INDEX($AX$466:$AX$918, ROWS($AX$466:$AX$918) - ROW() + ROW($AX$466))} -> 44798 | BC489: {=INDEX($AY$466:$AY$918, ROWS($AY$466:$AY$918) - ROW() + ROW($AY$466))} -> 276.45 | BE489: =((BC489-BC488)/BC488)*100 -> -1.7939609 | BF489: =WEEKDAY(BA489, 2) -> 3 | BG489: =IF(BF489=4, ((BC489 - BC484) / BC484)*100, "") | BH489: =IF(MONTH(BB489)<>MONTH(BB488), BB489, "") | BI489: =IF(ISNUMBER(BH489), (INDEX(BC:BC, MATCH(EOMONTH(BB489, 0), BB:BB, 1)) / BC489 - 1) * 100, "") | BJ489: 3.3024835 | BM489: 45435 | BN489: 45442 | BO489: 1447.8 | BQ489: {=INDEX($AW$466:$AW$918, ROWS($AW$466:$AW$918) - ROW() + ROW($AW$466))} -> 44776 | BR489: {=INDEX($AX$466:$AX$918, ROWS($AX$466:$AX$918) - ROW() + ROW($AX$466))} -> 44798 | BS489: {=INDEX($BO$466:$BO$918, ROWS($BO$466:$BO$918) - ROW() + ROW($BO$466))} -> 1289.05 | BU489: =((BS489-BS488)/BS488)*100 -> -0.18583762 | BV489: =WEEKDAY(BQ489, 2) -> 3 | BW489: =IF(BV489=4, ((BS489 - BS484) / BS484)*100, "") | BX489: =IF(MONTH(BR489)<>MONTH(BR488), BR489, "") | BY489: =IF(ISNUMBER(BX489), (INDEX(BS:BS, MATCH(EOMONTH(BR489, 0), BR:BR, 1)) / BS489 - 1) * 100, "") | BZ489: -0.70611369 | CC489: 45435 | CD489: 45442 | CE489: 1810.6 | CG489: {=INDEX($AW$466:$AW$918, ROWS($AW$466:$AW$918) - ROW() + ROW($AW$466))} -> 44776 | CH489: {=INDEX($AX$466:$AX$918, ROWS($AX$466:$AX$918) - ROW() + ROW($AX$466))} -> 44798 | CI489: {=INDEX($CE$466:$CE$918, ROWS($CE$466:$CE$918) - ROW() + ROW($CE$466))} -> 1555.05 | CK489: =((CI489-CI488)/CI488)*100 -> -2.1088414 | CL489: =WEEKDAY(CG489, 2) -> 3 | CM489: =IF(CL489=4, ((CI489 - CI484) / CI484)*100, "") | CN489: =IF(MONTH(CH489)<>MONTH(CH488), CH489, "") | CO489: =IF(ISNUMBER(CN489), (INDEX(CI:CI, MATCH(EOMONTH(CH489, 0), CH:CH, 1)) / CI489 - 1) * 100, "") | CP489: -2.2212392 | CS489: 45435 | CT489: 45442 | CU489: 849.95 | CW489: {=INDEX($AW$466:$AW$918, ROWS($AW$466:$AW$918) - ROW() + ROW($AW$466))} -> 44776 | CX489: {=INDEX($AX$466:$AX$918, ROWS($AX$466:$AX$918) - ROW() + ROW($AX$466))} -> 44798 | CY489: {=INDEX($CU$466:$CU$918, ROWS($CU$466:$CU$918) - ROW() + ROW($CU$466))} -> 374.1 | DA489: =((CY489-CY488)/CY488)*100 -> -1.0448353 | DB489: =WEEKDAY(CW489, 2) -> 3 | DC489: =IF(DB489=4, ((CY489 - CY484) / CY484)*100, "") | DD489: =IF(MONTH(CX489)<>MONTH(CX488), CX489, "") | DE489: =IF(ISNUMBER(DD489), (INDEX(CY:CY, MATCH(EOMONTH(CX489, 0), CX:CX, 1)) / CY489 - 1) * 100, "") | DF489: -1.1814682 | DI489: 45435 | DJ489: 45442 | DK489: 648.55 | DM489: {=INDEX($AW$466:$AW$918, ROWS($AW$466:$AW$918) - ROW() + ROW($AW$466))} -> 44776 | DN489: {=INDEX($AX$466:$AX$918, ROWS($AX$466:$AX$918) - ROW() + ROW($AX$466))} -> 44798 | DO489: {=INDEX($DK$466:$DK$918, ROWS($DK$466:$DK$918) - ROW() + ROW($DK$466))} -> 329.25 | DQ489: =((DO489-DO488)/DO488)*100 -> -0.39328392 | DR489: =WEEKDAY(DM489, 2) -> 3 | DS489: =IF(DR489=4, ((DO489 - DO484) / DO484)*100, "") | DT489: =IF(MONTH(DN489)<>MONTH(DN488), DN489, "") | DU489: =IF(ISNUMBER(DT489), (INDEX(DO:DO, MATCH(EOMONTH(DN489, 0), DN:DN, 1)) / DO489 - 1) * 100, "") | DV489: -0.57757942
A490: 45434 | B490: 45442 | C490: 144.25 | E490: {=INDEX($A$466:$A$918, ROWS($A$466:$A$918) - ROW() + ROW($A$466))} -> 44777 | F490: {=INDEX($B$466:$B$918, ROWS($B$466:$B$918) - ROW() + ROW($B$466))} -> 44798 | G490: {=INDEX($C$466:$C$918, ROWS($C$466:$C$918) - ROW() + ROW($C$466))} -> 159.75 | I490: =((G490-G489)/G489)*100 -> -1.5711645 | J490: =WEEKDAY(E490, 2) -> 4 | K490: =IF(J490=4, ((G490 - G485) / G485)*100, "") -> -1.3279802 | L490: =IF(MONTH(F490)<>MONTH(F489), F490, "") | M490: =IF(ISNUMBER(L490), (INDEX(G:G, MATCH(EOMONTH(F490, 0), F:F, 1)) / G490 - 1) * 100, "") | N490: -1.6610274 | O490: -0.80670183 | Q490: 45434 | R490: 45442 | S490: 35638.05 | U490: {=INDEX($Q$466:$Q$918, ROWS($Q$466:$Q$918) - ROW() + ROW($Q$466))} -> 44777 | V490: {=INDEX($R$466:$R$918, ROWS($R$466:$R$918) - ROW() + ROW($R$466))} -> 44798 | W490: {=INDEX($S$466:$S$918, ROWS($S$466:$S$918) - ROW() + ROW($S$466))} -> 49041.5 | Y490: =((W490-W489)/W489)*100 -> 1.7170449 | Z490: =WEEKDAY(U490, 2) -> 4 | AA490: =IF(Z490=4, ((W490 - W485) / W485)*100, "") -> 3.8047159 | AB490: =IF(MONTH(V490)<>MONTH(V489), V490, "") | AC490: =IF(ISNUMBER(AB490), (INDEX(W:W, MATCH(EOMONTH(V490, 0), V:V, 1)) / W490 - 1) * 100, "") | AD490: 2.1015211 | AE490: 2.6511448 | AG490: 45434 | AH490: 45442 | AI490: 374.1 | AK490: {=INDEX($AG$466:$AG$918, ROWS($AG$466:$AG$918) - ROW() + ROW($AG$466))} -> 44777 | AL490: {=INDEX($AH$466:$AH$918, ROWS($AH$466:$AH$918) - ROW() + ROW($AH$466))} -> 44798 | AM490: {=INDEX($AI$466:$AI$918, ROWS($AI$466:$AI$918) - ROW() + ROW($AI$466))} -> 152.05 | AO490: =((AM490-AM489)/AM489)*100 -> -3.214513 | AP490: =WEEKDAY(AK490, 2) -> 4 | AQ490: =IF(AP490=4, ((AM490 - AM485) / AM485)*100, "") -> 1.5358932 | AR490: =IF(MONTH(AL490)<>MONTH(AL489), AL490, "") | AS490: =IF(ISNUMBER(AR490), (INDEX(AM:AM, MATCH(EOMONTH(AL490, 0), AL:AL, 1)) / AM490 - 1) * 100, "") | AT490: -0.048923679 | AU490: 17.413793 | AW490: 45434 | AX490: 45442 | AY490: 283.85 | BA490: {=INDEX($AW$466:$AW$918, ROWS($AW$466:$AW$918) - ROW() + ROW($AW$466))} -> 44777 | BB490: {=INDEX($AX$466:$AX$918, ROWS($AX$466:$AX$918) - ROW() + ROW($AX$466))} -> 44798 | BC490: {=INDEX($AY$466:$AY$918, ROWS($AY$466:$AY$918) - ROW() + ROW($AY$466))} -> 283.25 | BE490: =((BC490-BC489)/BC489)*100 -> 2.4597576 | BF490: =WEEKDAY(BA490, 2) -> 4 | BG490: =IF(BF490=4, ((BC490 - BC485) / BC485)*100, "") -> 3.6596523 | BH490: =IF(MONTH(BB490)<>MONTH(BB489), BB490, "") | BI490: =IF(ISNUMBER(BH490), (INDEX(BC:BC, MATCH(EOMONTH(BB490, 0), BB:BB, 1)) / BC490 - 1) * 100, "") | BJ490: 3.0808895 | BK490: 5.6201294 | BM490: 45434 | BN490: 45442 | BO490: 1428.6 | BQ490: {=INDEX($AW$466:$AW$918, ROWS($AW$466:$AW$918) - ROW() + ROW($AW$466))} -> 44777 | BR490: {=INDEX($AX$466:$AX$918, ROWS($AX$466:$AX$918) - ROW() + ROW($AX$466))} -> 44798 | BS490: {=INDEX($BO$466:$BO$918, ROWS($BO$466:$BO$918) - ROW() + ROW($BO$466))} -> 1281.15 | BU490: =((BS490-BS489)/BS489)*100 -> -0.61285443 | BV490: =WEEKDAY(BQ490, 2) -> 4 | BW490: =IF(BV490=4, ((BS490 - BS485) / BS485)*100, "") -> 11.700597 | BX490: =IF(MONTH(BR490)<>MONTH(BR489), BR490, "") | BY490: =IF(ISNUMBER(BX490), (INDEX(BS:BS, MATCH(EOMONTH(BR490, 0), BR:BR, 1)) / BS490 - 1) * 100, "") | BZ490: -1.0081916 | CA490: 19.662677 | CC490: 45434 | CD490: 45442 | CE490: 1848.4 | CG490: {=INDEX($AW$466:$AW$918, ROWS($AW$466:$AW$918) - ROW() + ROW($AW$466))} -> 44777 | CH490: {=INDEX($AX$466:$AX$918, ROWS($AX$466:$AX$918) - ROW() + ROW($AX$466))} -> 44798 | CI490: {=INDEX($CE$466:$CE$918, ROWS($CE$466:$CE$918) - ROW() + ROW($CE$466))} -> 1569.5 | CK490: =((CI490-CI489)/CI489)*100 -> 0.92923057 | CL490: =WEEKDAY(CG490, 2) -> 4 | CM490: =IF(CL490=4, ((CI490 - CI485) / CI485)*100, "") -> -0.58905498 | CN490: =IF(MONTH(CH490)<>MONTH(CH489), CH490, "") | CO490: =IF(ISNUMBER(CN490), (INDEX(CI:CI, MATCH(EOMONTH(CH490, 0), CH:CH, 1)) / CI490 - 1) * 100, "") | CP490: 0.9403477 | CQ490: -1.4792153 | CS490: 45434 | CT490: 45442 | CU490: 848.25 | CW490: {=INDEX($AW$466:$AW$918, ROWS($AW$466:$AW$918) - ROW() + ROW($AW$466))} -> 44777 | CX490: {=INDEX($AX$466:$AX$918, ROWS($AX$466:$AX$918) - ROW() + ROW($AX$466))} -> 44798 | CY490: {=INDEX($CU$466:$CU$918, ROWS($CU$466:$CU$918) - ROW() + ROW($CU$466))} -> 368.7 | DA490: =((CY490-CY489)/CY489)*100 -> -1.4434643 | DB490: =WEEKDAY(CW490, 2) -> 4 | DC490: =IF(DB490=4, ((CY490 - CY485) / CY485)*100, "") -> -0.2165088 | DD490: =IF(MONTH(CX490)<>MONTH(CX489), CX490, "") | DE490: =IF(ISNUMBER(DD490), (INDEX(CY:CY, MATCH(EOMONTH(CX490, 0), CX:CX, 1)) / CY490 - 1) * 100, "") | DF490: -1.2358947 | DG490: -3.7696335 | DI490: 45434 | DJ490: 45442 | DK490: 642.55 | DM490: {=INDEX($AW$466:$AW$918, ROWS($AW$466:$AW$918) - ROW() + ROW($AW$466))} -> 44777 | DN490: {=INDEX($AX$466:$AX$918, ROWS($AX$466:$AX$918) - ROW() + ROW($AX$466))} -> 44798 | DO490: {=INDEX($DK$466:$DK$918, ROWS($DK$466:$DK$918) - ROW() + ROW($DK$466))} -> 329.3 | DQ490: =((DO490-DO489)/DO489)*100 -> 0.015186029 | DR490: =WEEKDAY(DM490, 2) -> 4 | DS490: =IF(DR490=4, ((DO490 - DO485) / DO485)*100, "") -> 1.4323117 | DT490: =IF(MONTH(DN490)<>MONTH(DN489), DN490, "") | DU490: =IF(ISNUMBER(DT490), (INDEX(DO:DO, MATCH(EOMONTH(DN490, 0), DN:DN, 1)) / DO490 - 1) * 100, "") | DV490: -0.73937153 | DW490: 0.72347267
A491: 45433 | B491: 45442 | C491: 145.15 | E491: {=INDEX($A$466:$A$918, ROWS($A$466:$A$918) - ROW() + ROW($A$466))} -> 44778 | F491: {=INDEX($B$466:$B$918, ROWS($B$466:$B$918) - ROW() + ROW($B$466))} -> 44798 | G491: {=INDEX($C$466:$C$918, ROWS($C$466:$C$918) - ROW() + ROW($C$466))} -> 160.7 | I491: =((G491-G490)/G490)*100 -> 0.59467919 | J491: =WEEKDAY(E491, 2) -> 5 | K491: =IF(J491=4, ((G491 - G486) / G486)*100, "") | L491: =IF(MONTH(F491)<>MONTH(F490), F491, "") | M491: =IF(ISNUMBER(L491), (INDEX(G:G, MATCH(EOMONTH(F491, 0), F:F, 1)) / G491 - 1) * 100, "") | N491: 0.75070378 | Q491: 45433 | R491: 45442 | S491: 34873 | U491: {=INDEX($Q$466:$Q$918, ROWS($Q$466:$Q$918) - ROW() + ROW($Q$466))} -> 44778 | V491: {=INDEX($R$466:$R$918, ROWS($R$466:$R$918) - ROW() + ROW($R$466))} -> 44798 | W491: {=INDEX($S$466:$S$918, ROWS($S$466:$S$918) - ROW() + ROW($S$466))} -> 48370.9 | Y491: =((W491-W490)/W490)*100 -> -1.3674133 | Z491: =WEEKDAY(U491, 2) -> 5 | AA491: =IF(Z491=4, ((W491 - W486) / W486)*100, "") | AB491: =IF(MONTH(V491)<>MONTH(V490), V491, "") | AC491: =IF(ISNUMBER(AB491), (INDEX(W:W, MATCH(EOMONTH(V491, 0), V:V, 1)) / W491 - 1) * 100, "") | AD491: -1.6625635 | AG491: 45433 | AH491: 45442 | AI491: 373.05 | AK491: {=INDEX($AG$466:$AG$918, ROWS($AG$466:$AG$918) - ROW() + ROW($AG$466))} -> 44778 | AL491: {=INDEX($AH$466:$AH$918, ROWS($AH$466:$AH$918) - ROW() + ROW($AH$466))} -> 44798 | AM491: {=INDEX($AI$466:$AI$918, ROWS($AI$466:$AI$918) - ROW() + ROW($AI$466))} -> 153.5 | AO491: =((AM491-AM490)/AM490)*100 -> 0.95363367 | AP491: =WEEKDAY(AK491, 2) -> 5 | AQ491: =IF(AP491=4, ((AM491 - AM486) / AM486)*100, "") | AR491: =IF(MONTH(AL491)<>MONTH(AL490), AL491, "") | AS491: =IF(ISNUMBER(AR491), (INDEX(AM:AM, MATCH(EOMONTH(AL491, 0), AL:AL, 1)) / AM491 - 1) * 100, "") | AT491: 1.9089574 | AW491: 45433 | AX491: 45442 | AY491: 274.9 | BA491: {=INDEX($AW$466:$AW$918, ROWS($AW$466:$AW$918) - ROW() + ROW($AW$466))} -> 44778 | BB491: {=INDEX($AX$466:$AX$918, ROWS($AX$466:$AX$918) - ROW() + ROW($AX$466))} -> 44798 | BC491: {=INDEX($AY$466:$AY$918, ROWS($AY$466:$AY$918) - ROW() + ROW($AY$466))} -> 274.75 | BE491: =((BC491-BC490)/BC490)*100 -> -3.0008826 | BF491: =WEEKDAY(BA491, 2) -> 5 | BG491: =IF(BF491=4, ((BC491 - BC486) / BC486)*100, "") | BH491: =IF(MONTH(BB491)<>MONTH(BB490), BB491, "") | BI491: =IF(ISNUMBER(BH491), (INDEX(BC:BC, MATCH(EOMONTH(BB491, 0), BB:BB, 1)) / BC491 - 1) * 100, "") | BJ491: 2.5698743 | BM491: 45433 | BN491: 45442 | BO491: 1435.8 | BQ491: {=INDEX($AW$466:$AW$918, ROWS($AW$466:$AW$918) - ROW() + ROW($AW$466))} -> 44778 | BR491: {=INDEX($AX$466:$AX$918, ROWS($AX$466:$AX$918) - ROW() + ROW($AX$466))} -> 44798 | BS491: {=INDEX($BO$466:$BO$918, ROWS($BO$466:$BO$918) - ROW() + ROW($BO$466))} -> 1271.3 | BU491: =((BS491-BS490)/BS490)*100 -> -0.76884049 | BV491: =WEEKDAY(BQ491, 2) -> 5 | BW491: =IF(BV491=4, ((BS491 - BS486) / BS486)*100, "") | BX491: =IF(MONTH(BR491)<>MONTH(BR490), BR491, "") | BY491: =IF(ISNUMBER(BX491), (INDEX(BS:BS, MATCH(EOMONTH(BR491, 0), BR:BR, 1)) / BS491 - 1) * 100, "") | BZ491: 3.8919705 | CC491: 45433 | CD491: 45442 | CE491: 1846.3 | CG491: {=INDEX($AW$466:$AW$918, ROWS($AW$466:$AW$918) - ROW() + ROW($AW$466))} -> 44778 | CH491: {=INDEX($AX$466:$AX$918, ROWS($AX$466:$AX$918) - ROW() + ROW($AX$466))} -> 44798 | CI491: {=INDEX($CE$466:$CE$918, ROWS($CE$466:$CE$918) - ROW() + ROW($CE$466))} -> 1622.65 | CK491: =((CI491-CI490)/CI490)*100 -> 3.3864288 | CL491: =WEEKDAY(CG491, 2) -> 5 | CM491: =IF(CL491=4, ((CI491 - CI486) / CI486)*100, "") | CN491: =IF(MONTH(CH491)<>MONTH(CH490), CH491, "") | CO491: =IF(ISNUMBER(CN491), (INDEX(CI:CI, MATCH(EOMONTH(CH491, 0), CH:CH, 1)) / CI491 - 1) * 100, "") | CP491: 3.4862503 | CS491: 45433 | CT491: 45442 | CU491: 853.2 | CW491: {=INDEX($AW$466:$AW$918, ROWS($AW$466:$AW$918) - ROW() + ROW($AW$466))} -> 44778 | CX491: {=INDEX($AX$466:$AX$918, ROWS($AX$466:$AX$918) - ROW() + ROW($AX$466))} -> 44798 | CY491: {=INDEX($CU$466:$CU$918, ROWS($CU$466:$CU$918) - ROW() + ROW($CU$466))} -> 368.7 | DA491: =((CY491-CY490)/CY490)*100 -> 0 | DB491: =WEEKDAY(CW491, 2) -> 5 | DC491: =IF(DB491=4, ((CY491 - CY486) / CY486)*100, "") | DD491: =IF(MONTH(CX491)<>MONTH(CX490), CX491, "") | DE491: =IF(ISNUMBER(DD491), (INDEX(CY:CY, MATCH(EOMONTH(CX491, 0), CX:CX, 1)) / CY491 - 1) * 100, "") | DF491: 0.054406964 | DI491: 45433 | DJ491: 45442 | DK491: 646.7 | DM491: {=INDEX($AW$466:$AW$918, ROWS($AW$466:$AW$918) - ROW() + ROW($AW$466))} -> 44778 | DN491: {=INDEX($AX$466:$AX$918, ROWS($AX$466:$AX$918) - ROW() + ROW($AX$466))} -> 44798 | DO491: {=INDEX($DK$466:$DK$918, ROWS($DK$466:$DK$918) - ROW() + ROW($DK$466))} -> 331.85 | DQ491: =((DO491-DO490)/DO490)*100 -> 0.77436988 | DR491: =WEEKDAY(DM491, 2) -> 5 | DS491: =IF(DR491=4, ((DO491 - DO486) / DO486)*100, "") | DT491: =IF(MONTH(DN491)<>MONTH(DN490), DN491, "") | DU491: =IF(ISNUMBER(DT491), (INDEX(DO:DO, MATCH(EOMONTH(DN491, 0), DN:DN, 1)) / DO491 - 1) * 100, "") | DV491: 5.2407555
A492: 45430 | B492: 45442 | C492: 153.15 | E492: {=INDEX($A$466:$A$918, ROWS($A$466:$A$918) - ROW() + ROW($A$466))} -> 44781 | F492: {=INDEX($B$466:$B$918, ROWS($B$466:$B$918) - ROW() + ROW($B$466))} -> 44798 | G492: {=INDEX($C$466:$C$918, ROWS($C$466:$C$918) - ROW() + ROW($C$466))} -> 162.55 | I492: =((G492-G491)/G491)*100 -> 1.1512134 | J492: =WEEKDAY(E492, 2) -> 1 | K492: =IF(J492=4, ((G492 - G487) / G487)*100, "") | L492: =IF(MONTH(F492)<>MONTH(F491), F492, "") | M492: =IF(ISNUMBER(L492), (INDEX(G:G, MATCH(EOMONTH(F492, 0), F:F, 1)) / G492 - 1) * 100, "") | N492: 1.0866191 | Q492: 45430 | R492: 45442 | S492: 35207.65 | U492: {=INDEX($Q$466:$Q$918, ROWS($Q$466:$Q$918) - ROW() + ROW($Q$466))} -> 44781 | V492: {=INDEX($R$466:$R$918, ROWS($R$466:$R$918) - ROW() + ROW($R$466))} -> 44798 | W492: {=INDEX($S$466:$S$918, ROWS($S$466:$S$918) - ROW() + ROW($S$466))} -> 48776.35 | Y492: =((W492-W491)/W491)*100 -> 0.83821058 | Z492: =WEEKDAY(U492, 2) -> 1 | AA492: =IF(Z492=4, ((W492 - W487) / W487)*100, "") | AB492: =IF(MONTH(V492)<>MONTH(V491), V492, "") | AC492: =IF(ISNUMBER(AB492), (INDEX(W:W, MATCH(EOMONTH(V492, 0), V:V, 1)) / W492 - 1) * 100, "") | AD492: 0.86182578 | AG492: 45430 | AH492: 45442 | AI492: 366.35 | AK492: {=INDEX($AG$466:$AG$918, ROWS($AG$466:$AG$918) - ROW() + ROW($AG$466))} -> 44781 | AL492: {=INDEX($AH$466:$AH$918, ROWS($AH$466:$AH$918) - ROW() + ROW($AH$466))} -> 44798 | AM492: {=INDEX($AI$466:$AI$918, ROWS($AI$466:$AI$918) - ROW() + ROW($AI$466))} -> 157 | AO492: =((AM492-AM491)/AM491)*100 -> 2.2801303 | AP492: =WEEKDAY(AK492, 2) -> 1 | AQ492: =IF(AP492=4, ((AM492 - AM487) / AM487)*100, "") | AR492: =IF(MONTH(AL492)<>MONTH(AL491), AL492, "") | AS492: =IF(ISNUMBER(AR492), (INDEX(AM:AM, MATCH(EOMONTH(AL492, 0), AL:AL, 1)) / AM492 - 1) * 100, "") | AT492: -0.81652257 | AW492: 45430 | AX492: 45442 | AY492: 258.7 | BA492: {=INDEX($AW$466:$AW$918, ROWS($AW$466:$AW$918) - ROW() + ROW($AW$466))} -> 44781 | BB492: {=INDEX($AX$466:$AX$918, ROWS($AX$466:$AX$918) - ROW() + ROW($AX$466))} -> 44798 | BC492: {=INDEX($AY$466:$AY$918, ROWS($AY$466:$AY$918) - ROW() + ROW($AY$466))} -> 283.35 | BE492: =((BC492-BC491)/BC491)*100 -> 3.1301183 | BF492: =WEEKDAY(BA492, 2) -> 1 | BG492: =IF(BF492=4, ((BC492 - BC487) / BC487)*100, "") | BH492: =IF(MONTH(BB492)<>MONTH(BB491), BB492, "") | BI492: =IF(ISNUMBER(BH492), (INDEX(BC:BC, MATCH(EOMONTH(BB492, 0), BB:BB, 1)) / BC492 - 1) * 100, "") | BJ492: 1.6093636 | BM492: 45430 | BN492: 45442 | BO492: 1441.15 | BQ492: {=INDEX($AW$466:$AW$918, ROWS($AW$466:$AW$918) - ROW() + ROW($AW$466))} -> 44781 | BR492: {=INDEX($AX$466:$AX$918, ROWS($AX$466:$AX$918) - ROW() + ROW($AX$466))} -> 44798 | BS492: {=INDEX($BO$466:$BO$918, ROWS($BO$466:$BO$918) - ROW() + ROW($BO$466))} -> 1276.3 | BU492: =((BS492-BS491)/BS491)*100 -> 0.3932982 | BV492: =WEEKDAY(BQ492, 2) -> 1 | BW492: =IF(BV492=4, ((BS492 - BS487) / BS487)*100, "") | BX492: =IF(MONTH(BR492)<>MONTH(BR491), BR492, "") | BY492: =IF(ISNUMBER(BX492), (INDEX(BS:BS, MATCH(EOMONTH(BR492, 0), BR:BR, 1)) / BS492 - 1) * 100, "") | BZ492: -2.4157549 | CC492: 45430 | CD492: 45442 | CE492: 1820.85 | CG492: {=INDEX($AW$466:$AW$918, ROWS($AW$466:$AW$918) - ROW() + ROW($AW$466))} -> 44781 | CH492: {=INDEX($AX$466:$AX$918, ROWS($AX$466:$AX$918) - ROW() + ROW($AX$466))} -> 44798 | CI492: {=INDEX($CE$466:$CE$918, ROWS($CE$466:$CE$918) - ROW() + ROW($CE$466))} -> 1611.25 | CK492: =((CI492-CI491)/CI491)*100 -> -0.70255446 | CL492: =WEEKDAY(CG492, 2) -> 1 | CM492: =IF(CL492=4, ((CI492 - CI487) / CI487)*100, "") | CN492: =IF(MONTH(CH492)<>MONTH(CH491), CH492, "") | CO492: =IF(ISNUMBER(CN492), (INDEX(CI:CI, MATCH(EOMONTH(CH492, 0), CH:CH, 1)) / CI492 - 1) * 100, "") | CP492: -0.80430613 | CS492: 45430 | CT492: 45442 | CU492: 853.75 | CW492: {=INDEX($AW$466:$AW$918, ROWS($AW$466:$AW$918) - ROW() + ROW($AW$466))} -> 44781 | CX492: {=INDEX($AX$466:$AX$918, ROWS($AX$466:$AX$918) - ROW() + ROW($AX$466))} -> 44798 | CY492: {=INDEX($CU$466:$CU$918, ROWS($CU$466:$CU$918) - ROW() + ROW($CU$466))} -> 371.4 | DA492: =((CY492-CY491)/CY491)*100 -> 0.73230269 | DB492: =WEEKDAY(CW492, 2) -> 1 | DC492: =IF(DB492=4, ((CY492 - CY487) / CY487)*100, "") | DD492: =IF(MONTH(CX492)<>MONTH(CX491), CX492, "") | DE492: =IF(ISNUMBER(DD492), (INDEX(CY:CY, MATCH(EOMONTH(CX492, 0), CX:CX, 1)) / CY492 - 1) * 100, "") | DF492: 0.67971724 | DI492: 45430 | DJ492: 45442 | DK492: 628.75 | DM492: {=INDEX($AW$466:$AW$918, ROWS($AW$466:$AW$918) - ROW() + ROW($AW$466))} -> 44781 | DN492: {=INDEX($AX$466:$AX$918, ROWS($AX$466:$AX$918) - ROW() + ROW($AX$466))} -> 44798 | DO492: {=INDEX($DK$466:$DK$918, ROWS($DK$466:$DK$918) - ROW() + ROW($DK$466))} -> 320.25 | DQ492: =((DO492-DO491)/DO491)*100 -> -3.4955552 | DR492: =WEEKDAY(DM492, 2) -> 1 | DS492: =IF(DR492=4, ((DO492 - DO487) / DO487)*100, "") | DT492: =IF(MONTH(DN492)<>MONTH(DN491), DN492, "") | DU492: =IF(ISNUMBER(DT492), (INDEX(DO:DO, MATCH(EOMONTH(DN492, 0), DN:DN, 1)) / DO492 - 1) * 100, "") | DV492: 0.075834176
A493: 45429 | B493: 45442 | C493: 152.15 | E493: {=INDEX($A$466:$A$918, ROWS($A$466:$A$918) - ROW() + ROW($A$466))} -> 44783 | F493: {=INDEX($B$466:$B$918, ROWS($B$466:$B$918) - ROW() + ROW($B$466))} -> 44798 | G493: {=INDEX($C$466:$C$918, ROWS($C$466:$C$918) - ROW() + ROW($C$466))} -> 176.85 | I493: =((G493-G492)/G492)*100 -> 8.7972931 | J493: =WEEKDAY(E493, 2) -> 3 | K493: =IF(J493=4, ((G493 - G488) / G488)*100, "") | L493: =IF(MONTH(F493)<>MONTH(F492), F493, "") | M493: =IF(ISNUMBER(L493), (INDEX(G:G, MATCH(EOMONTH(F493, 0), F:F, 1)) / G493 - 1) * 100, "") | N493: 8.5380835 | Q493: 45429 | R493: 45442 | S493: 35353.1 | U493: {=INDEX($Q$466:$Q$918, ROWS($Q$466:$Q$918) - ROW() + ROW($Q$466))} -> 44783 | V493: {=INDEX($R$466:$R$918, ROWS($R$466:$R$918) - ROW() + ROW($R$466))} -> 44798 | W493: {=INDEX($S$466:$S$918, ROWS($S$466:$S$918) - ROW() + ROW($S$466))} -> 48545.9 | Y493: =((W493-W492)/W492)*100 -> -0.47246258 | Z493: =WEEKDAY(U493, 2) -> 3 | AA493: =IF(Z493=4, ((W493 - W488) / W488)*100, "") | AB493: =IF(MONTH(V493)<>MONTH(V492), V493, "") | AC493: =IF(ISNUMBER(AB493), (INDEX(W:W, MATCH(EOMONTH(V493, 0), V:V, 1)) / W493 - 1) * 100, "") | AD493: -0.49293501 | AG493: 45429 | AH493: 45442 | AI493: 365.8 | AK493: {=INDEX($AG$466:$AG$918, ROWS($AG$466:$AG$918) - ROW() + ROW($AG$466))} -> 44783 | AL493: {=INDEX($AH$466:$AH$918, ROWS($AH$466:$AH$918) - ROW() + ROW($AH$466))} -> 44798 | AM493: {=INDEX($AI$466:$AI$918, ROWS($AI$466:$AI$918) - ROW() + ROW($AI$466))} -> 156.6 | AO493: =((AM493-AM492)/AM492)*100 -> -0.25477707 | AP493: =WEEKDAY(AK493, 2) -> 3 | AQ493: =IF(AP493=4, ((AM493 - AM488) / AM488)*100, "") | AR493: =IF(MONTH(AL493)<>MONTH(AL492), AL493, "") | AS493: =IF(ISNUMBER(AR493), (INDEX(AM:AM, MATCH(EOMONTH(AL493, 0), AL:AL, 1)) / AM493 - 1) * 100, "") | AT493: 5.9564165 | AW493: 45429 | AX493: 45442 | AY493: 248.95 | BA493: {=INDEX($AW$466:$AW$918, ROWS($AW$466:$AW$918) - ROW() + ROW($AW$466))} -> 44783 | BB493: {=INDEX($AX$466:$AX$918, ROWS($AX$466:$AX$918) - ROW() + ROW($AX$466))} -> 44798 | BC493: {=INDEX($AY$466:$AY$918, ROWS($AY$466:$AY$918) - ROW() + ROW($AY$466))} -> 288.9 | BE493: =((BC493-BC492)/BC492)*100 -> 1.9587083 | BF493: =WEEKDAY(BA493, 2) -> 3 | BG493: =IF(BF493=4, ((BC493 - BC488) / BC488)*100, "") | BH493: =IF(MONTH(BB493)<>MONTH(BB492), BB493, "") | BI493: =IF(ISNUMBER(BH493), (INDEX(BC:BC, MATCH(EOMONTH(BB493, 0), BB:BB, 1)) / BC493 - 1) * 100, "") | BJ493: 0 | BM493: 45429 | BN493: 45442 | BO493: 1439.15 | BQ493: {=INDEX($AW$466:$AW$918, ROWS($AW$466:$AW$918) - ROW() + ROW($AW$466))} -> 44783 | BR493: {=INDEX($AX$466:$AX$918, ROWS($AX$466:$AX$918) - ROW() + ROW($AX$466))} -> 44798 | BS493: {=INDEX($BO$466:$BO$918, ROWS($BO$466:$BO$918) - ROW() + ROW($BO$466))} -> 1276 | BU493: =((BS493-BS492)/BS492)*100 -> -0.023505445 | BV493: =WEEKDAY(BQ493, 2) -> 3 | BW493: =IF(BV493=4, ((BS493 - BS488) / BS488)*100, "") | BX493: =IF(MONTH(BR493)<>MONTH(BR492), BR493, "") | BY493: =IF(ISNUMBER(BX493), (INDEX(BS:BS, MATCH(EOMONTH(BR493, 0), BR:BR, 1)) / BS493 - 1) * 100, "") | BZ493: 0.54713427 | CC493: 45429 | CD493: 45442 | CE493: 1815.45 | CG493: {=INDEX($AW$466:$AW$918, ROWS($AW$466:$AW$918) - ROW() + ROW($AW$466))} -> 44783 | CH493: {=INDEX($AX$466:$AX$918, ROWS($AX$466:$AX$918) - ROW() + ROW($AX$466))} -> 44798 | CI493: {=INDEX($CE$466:$CE$918, ROWS($CE$466:$CE$918) - ROW() + ROW($CE$466))} -> 1562.9 | CK493: =((CI493-CI492)/CI492)*100 -> -3.0007758 | CL493: =WEEKDAY(CG493, 2) -> 3 | CM493: =IF(CL493=4, ((CI493 - CI488) / CI488)*100, "") | CN493: =IF(MONTH(CH493)<>MONTH(CH492), CH493, "") | CO493: =IF(ISNUMBER(CN493), (INDEX(CI:CI, MATCH(EOMONTH(CH493, 0), CH:CH, 1)) / CI493 - 1) * 100, "") | CP493: -2.844134 | CS493: 45429 | CT493: 45442 | CU493: 852.1 | CW493: {=INDEX($AW$466:$AW$918, ROWS($AW$466:$AW$918) - ROW() + ROW($AW$466))} -> 44783 | CX493: {=INDEX($AX$466:$AX$918, ROWS($AX$466:$AX$918) - ROW() + ROW($AX$466))} -> 44798 | CY493: {=INDEX($CU$466:$CU$918, ROWS($CU$466:$CU$918) - ROW() + ROW($CU$466))} -> 370.2 | DA493: =((CY493-CY492)/CY492)*100 -> -0.32310178 | DB493: =WEEKDAY(CW493, 2) -> 3 | DC493: =IF(DB493=4, ((CY493 - CY488) / CY488)*100, "") | DD493: =IF(MONTH(CX493)<>MONTH(CX492), CX493, "") | DE493: =IF(ISNUMBER(DD493), (INDEX(CY:CY, MATCH(EOMONTH(CX493, 0), CX:CX, 1)) / CY493 - 1) * 100, "") | DF493: -0.48609236 | DI493: 45429 | DJ493: 45442 | DK493: 629.85 | DM493: {=INDEX($AW$466:$AW$918, ROWS($AW$466:$AW$918) - ROW() + ROW($AW$466))} -> 44783 | DN493: {=INDEX($AX$466:$AX$918, ROWS($AX$466:$AX$918) - ROW() + ROW($AX$466))} -> 44798 | DO493: {=INDEX($DK$466:$DK$918, ROWS($DK$466:$DK$918) - ROW() + ROW($DK$466))} -> 323.85 | DQ493: =((DO493-DO492)/DO492)*100 -> 1.1241218 | DR493: =WEEKDAY(DM493, 2) -> 3 | DS493: =IF(DR493=4, ((DO493 - DO488) / DO488)*100, "") | DT493: =IF(MONTH(DN493)<>MONTH(DN492), DN493, "") | DU493: =IF(ISNUMBER(DT493), (INDEX(DO:DO, MATCH(EOMONTH(DN493, 0), DN:DN, 1)) / DO493 - 1) * 100, "") | DV493: -5.5822177
A494: 45428 | B494: 45442 | C494: 154.75 | E494: {=INDEX($A$466:$A$918, ROWS($A$466:$A$918) - ROW() + ROW($A$466))} -> 44784 | F494: {=INDEX($B$466:$B$918, ROWS($B$466:$B$918) - ROW() + ROW($B$466))} -> 44798 | G494: {=INDEX($C$466:$C$918, ROWS($C$466:$C$918) - ROW() + ROW($C$466))} -> 175.5 | I494: =((G494-G493)/G493)*100 -> -0.76335878 | J494: =WEEKDAY(E494, 2) -> 4 | K494: =IF(J494=4, ((G494 - G489) / G489)*100, "") -> 8.1330869 | L494: =IF(MONTH(F494)<>MONTH(F493), F494, "") | M494: =IF(ISNUMBER(L494), (INDEX(G:G, MATCH(EOMONTH(F494, 0), F:F, 1)) / G494 - 1) * 100, "") | N494: -0.87719298 | O494: 7.7514611 | Q494: 45428 | R494: 45442 | S494: 35458.15 | U494: {=INDEX($Q$466:$Q$918, ROWS($Q$466:$Q$918) - ROW() + ROW($Q$466))} -> 44784 | V494: {=INDEX($R$466:$R$918, ROWS($R$466:$R$918) - ROW() + ROW($R$466))} -> 44798 | W494: {=INDEX($S$466:$S$918, ROWS($S$466:$S$918) - ROW() + ROW($S$466))} -> 49158.9 | Y494: =((W494-W493)/W493)*100 -> 1.2627225 | Z494: =WEEKDAY(U494, 2) -> 4 | AA494: =IF(Z494=4, ((W494 - W489) / W489)*100, "") -> 1.9605444 | AB494: =IF(MONTH(V494)<>MONTH(V493), V494, "") | AC494: =IF(ISNUMBER(AB494), (INDEX(W:W, MATCH(EOMONTH(V494, 0), V:V, 1)) / W494 - 1) * 100, "") | AD494: 1.2889719 | AE494: 2.069033 | AG494: 45428 | AH494: 45442 | AI494: 362.15 | AK494: {=INDEX($AG$466:$AG$918, ROWS($AG$466:$AG$918) - ROW() + ROW($AG$466))} -> 44784 | AL494: {=INDEX($AH$466:$AH$918, ROWS($AH$466:$AH$918) - ROW() + ROW($AH$466))} -> 44798 | AM494: {=INDEX($AI$466:$AI$918, ROWS($AI$466:$AI$918) - ROW() + ROW($AI$466))} -> 154.1 | AO494: =((AM494-AM493)/AM493)*100 -> -1.596424 | AP494: =WEEKDAY(AK494, 2) -> 4 | AQ494: =IF(AP494=4, ((AM494 - AM489) / AM489)*100, "") -> -1.9096117 | AR494: =IF(MONTH(AL494)<>MONTH(AL493), AL494, "") | AS494: =IF(ISNUMBER(AR494), (INDEX(AM:AM, MATCH(EOMONTH(AL494, 0), AL:AL, 1)) / AM494 - 1) * 100, "") | AT494: 3.1078611 | AU494: 10.37182 | AW494: 45428 | AX494: 45442 | AY494: 239.15 | BA494: {=INDEX($AW$466:$AW$918, ROWS($AW$466:$AW$918) - ROW() + ROW($AW$466))} -> 44784 | BB494: {=INDEX($AX$466:$AX$918, ROWS($AX$466:$AX$918) - ROW() + ROW($AX$466))} -> 44798 | BC494: {=INDEX($AY$466:$AY$918, ROWS($AY$466:$AY$918) - ROW() + ROW($AY$466))} -> 288.85 | BE494: =((BC494-BC493)/BC493)*100 -> -0.017307027 | BF494: =WEEKDAY(BA494, 2) -> 4 | BG494: =IF(BF494=4, ((BC494 - BC489) / BC489)*100, "") -> 4.4854404 | BH494: =IF(MONTH(BB494)<>MONTH(BB493), BB494, "") | BI494: =IF(ISNUMBER(BH494), (INDEX(BC:BC, MATCH(EOMONTH(BB494, 0), BB:BB, 1)) / BC494 - 1) * 100, "") | BJ494: -0.14398848 | BK494: 7.2768289 | BM494: 45428 | BN494: 45442 | BO494: 1455.25 | BQ494: {=INDEX($AW$466:$AW$918, ROWS($AW$466:$AW$918) - ROW() + ROW($AW$466))} -> 44784 | BR494: {=INDEX($AX$466:$AX$918, ROWS($AX$466:$AX$918) - ROW() + ROW($AX$466))} -> 44798 | BS494: {=INDEX($BO$466:$BO$918, ROWS($BO$466:$BO$918) - ROW() + ROW($BO$466))} -> 1267.05 | BU494: =((BS494-BS493)/BS493)*100 -> -0.70141066 | BV494: =WEEKDAY(BQ494, 2) -> 4 | BW494: =IF(BV494=4, ((BS494 - BS489) / BS489)*100, "") -> -1.7066832 | BX494: =IF(MONTH(BR494)<>MONTH(BR493), BR494, "") | BY494: =IF(ISNUMBER(BX494), (INDEX(BS:BS, MATCH(EOMONTH(BR494, 0), BR:BR, 1)) / BS494 - 1) * 100, "") | BZ494: 4.058876 | CA494: 5.0049509 | CC494: 45428 | CD494: 45442 | CE494: 1795.35 | CG494: {=INDEX($AW$466:$AW$918, ROWS($AW$466:$AW$918) - ROW() + ROW($AW$466))} -> 44784 | CH494: {=INDEX($AX$466:$AX$918, ROWS($AX$466:$AX$918) - ROW() + ROW($AX$466))} -> 44798 | CI494: {=INDEX($CE$466:$CE$918, ROWS($CE$466:$CE$918) - ROW() + ROW($CE$466))} -> 1570.3 | CK494: =((CI494-CI493)/CI493)*100 -> 0.47347879 | CL494: =WEEKDAY(CG494, 2) -> 4 | CM494: =IF(CL494=4, ((CI494 - CI489) / CI489)*100, "") -> 0.98067586 | CN494: =IF(MONTH(CH494)<>MONTH(CH493), CH494, "") | CO494: =IF(ISNUMBER(CN494), (INDEX(CI:CI, MATCH(EOMONTH(CH494, 0), CH:CH, 1)) / CI494 - 1) * 100, "") | CP494: 0.35629454 | CQ494: 1.0308279 | CS494: 45428 | CT494: 45442 | CU494: 846.75 | CW494: {=INDEX($AW$466:$AW$918, ROWS($AW$466:$AW$918) - ROW() + ROW($AW$466))} -> 44784 | CX494: {=INDEX($AX$466:$AX$918, ROWS($AX$466:$AX$918) - ROW() + ROW($AX$466))} -> 44798 | CY494: {=INDEX($CU$466:$CU$918, ROWS($CU$466:$CU$918) - ROW() + ROW($CU$466))} -> 374.1 | DA494: =((CY494-CY493)/CY493)*100 -> 1.0534846 | DB494: =WEEKDAY(CW494, 2) -> 4 | DC494: =IF(DB494=4, ((CY494 - CY489) / CY489)*100, "") -> 0 | DD494: =IF(MONTH(CX494)<>MONTH(CX493), CX494, "") | DE494: =IF(ISNUMBER(DD494), (INDEX(CY:CY, MATCH(EOMONTH(CX494, 0), CX:CX, 1)) / CY494 - 1) * 100, "") | DF494: 1.0990502 | DG494: 0.094035465 | DI494: 45428 | DJ494: 45442 | DK494: 621.35 | DM494: {=INDEX($AW$466:$AW$918, ROWS($AW$466:$AW$918) - ROW() + ROW($AW$466))} -> 44784 | DN494: {=INDEX($AX$466:$AX$918, ROWS($AX$466:$AX$918) - ROW() + ROW($AX$466))} -> 44798 | DO494: {=INDEX($DK$466:$DK$918, ROWS($DK$466:$DK$918) - ROW() + ROW($DK$466))} -> 323.55 | DQ494: =((DO494-DO493)/DO493)*100 -> -0.092635479 | DR494: =WEEKDAY(DM494, 2) -> 4 | DS494: =IF(DR494=4, ((DO494 - DO489) / DO489)*100, "") -> -1.7312073 | DT494: =IF(MONTH(DN494)<>MONTH(DN493), DN494, "") | DU494: =IF(ISNUMBER(DT494), (INDEX(DO:DO, MATCH(EOMONTH(DN494, 0), DN:DN, 1)) / DO494 - 1) * 100, "") | DV494: 0.56179775 | DW494: -0.73937153
A495: 45427 | B495: 45442 | C495: 153.4 | E495: {=INDEX($A$466:$A$918, ROWS($A$466:$A$918) - ROW() + ROW($A$466))} -> 44785 | F495: {=INDEX($B$466:$B$918, ROWS($B$466:$B$918) - ROW() + ROW($B$466))} -> 44798 | G495: {=INDEX($C$466:$C$918, ROWS($C$466:$C$918) - ROW() + ROW($C$466))} -> 177.25 | I495: =((G495-G494)/G494)*100 -> 0.997151 | J495: =WEEKDAY(E495, 2) -> 5 | K495: =IF(J495=4, ((G495 - G490) / G490)*100, "") | L495: =IF(MONTH(F495)<>MONTH(F494), F495, "") | M495: =IF(ISNUMBER(L495), (INDEX(G:G, MATCH(EOMONTH(F495, 0), F:F, 1)) / G495 - 1) * 100, "") | N495: 1.0562375 | Q495: 45427 | R495: 45442 | S495: 34951.75 | U495: {=INDEX($Q$466:$Q$918, ROWS($Q$466:$Q$918) - ROW() + ROW($Q$466))} -> 44785 | V495: {=INDEX($R$466:$R$918, ROWS($R$466:$R$918) - ROW() + ROW($R$466))} -> 44798 | W495: {=INDEX($S$466:$S$918, ROWS($S$466:$S$918) - ROW() + ROW($S$466))} -> 49165.5 | Y495: =((W495-W494)/W494)*100 -> 0.01342585 | Z495: =WEEKDAY(U495, 2) -> 5 | AA495: =IF(Z495=4, ((W495 - W490) / W490)*100, "") | AB495: =IF(MONTH(V495)<>MONTH(V494), V495, "") | AC495: =IF(ISNUMBER(AB495), (INDEX(W:W, MATCH(EOMONTH(V495, 0), V:V, 1)) / W495 - 1) * 100, "") | AD495: 0.25759471 | AG495: 45427 | AH495: 45442 | AI495: 362.4 | AK495: {=INDEX($AG$466:$AG$918, ROWS($AG$466:$AG$918) - ROW() + ROW($AG$466))} -> 44785 | AL495: {=INDEX($AH$466:$AH$918, ROWS($AH$466:$AH$918) - ROW() + ROW($AH$466))} -> 44798 | AM495: {=INDEX($AI$466:$AI$918, ROWS($AI$466:$AI$918) - ROW() + ROW($AI$466))} -> 158.95 | AO495: =((AM495-AM494)/AM494)*100 -> 3.1473069 | AP495: =WEEKDAY(AK495, 2) -> 5 | AQ495: =IF(AP495=4, ((AM495 - AM490) / AM490)*100, "") | AR495: =IF(MONTH(AL495)<>MONTH(AL494), AL495, "") | AS495: =IF(ISNUMBER(AR495), (INDEX(AM:AM, MATCH(EOMONTH(AL495, 0), AL:AL, 1)) / AM495 - 1) * 100, "") | AT495: -0.66489362 | AW495: 45427 | AX495: 45442 | AY495: 234 | BA495: {=INDEX($AW$466:$AW$918, ROWS($AW$466:$AW$918) - ROW() + ROW($AW$466))} -> 44785 | BB495: {=INDEX($AX$466:$AX$918, ROWS($AX$466:$AX$918) - ROW() + ROW($AX$466))} -> 44798 | BC495: {=INDEX($AY$466:$AY$918, ROWS($AY$466:$AY$918) - ROW() + ROW($AY$466))} -> 292.05 | BE495: =((BC495-BC494)/BC494)*100 -> 1.1078414 | BF495: =WEEKDAY(BA495, 2) -> 5 | BG495: =IF(BF495=4, ((BC495 - BC490) / BC490)*100, "") | BH495: =IF(MONTH(BB495)<>MONTH(BB494), BB495, "") | BI495: =IF(ISNUMBER(BH495), (INDEX(BC:BC, MATCH(EOMONTH(BB495, 0), BB:BB, 1)) / BC495 - 1) * 100, "") | BJ495: 0.76303773 | BM495: 45427 | BN495: 45442 | BO495: 1436.65 | BQ495: {=INDEX($AW$466:$AW$918, ROWS($AW$466:$AW$918) - ROW() + ROW($AW$466))} -> 44785 | BR495: {=INDEX($AX$466:$AX$918, ROWS($AX$466:$AX$918) - ROW() + ROW($AX$466))} -> 44798 | BS495: {=INDEX($BO$466:$BO$918, ROWS($BO$466:$BO$918) - ROW() + ROW($BO$466))} -> 1288.55 | BU495: =((BS495-BS494)/BS494)*100 -> 1.6968549 | BV495: =WEEKDAY(BQ495, 2) -> 5 | BW495: =IF(BV495=4, ((BS495 - BS490) / BS490)*100, "") | BX495: =IF(MONTH(BR495)<>MONTH(BR494), BR495, "") | BY495: =IF(ISNUMBER(BX495), (INDEX(BS:BS, MATCH(EOMONTH(BR495, 0), BR:BR, 1)) / BS495 - 1) * 100, "") | BZ495: -1.731676 | CC495: 45427 | CD495: 45442 | CE495: 1764.8 | CG495: {=INDEX($AW$466:$AW$918, ROWS($AW$466:$AW$918) - ROW() + ROW($AW$466))} -> 44785 | CH495: {=INDEX($AX$466:$AX$918, ROWS($AX$466:$AX$918) - ROW() + ROW($AX$466))} -> 44798 | CI495: {=INDEX($CE$466:$CE$918, ROWS($CE$466:$CE$918) - ROW() + ROW($CE$466))} -> 1565.1 | CK495: =((CI495-CI494)/CI494)*100 -> -0.33114691 | CL495: =WEEKDAY(CG495, 2) -> 5 | CM495: =IF(CL495=4, ((CI495 - CI490) / CI490)*100, "") | CN495: =IF(MONTH(CH495)<>MONTH(CH494), CH495, "") | CO495: =IF(ISNUMBER(CN495), (INDEX(CI:CI, MATCH(EOMONTH(CH495, 0), CH:CH, 1)) / CI495 - 1) * 100, "") | CP495: -0.22069407 | CS495: 45427 | CT495: 45442 | CU495: 829.3 | CW495: {=INDEX($AW$466:$AW$918, ROWS($AW$466:$AW$918) - ROW() + ROW($AW$466))} -> 44785 | CX495: {=INDEX($AX$466:$AX$918, ROWS($AX$466:$AX$918) - ROW() + ROW($AX$466))} -> 44798 | CY495: {=INDEX($CU$466:$CU$918, ROWS($CU$466:$CU$918) - ROW() + ROW($CU$466))} -> 373.6 | DA495: =((CY495-CY494)/CY494)*100 -> -0.1336541 | DB495: =WEEKDAY(CW495, 2) -> 5 | DC495: =IF(DB495=4, ((CY495 - CY490) / CY490)*100, "") | DD495: =IF(MONTH(CX495)<>MONTH(CX494), CX495, "") | DE495: =IF(ISNUMBER(DD495), (INDEX(CY:CY, MATCH(EOMONTH(CX495, 0), CX:CX, 1)) / CY495 - 1) * 100, "") | DF495: 0.093947121 | DI495: 45427 | DJ495: 45442 | DK495: 628.35 | DM495: {=INDEX($AW$466:$AW$918, ROWS($AW$466:$AW$918) - ROW() + ROW($AW$466))} -> 44785 | DN495: {=INDEX($AX$466:$AX$918, ROWS($AX$466:$AX$918) - ROW() + ROW($AX$466))} -> 44798 | DO495: {=INDEX($DK$466:$DK$918, ROWS($DK$466:$DK$918) - ROW() + ROW($DK$466))} -> 328.4 | DQ495: =((DO495-DO494)/DO494)*100 -> 1.4989955 | DR495: =WEEKDAY(DM495, 2) -> 5 | DS495: =IF(DR495=4, ((DO495 - DO490) / DO490)*100, "") | DT495: =IF(MONTH(DN495)<>MONTH(DN494), DN495, "") | DU495: =IF(ISNUMBER(DT495), (INDEX(DO:DO, MATCH(EOMONTH(DN495, 0), DN:DN, 1)) / DO495 - 1) * 100, "") | DV495: 1.2769354
A496: 45426 | B496: 45442 | C496: 155.15 | E496: {=INDEX($A$466:$A$918, ROWS($A$466:$A$918) - ROW() + ROW($A$466))} -> 44789 | F496: {=INDEX($B$466:$B$918, ROWS($B$466:$B$918) - ROW() + ROW($B$466))} -> 44798 | G496: {=INDEX($C$466:$C$918, ROWS($C$466:$C$918) - ROW() + ROW($C$466))} -> 179.15 | I496: =((G496-G495)/G495)*100 -> 1.0719323 | J496: =WEEKDAY(E496, 2) -> 2 | K496: =IF(J496=4, ((G496 - G491) / G491)*100, "") | L496: =IF(MONTH(F496)<>MONTH(F495), F496, "") | M496: =IF(ISNUMBER(L496), (INDEX(G:G, MATCH(EOMONTH(F496, 0), F:F, 1)) / G496 - 1) * 100, "") | N496: 0.70621469 | Q496: 45426 | R496: 45442 | S496: 35212.45 | U496: {=INDEX($Q$466:$Q$918, ROWS($Q$466:$Q$918) - ROW() + ROW($Q$466))} -> 44789 | V496: {=INDEX($R$466:$R$918, ROWS($R$466:$R$918) - ROW() + ROW($R$466))} -> 44798 | W496: {=INDEX($S$466:$S$918, ROWS($S$466:$S$918) - ROW() + ROW($S$466))} -> 49746 | Y496: =((W496-W495)/W495)*100 -> 1.180706 | Z496: =WEEKDAY(U496, 2) -> 2 | AA496: =IF(Z496=4, ((W496 - W491) / W491)*100, "") | AB496: =IF(MONTH(V496)<>MONTH(V495), V496, "") | AC496: =IF(ISNUMBER(AB496), (INDEX(W:W, MATCH(EOMONTH(V496, 0), V:V, 1)) / W496 - 1) * 100, "") | AD496: 1.102013 | AG496: 45426 | AH496: 45442 | AI496: 357.75 | AK496: {=INDEX($AG$466:$AG$918, ROWS($AG$466:$AG$918) - ROW() + ROW($AG$466))} -> 44789 | AL496: {=INDEX($AH$466:$AH$918, ROWS($AH$466:$AH$918) - ROW() + ROW($AH$466))} -> 44798 | AM496: {=INDEX($AI$466:$AI$918, ROWS($AI$466:$AI$918) - ROW() + ROW($AI$466))} -> 159.4 | AO496: =((AM496-AM495)/AM495)*100 -> 0.2831079 | AP496: =WEEKDAY(AK496, 2) -> 2 | AQ496: =IF(AP496=4, ((AM496 - AM491) / AM491)*100, "") | AR496: =IF(MONTH(AL496)<>MONTH(AL495), AL496, "") | AS496: =IF(ISNUMBER(AR496), (INDEX(AM:AM, MATCH(EOMONTH(AL496, 0), AL:AL, 1)) / AM496 - 1) * 100, "") | AT496: -5.577867 | AW496: 45426 | AX496: 45442 | AY496: 232.25 | BA496: {=INDEX($AW$466:$AW$918, ROWS($AW$466:$AW$918) - ROW() + ROW($AW$466))} -> 44789 | BB496: {=INDEX($AX$466:$AX$918, ROWS($AX$466:$AX$918) - ROW() + ROW($AX$466))} -> 44798 | BC496: {=INDEX($AY$466:$AY$918, ROWS($AY$466:$AY$918) - ROW() + ROW($AY$466))} -> 294.3 | BE496: =((BC496-BC495)/BC495)*100 -> 0.77041602 | BF496: =WEEKDAY(BA496, 2) -> 2 | BG496: =IF(BF496=4, ((BC496 - BC491) / BC491)*100, "") | BH496: =IF(MONTH(BB496)<>MONTH(BB495), BB496, "") | BI496: =IF(ISNUMBER(BH496), (INDEX(BC:BC, MATCH(EOMONTH(BB496, 0), BB:BB, 1)) / BC496 - 1) * 100, "") | BJ496: 2.5341363 | BM496: 45426 | BN496: 45442 | BO496: 1437.55 | BQ496: {=INDEX($AW$466:$AW$918, ROWS($AW$466:$AW$918) - ROW() + ROW($AW$466))} -> 44789 | BR496: {=INDEX($AX$466:$AX$918, ROWS($AX$466:$AX$918) - ROW() + ROW($AX$466))} -> 44798 | BS496: {=INDEX($BO$466:$BO$918, ROWS($BO$466:$BO$918) - ROW() + ROW($BO$466))} -> 1315.15 | BU496: =((BS496-BS495)/BS495)*100 -> 2.0643359 | BV496: =WEEKDAY(BQ496, 2) -> 2 | BW496: =IF(BV496=4, ((BS496 - BS491) / BS491)*100, "") | BX496: =IF(MONTH(BR496)<>MONTH(BR495), BR496, "") | BY496: =IF(ISNUMBER(BX496), (INDEX(BS:BS, MATCH(EOMONTH(BR496, 0), BR:BR, 1)) / BS496 - 1) * 100, "") | BZ496: 0.68917386 | CC496: 45426 | CD496: 45442 | CE496: 1763.55 | CG496: {=INDEX($AW$466:$AW$918, ROWS($AW$466:$AW$918) - ROW() + ROW($AW$466))} -> 44789 | CH496: {=INDEX($AX$466:$AX$918, ROWS($AX$466:$AX$918) - ROW() + ROW($AX$466))} -> 44798 | CI496: {=INDEX($CE$466:$CE$918, ROWS($CE$466:$CE$918) - ROW() + ROW($CE$466))} -> 1591.15 | CK496: =((CI496-CI495)/CI495)*100 -> 1.6644304 | CL496: =WEEKDAY(CG496, 2) -> 2 | CM496: =IF(CL496=4, ((CI496 - CI491) / CI491)*100, "") | CN496: =IF(MONTH(CH496)<>MONTH(CH495), CH496, "") | CO496: =IF(ISNUMBER(CN496), (INDEX(CI:CI, MATCH(EOMONTH(CH496, 0), CH:CH, 1)) / CI496 - 1) * 100, "") | CP496: 1.593153 | CS496: 45426 | CT496: 45442 | CU496: 844.1 | CW496: {=INDEX($AW$466:$AW$918, ROWS($AW$466:$AW$918) - ROW() + ROW($AW$466))} -> 44789 | CX496: {=INDEX($AX$466:$AX$918, ROWS($AX$466:$AX$918) - ROW() + ROW($AX$466))} -> 44798 | CY496: {=INDEX($CU$466:$CU$918, ROWS($CU$466:$CU$918) - ROW() + ROW($CU$466))} -> 379.75 | DA496: =((CY496-CY495)/CY495)*100 -> 1.6461456 | DB496: =WEEKDAY(CW496, 2) -> 2 | DC496: =IF(DB496=4, ((CY496 - CY491) / CY491)*100, "") | DD496: =IF(MONTH(CX496)<>MONTH(CX495), CX496, "") | DE496: =IF(ISNUMBER(DD496), (INDEX(CY:CY, MATCH(EOMONTH(CX496, 0), CX:CX, 1)) / CY496 - 1) * 100, "") | DF496: 1.6760526 | DI496: 45426 | DJ496: 45442 | DK496: 609.55 | DM496: {=INDEX($AW$466:$AW$918, ROWS($AW$466:$AW$918) - ROW() + ROW($AW$466))} -> 44789 | DN496: {=INDEX($AX$466:$AX$918, ROWS($AX$466:$AX$918) - ROW() + ROW($AX$466))} -> 44798 | DO496: {=INDEX($DK$466:$DK$918, ROWS($DK$466:$DK$918) - ROW() + ROW($DK$466))} -> 341.1 | DQ496: =((DO496-DO495)/DO495)*100 -> 3.8672351 | DR496: =WEEKDAY(DM496, 2) -> 2 | DS496: =IF(DR496=4, ((DO496 - DO491) / DO491)*100, "") | DT496: =IF(MONTH(DN496)<>MONTH(DN495), DN496, "") | DU496: =IF(ISNUMBER(DT496), (INDEX(DO:DO, MATCH(EOMONTH(DN496, 0), DN:DN, 1)) / DO496 - 1) * 100, "") | DV496: 0.18387182
A497: 45425 | B497: 45442 | C497: 150.7 | E497: {=INDEX($A$466:$A$918, ROWS($A$466:$A$918) - ROW() + ROW($A$466))} -> 44790 | F497: {=INDEX($B$466:$B$918, ROWS($B$466:$B$918) - ROW() + ROW($B$466))} -> 44798 | G497: {=INDEX($C$466:$C$918, ROWS($C$466:$C$918) - ROW() + ROW($C$466))} -> 178.5 | I497: =((G497-G496)/G496)*100 -> -0.36282445 | J497: =WEEKDAY(E497, 2) -> 3 | K497: =IF(J497=4, ((G497 - G492) / G492)*100, "") | L497: =IF(MONTH(F497)<>MONTH(F496), F497, "") | M497: =IF(ISNUMBER(L497), (INDEX(G:G, MATCH(EOMONTH(F497, 0), F:F, 1)) / G497 - 1) * 100, "") | N497: -0.28050491 | Q497: 45425 | R497: 45442 | S497: 35104.2 | U497: {=INDEX($Q$466:$Q$918, ROWS($Q$466:$Q$918) - ROW() + ROW($Q$466))} -> 44790 | V497: {=INDEX($R$466:$R$918, ROWS($R$466:$R$918) - ROW() + ROW($R$466))} -> 44798 | W497: {=INDEX($S$466:$S$918, ROWS($S$466:$S$918) - ROW() + ROW($S$466))} -> 49690 | Y497: =((W497-W496)/W496)*100 -> -0.11257187 | Z497: =WEEKDAY(U497, 2) -> 3 | AA497: =IF(Z497=4, ((W497 - W492) / W492)*100, "") | AB497: =IF(MONTH(V497)<>MONTH(V496), V497, "") | AC497: =IF(ISNUMBER(AB497), (INDEX(W:W, MATCH(EOMONTH(V497, 0), V:V, 1)) / W497 - 1) * 100, "") | AD497: -0.37772613 | AG497: 45425 | AH497: 45442 | AI497: 352.85 | AK497: {=INDEX($AG$466:$AG$918, ROWS($AG$466:$AG$918) - ROW() + ROW($AG$466))} -> 44790 | AL497: {=INDEX($AH$466:$AH$918, ROWS($AH$466:$AH$918) - ROW() + ROW($AH$466))} -> 44798 | AM497: {=INDEX($AI$466:$AI$918, ROWS($AI$466:$AI$918) - ROW() + ROW($AI$466))} -> 161.7 | AO497: =((AM497-AM496)/AM496)*100 -> 1.4429109 | AP497: =WEEKDAY(AK497, 2) -> 3 | AQ497: =IF(AP497=4, ((AM497 - AM492) / AM492)*100, "") | AR497: =IF(MONTH(AL497)<>MONTH(AL496), AL497, "") | AS497: =IF(ISNUMBER(AR497), (INDEX(AM:AM, MATCH(EOMONTH(AL497, 0), AL:AL, 1)) / AM497 - 1) * 100, "") | AT497: -0.14177694 | AW497: 45425 | AX497: 45442 | AY497: 226 | BA497: {=INDEX($AW$466:$AW$918, ROWS($AW$466:$AW$918) - ROW() + ROW($AW$466))} -> 44790 | BB497: {=INDEX($AX$466:$AX$918, ROWS($AX$466:$AX$918) - ROW() + ROW($AX$466))} -> 44798 | BC497: {=INDEX($AY$466:$AY$918, ROWS($AY$466:$AY$918) - ROW() + ROW($AY$466))} -> 292.6 | BE497: =((BC497-BC496)/BC496)*100 -> -0.57764186 | BF497: =WEEKDAY(BA497, 2) -> 3 | BG497: =IF(BF497=4, ((BC497 - BC492) / BC492)*100, "") | BH497: =IF(MONTH(BB497)<>MONTH(BB496), BB497, "") | BI497: =IF(ISNUMBER(BH497), (INDEX(BC:BC, MATCH(EOMONTH(BB497, 0), BB:BB, 1)) / BC497 - 1) * 100, "") | BJ497: 0.50011631 | BM497: 45425 | BN497: 45442 | BO497: 1434.1 | BQ497: {=INDEX($AW$466:$AW$918, ROWS($AW$466:$AW$918) - ROW() + ROW($AW$466))} -> 44790 | BR497: {=INDEX($AX$466:$AX$918, ROWS($AX$466:$AX$918) - ROW() + ROW($AX$466))} -> 44798 | BS497: {=INDEX($BO$466:$BO$918, ROWS($BO$466:$BO$918) - ROW() + ROW($BO$466))} -> 1310.15 | BU497: =((BS497-BS496)/BS496)*100 -> -0.38018477 | BV497: =WEEKDAY(BQ497, 2) -> 3 | BW497: =IF(BV497=4, ((BS497 - BS492) / BS492)*100, "") | BX497: =IF(MONTH(BR497)<>MONTH(BR496), BR497, "") | BY497: =IF(ISNUMBER(BX497), (INDEX(BS:BS, MATCH(EOMONTH(BR497, 0), BR:BR, 1)) / BS497 - 1) * 100, "") | BZ497: -0.91838503 | CC497: 45425 | CD497: 45442 | CE497: 1747.75 | CG497: {=INDEX($AW$466:$AW$918, ROWS($AW$466:$AW$918) - ROW() + ROW($AW$466))} -> 44790 | CH497: {=INDEX($AX$466:$AX$918, ROWS($AX$466:$AX$918) - ROW() + ROW($AX$466))} -> 44798 | CI497: {=INDEX($CE$466:$CE$918, ROWS($CE$466:$CE$918) - ROW() + ROW($CE$466))} -> 1596.35 | CK497: =((CI497-CI496)/CI496)*100 -> 0.32680765 | CL497: =WEEKDAY(CG497, 2) -> 3 | CM497: =IF(CL497=4, ((CI497 - CI492) / CI492)*100, "") | CN497: =IF(MONTH(CH497)<>MONTH(CH496), CH497, "") | CO497: =IF(ISNUMBER(CN497), (INDEX(CI:CI, MATCH(EOMONTH(CH497, 0), CH:CH, 1)) / CI497 - 1) * 100, "") | CP497: 0.67522797 | CS497: 45425 | CT497: 45442 | CU497: 844.1 | CW497: {=INDEX($AW$466:$AW$918, ROWS($AW$466:$AW$918) - ROW() + ROW($AW$466))} -> 44790 | CX497: {=INDEX($AX$466:$AX$918, ROWS($AX$466:$AX$918) - ROW() + ROW($AX$466))} -> 44798 | CY497: {=INDEX($CU$466:$CU$918, ROWS($CU$466:$CU$918) - ROW() + ROW($CU$466))} -> 380.9 | DA497: =((CY497-CY496)/CY496)*100 -> 0.30283081 | DB497: =WEEKDAY(CW497, 2) -> 3 | DC497: =IF(DB497=4, ((CY497 - CY492) / CY492)*100, "") | DD497: =IF(MONTH(CX497)<>MONTH(CX496), CX497, "") | DE497: =IF(ISNUMBER(DD497), (INDEX(CY:CY, MATCH(EOMONTH(CX497, 0), CX:CX, 1)) / CY497 - 1) * 100, "") | DF497: 0.31649743 | DI497: 45425 | DJ497: 45442 | DK497: 610.3 | DM497: {=INDEX($AW$466:$AW$918, ROWS($AW$466:$AW$918) - ROW() + ROW($AW$466))} -> 44790 | DN497: {=INDEX($AX$466:$AX$918, ROWS($AX$466:$AX$918) - ROW() + ROW($AX$466))} -> 44798 | DO497: {=INDEX($DK$466:$DK$918, ROWS($DK$466:$DK$918) - ROW() + ROW($DK$466))} -> 347.55 | DQ497: =((DO497-DO496)/DO496)*100 -> 1.8909411 | DR497: =WEEKDAY(DM497, 2) -> 3 | DS497: =IF(DR497=4, ((DO497 - DO492) / DO492)*100, "") | DT497: =IF(MONTH(DN497)<>MONTH(DN496), DN497, "") | DU497: =IF(ISNUMBER(DT497), (INDEX(DO:DO, MATCH(EOMONTH(DN497, 0), DN:DN, 1)) / DO497 - 1) * 100, "") | DV497: -0.15731515
